Workbook

Sheet Control_Panel
A1: Control Panel
A2: Application entry point. Button cells identify macro actions after VBA import.
A4: Action | B4: Macro / Target | C4: Status / Notes
A5: Refresh All | B5: RefreshAll | C5: Rebuilds register, buildup, cash flow, escalation, contingency, dashboard and QA
A6: Build Cost Register | B6: BuildCostRegister | C6: Header-based macro; reads input sheets only
A7: Run QA | B7: RunQA | C7: Writes PASS/FAIL to QA_Checks
A8: Run Monte Carlo | B8: RunMonteCarlo | C8: Populates MonteCarlo_Results only; does not touch charts
A9: Load Demo Project | B9: LoadDemoProject | C9: Reloads 40 M€ demo dataset
A10: Reset Demo Data | B10: ResetDemoData | C10: Clears demo input/output areas
A11: Last Refresh | C11: 2026-06-03 14:03:33
A12: Last QA Status | C12: =NOW()
A13: Cost Items | C13: =MAX(0,COUNTA(Cost_Register!$C$5:$C$500))
A14: Base Cost EUR | C14: =SUM(Cost_Register!$P$5:$P$500)
A15: Total Project Cost EUR | C15: ='Estimate_Summary'!B18
A17: Key sheet | B17: Purpose
A18: Project_Setup | B18: Project metadata and defaults
A19: Cost_Register | B19: Single source of truth
A20: Estimate_Summary | B20: Executive output
A21: Dashboard | B21: Charts and KPI overview
A22: QA_Checks | B22: Gate status
A23: ReadMe | B23: Use instructions
A24: Release_Notes | B24: Limitations and next steps
A25: VBA source | B25: See exported .bas file
A27: Configurable Parameter | B27: Source / Macro Use | C27: Value
A28: Data Mode | B28: LoadDemoProject / ResetDemoData | C28: ='Project_Setup'!B18
A29: Monte Carlo Iterations | B29: RunMonteCarlo | C29: ='Project_Setup'!B19
A30: Standard Hours per Month | B30: Resource_Rates / Manpower | C30: ='Project_Setup'!B20
A31: Project Duration Months | B31: CashFlow / Manpower / Charts | C31: ='Project_Setup'!B12
A32: Annual Escalation Rate | B32: CalculateCashFlow / CalculateEscalation | C32: ='Project_Setup'!B15
A33: Selected Contingency Method | B33: CalculateContingency | C33: ='Project_Setup'!B14
A34: Release Package | B34: Workbook is xlsx; VBA provided as .bas for import into Excel | C34: See Release_Notes
A35: Final Status | B35: Automated tests performed in artifact environment | C35: Candidate - Excel desktop VBA import required

Sheet Project_Setup
A1: Project Setup
A2: Primary project metadata and global defaults.
A4: Project Name | B4: Industrial CAPEX Demo Project - Clean Build RC8
A5: Project Code | B5: CAPEX-RC8-DEMO
A6: Estimate Date | B6: 46176
A7: Estimate Class | B7: Class 3
A8: Project Phase | B8: FEED
A9: Base Currency | B9: EUR
A10: Project Start Date | B10: 46204
A11: Project End Date | B11: 47299
A12: Project Duration Months | B12: =(YEAR(B11)-YEAR(B10))*12+MONTH(B11)-MONTH(B10)+1
A13: Base Cost Target EUR | B13: 40000000
A14: Default Contingency Method | B14: Monte Carlo P80 - Base Cost
A15: Default Annual Escalation | B15: 0.03
A16: Excel Target | B16: Microsoft Excel desktop Windows
A17: Build Rule | B17: Clean rebuild from functional references only
A18: Data Mode | B18: Demo
A19: Monte Carlo Iterations | B19: 10000
A20: Standard Hours per Month | B20: 160
A21: Max Cash Flow Months | B21: 60
A22: RC8.1 Status | B22: Patched workbook + corrected VBA module supplied separately

Sheet Basis_of_Estimate
A1: Basis of Estimate
A2: Configurable AACE-style estimate classes and accuracy ranges.
A4: Estimate Class | B4: Description | C4: Low Accuracy % | D4: High Accuracy % | E4: Typical Deliverables | F4: Configurable | G4: Default Contingency Range | H4: Notes
A5: Class 5 | B5: Concept Screening | C5: -0.5 | D5: 1 | E5: Stage gate package, scope definition, quantity maturity, vendor inputs | F5: Yes | G5: 10%–25% | H5: Used by all input sheets
A6: Class 4 | B6: Concept Selection | C6: -0.3 | D6: 0.5 | E6: Stage gate package, scope definition, quantity maturity, vendor inputs | F6: Yes | G6: 10%–25% | H6: Used by all input sheets
A7: Class 3 | B7: FEED | C7: -0.2 | D7: 0.3 | E7: Stage gate package, scope definition, quantity maturity, vendor inputs | F7: Yes | G7: 8%–15% | H7: Used by all input sheets
A8: Class 2 | B8: Pre-Execution | C8: -0.15 | D8: 0.2 | E8: Stage gate package, scope definition, quantity maturity, vendor inputs | F8: Yes | G8: 8%–15% | H8: Used by all input sheets
A9: Class 1 | B9: Definitive Estimate | C9: -0.1 | D9: 0.15 | E9: Stage gate package, scope definition, quantity maturity, vendor inputs | F9: Yes | G9: 8%–15% | H9: Used by all input sheets

Sheet WBS_CBS
A1: WBS / CBS
A2: Standard breakdown structure used across Cost_Register and reports.
A4: WBS | B4: WBS Description | C4: CBS | D4: CBS Description | E4: Default Discipline | F4: Default Phase | G4: WBS Display | H4: Active | I4: Notes | J4: Default Cost Category | K4: Default Spend Category | L4: Default Spend Curve | M4: Default Contingency Eligible | N4: Default Escalation Eligible
A5: 1.0 | B5: Project Management | C5: PM | D5: Project Management | E5: Project Management | F5: Engineering | G5: 1.0 - Project Management | H5: Yes | I5: Clean build standard list | J5: Indirect Cost | K5: Engineering | L5: Bell Curve | M5: Yes | N5: Yes
A6: 2.0 | B6: Engineering | C6: ENG | D6: Engineering | E6: Project Management | F6: Engineering | G6: 2.0 - Engineering | H6: Yes | I6: Clean build standard list | J6: Indirect Cost | K6: Engineering | L6: Bell Curve | M6: Yes | N6: Yes
A7: 3.0 | B7: Procurement | C7: PROC | D7: Procurement | E7: Procurement | F7: Procurement | G7: 3.0 - Procurement | H7: Yes | I7: Clean build standard list | J7: Indirect Cost | K7: Procurement | L7: Linear | M7: Yes | N7: Yes
A8: 4.0 | B8: Equipment | C8: EQP | D8: Equipment | E8: Mechanical | F8: Procurement | G8: 4.0 - Equipment | H8: Yes | I8: Clean build standard list | J8: Direct Cost | K8: Procurement | L8: Back Loaded | M8: Yes | N8: Yes
A9: 5.0 | B9: Bulk Materials | C9: BULK | D9: Bulk Materials | E9: Piping | F9: Procurement | G9: 5.0 - Bulk Materials | H9: Yes | I9: Clean build standard list | J9: Direct Cost | K9: Procurement | L9: Linear | M9: Yes | N9: Yes
A10: 6.0 | B10: Civil & Structural | C10: CIV | D10: Civil | E10: Civil | F10: Construction | G10: 6.0 - Civil & Structural | H10: Yes | I10: Clean build standard list | J10: Direct Cost | K10: Construction | L10: Front Loaded | M10: Yes | N10: Yes
A11: 7.0 | B11: Electrical | C11: ELE | D11: Electrical | E11: Electrical | F11: Construction | G11: 7.0 - Electrical | H11: Yes | I11: Clean build standard list | J11: Direct Cost | K11: Construction | L11: Bell Curve | M11: Yes | N11: Yes
A12: 8.0 | B12: Instrumentation & Automation | C12: I&A | D12: Instrumentation & Automation | E12: Instrumentation | F12: Construction | G12: 8.0 - Instrumentation & Automation | H12: Yes | I12: Clean build standard list | J12: Direct Cost | K12: Construction | L12: Bell Curve | M12: Yes | N12: Yes
A13: 9.0 | B13: Construction | C13: CON | D13: Construction | E13: Construction | F13: Construction | G13: 9.0 - Construction | H13: Yes | I13: Clean build standard list | J13: Direct Cost | K13: Construction | L13: Bell Curve | M13: Yes | N13: Yes
A14: 10.0 | B14: Commissioning & Start-up | C14: COM | D14: Commissioning | E14: Commissioning | F14: Commissioning | G14: 10.0 - Commissioning & Start-up | H14: Yes | I14: Clean build standard list | J14: Direct Cost | K14: Commissioning | L14: Back Loaded | M14: Yes | N14: Yes
A15: 11.0 | B15: Owner Costs | C15: OWN | D15: Owner Costs | E15: Owner | F15: Other | G15: 11.0 - Owner Costs | H15: Yes | I15: Clean build standard list | J15: Owner Cost | K15: Other | L15: Front Loaded | M15: Yes | N15: Yes
A16: 12.0 | B16: Other Costs | C16: OTH | D16: Other Costs | E16: Other | F16: Other | G16: 12.0 - Other Costs | H16: Yes | I16: Clean build standard list | J16: Other Cost | K16: Other | L16: Back Loaded | M16: Yes | N16: Yes

Sheet FX_Rates
A1: FX Rates
A2: Configurable rate to EUR. EUR is the base currency.
A4: Currency | B4: Rate to EUR | C4: Source / Notes | D4: Last Updated | E4: Active | F4: QA
A5: EUR | B5: 1 | C5: Demo static rate. Replace with approved project FX. | D5: 46176 | E5: Yes | F5: PASS
A6: USD | B6: 0.92 | C6: Demo static rate. Replace with approved project FX. | D6: 46176 | E6: Yes | F6: PASS
A7: GBP | B7: 1.17 | C7: Demo static rate. Replace with approved project FX. | D7: 46176 | E7: Yes | F7: PASS
A8: CHF | B8: 1.04 | C8: Demo static rate. Replace with approved project FX. | D8: 46176 | E8: Yes | F8: PASS
A9: DKK | B9: 0.134 | C9: Demo static rate. Replace with approved project FX. | D9: 46176 | E9: Yes | F9: PASS
A10: SEK | B10: 0.087 | C10: Demo static rate. Replace with approved project FX. | D10: 46176 | E10: Yes | F10: PASS
A11: NOK | B11: 0.086 | C11: Demo static rate. Replace with approved project FX. | D11: 46176 | E11: Yes | F11: PASS
A12: PLN | B12: 0.235 | C12: Demo static rate. Replace with approved project FX. | D12: 46176 | E12: Yes | F12: PASS
A13: TRY | B13: 0.028 | C13: Demo static rate. Replace with approved project FX. | D13: 46176 | E13: Yes | F13: PASS
A14: MAD | B14: 0.092 | C14: Demo static rate. Replace with approved project FX. | D14: 46176 | E14: Yes | F14: PASS

Sheet Lists_Config
A1: Lists Config
A2: Central dropdown values. Input sheets use these lists.
A4: Discipline | B4: Cost Category | C4: Cost Type | D4: Phase | E4: Y/N | F4: Currency | G4: Estimate Basis | H4: Spend Category | I4: Spend Curve | J4: Unit | K4: Location
A5: Process | B5: Direct Cost | C5: Equipment | D5: Engineering | E5: Yes | F5: EUR | G5: Class 5 | H5: Engineering | I5: Linear | J5: lot | K5: Spain
A6: Mechanical | B6: Indirect Cost | C6: Bulk Material | D6: Procurement | E6: No | F6: USD | G6: Class 4 | H6: Procurement | I6: Front Loaded | J6: each | K6: France
A7: Piping | B7: Owner Cost | C7: Construction | D7: Construction | F7: GBP | G7: Class 3 | H7: Construction | I7: Back Loaded | J7: m | K7: Germany
A8: Civil | B8: Manpower Cost | C8: Engineering | D8: Commissioning | F8: CHF | G8: Class 2 | H8: Commissioning | I8: Bell Curve | J8: m2 | K8: Italy
A9: Electrical | B9: Other Cost | C9: EPCM | D9: Other | F9: DKK | G9: Class 1 | H9: Other | I9: Manual | J9: m3 | K9: Netherlands
A10: Instrumentation | C10: Owner | F10: SEK | J10: kg | K10: Belgium
A11: Automation | C11: Labour | F11: NOK | J11: ton | K11: UK
A12: Construction | C12: Freight | F12: PLN | J12: h | K12: Poland
A13: Project Management | C13: Spares | F13: TRY | J13: month | K13: Remote
A14: Procurement | C14: Other | F14: MAD | J14: FTE-month
A15: HSE
A16: Commissioning
A17: Owner
A18: Other

Sheet Data_Dictionary
A1: Data Dictionary
A2: Column-level definition of operational sheets.
A4: Sheet | B4: Column | C4: Description | D4: Type | E4: Required | F4: Input / Formula / Macro | G4: Source | H4: Validation | I4: Used By | J4: Notes
A5: Equipment_Estimate | B5: Item ID | C5: Item ID for elementary cost item | D5: Text/Number | E5: Yes | F5: Input | G5: User / Config | H5: Lists_Config / formula | I5: BuildCostRegister, QA, Summary | J5: Header-based mapping required
A6: Equipment_Estimate | B6: Description | C6: Description for elementary cost item | D6: Text/Number | E6: Yes | F6: Input | G6: User / Config | H6: Lists_Config / formula | I6: BuildCostRegister, QA, Summary | J6: Header-based mapping required
A7: Equipment_Estimate | B7: Discipline | C7: Discipline for elementary cost item | D7: Text/Number | E7: Yes | F7: Input | G7: User / Config | H7: Lists_Config / formula | I7: BuildCostRegister, QA, Summary | J7: Header-based mapping required
A8: Equipment_Estimate | B8: WBS | C8: WBS for elementary cost item | D8: Text/Number | E8: Yes | F8: Input | G8: User / Config | H8: Lists_Config / formula | I8: BuildCostRegister, QA, Summary | J8: Header-based mapping required
A9: Equipment_Estimate | B9: CBS | C9: CBS for elementary cost item | D9: Text/Number | E9: Yes | F9: Input | G9: User / Config | H9: Lists_Config / formula | I9: BuildCostRegister, QA, Summary | J9: Header-based mapping required
A10: Equipment_Estimate | B10: Cost Category | C10: Cost Category for elementary cost item | D10: Text/Number | E10: Yes | F10: Input | G10: User / Config | H10: Lists_Config / formula | I10: BuildCostRegister, QA, Summary | J10: Header-based mapping required
A11: Equipment_Estimate | B11: Cost Type | C11: Cost Type for elementary cost item | D11: Text/Number | E11: Yes | F11: Input | G11: User / Config | H11: Lists_Config / formula | I11: BuildCostRegister, QA, Summary | J11: Header-based mapping required
A12: Equipment_Estimate | B12: Quantity | C12: Quantity for elementary cost item | D12: Text/Number | E12: Yes | F12: Input | G12: User / Config | H12: Lists_Config / formula | I12: BuildCostRegister, QA, Summary | J12: Header-based mapping required
A13: Equipment_Estimate | B13: Unit | C13: Unit for elementary cost item | D13: Text/Number | E13: Yes | F13: Input | G13: User / Config | H13: Lists_Config / formula | I13: BuildCostRegister, QA, Summary | J13: Header-based mapping required
A14: Equipment_Estimate | B14: Unit Rate | C14: Unit Rate for elementary cost item | D14: Text/Number | E14: Yes | F14: Input | G14: User / Config | H14: Lists_Config / formula | I14: BuildCostRegister, QA, Summary | J14: Header-based mapping required
A15: Equipment_Estimate | B15: Currency | C15: Currency for elementary cost item | D15: Text/Number | E15: Yes | F15: Input | G15: User / Config | H15: Lists_Config / formula | I15: BuildCostRegister, QA, Summary | J15: Header-based mapping required
... A200: Other_Costs | B200: Notes | C200: Notes for elementary cost item | D200: Text/Number | E200: No | F200: Input | G200: User / Config | H200: Lists_Config / formula | I200: BuildCostRegister, QA, Summary | J200: Header-based mapping required
A201: Resource_Rates | B201: Role | C201: Role field | D201: Text/Number | E201: Yes | F201: Input/Formula | G201: User / FX_Rates | H201: Lists_Config | I201: Manpower_Plan
A202: Resource_Rates | B202: Discipline | C202: Discipline field | D202: Text/Number | E202: Yes | F202: Input/Formula | G202: User / FX_Rates | H202: Lists_Config | I202: Manpower_Plan
A203: Resource_Rates | B203: Location | C203: Location field | D203: Text/Number | E203: Yes | F203: Input/Formula | G203: User / FX_Rates | H203: Lists_Config | I203: Manpower_Plan
A204: Resource_Rates | B204: Currency | C204: Currency field | D204: Text/Number | E204: Yes | F204: Input/Formula | G204: User / FX_Rates | H204: Lists_Config | I204: Manpower_Plan
A205: Resource_Rates | B205: Hourly Rate | C205: Hourly Rate field | D205: Text/Number | E205: Yes | F205: Input/Formula | G205: User / FX_Rates | H205: Lists_Config | I205: Manpower_Plan
A206: Resource_Rates | B206: Hours per Month | C206: Hours per Month field | D206: Text/Number | E206: Yes | F206: Input/Formula | G206: User / FX_Rates | H206: Lists_Config | I206: Manpower_Plan
A207: Resource_Rates | B207: Monthly Rate | C207: Monthly Rate field | D207: Text/Number | E207: Yes | F207: Input/Formula | G207: User / FX_Rates | H207: Lists_Config | I207: Manpower_Plan
A208: Resource_Rates | B208: FX Rate | C208: FX Rate field | D208: Text/Number | E208: Yes | F208: Input/Formula | G208: User / FX_Rates | H208: Lists_Config | I208: Manpower_Plan
A209: Resource_Rates | B209: Monthly Rate EUR | C209: Monthly Rate EUR field | D209: Text/Number | E209: Yes | F209: Input/Formula | G209: User / FX_Rates | H209: Lists_Config | I209: Manpower_Plan
A210: Resource_Rates | B210: Notes | C210: Notes field | D210: Text/Number | E210: No | F210: Input/Formula | G210: User / FX_Rates | H210: Lists_Config | I210: Manpower_Plan
A211: Cost_Register | B211: Source Sheet | C211: Source Sheet normalized field | D211: Text/Number | E211: Yes | F211: Macro Output | G211: Input Sheets | H211: Header validation | I211: All reports | J211: Single source of truth
A212: Cost_Register | B212: Source Row | C212: Source Row normalized field | D212: Text/Number | E212: Yes | F212: Macro Output | G212: Input Sheets | H212: Header validation | I212: All reports | J212: Single source of truth
A213: Cost_Register | B213: Item ID | C213: Item ID normalized field | D213: Text/Number | E213: Yes | F213: Macro Output | G213: Input Sheets | H213: Header validation | I213: All reports | J213: Single source of truth
A214: Cost_Register | B214: Description | C214: Description normalized field | D214: Text/Number | E214: Yes | F214: Macro Output | G214: Input Sheets | H214: Header validation | I214: All reports | J214: Single source of truth
A215: Cost_Register | B215: Discipline | C215: Discipline normalized field | D215: Text/Number | E215: Yes | F215: Macro Output | G215: Input Sheets | H215: Header validation | I215: All reports | J215: Single source of truth
A216: Cost_Register | B216: WBS | C216: WBS normalized field | D216: Text/Number | E216: Yes | F216: Macro Output | G216: Input Sheets | H216: Header validation | I216: All reports | J216: Single source of truth
A217: Cost_Register | B217: CBS | C217: CBS normalized field | D217: Text/Number | E217: Yes | F217: Macro Output | G217: Input Sheets | H217: Header validation | I217: All reports | J217: Single source of truth
A218: Cost_Register | B218: Cost Category | C218: Cost Category normalized field | D218: Text/Number | E218: Yes | F218: Macro Output | G218: Input Sheets | H218: Header validation | I218: All reports | J218: Single source of truth
A219: Cost_Register | B219: Cost Type | C219: Cost Type normalized field | D219: Text/Number | E219: Yes | F219: Macro Output | G219: Input Sheets | H219: Header validation | I219: All reports | J219: Single source of truth
A220: Cost_Register | B220: Quantity | C220: Quantity normalized field | D220: Text/Number | E220: Yes | F220: Macro Output | G220: Input Sheets | H220: Header validation | I220: All reports | J220: Single source of truth
A221: Cost_Register | B221: Unit | C221: Unit normalized field | D221: Text/Number | E221: Yes | F221: Macro Output | G221: Input Sheets | H221: Header validation | I221: All reports | J221: Single source of truth
A222: Cost_Register | B222: Unit Rate | C222: Unit Rate normalized field | D222: Text/Number | E222: Yes | F222: Macro Output | G222: Input Sheets | H222: Header validation | I222: All reports | J222: Single source of truth
... A240: Cost_Register | B240: Notes | C240: Notes normalized field | D240: Text/Number | E240: Yes | F240: Macro Output | G240: Input Sheets | H240: Header validation | I240: All reports | J240: Single source of truth

Sheet Equipment_Estimate
A1: Equipment Estimate
A2: User input layer. Cost_Register must be rebuilt from these sheets via BuildCostRegister.
A4: Item ID | B4: Description | C4: Discipline | D4: WBS | E4: CBS | F4: Cost Category | G4: Cost Type | H4: Quantity | I4: Unit | J4: Unit Rate | K4: Currency | L4: FX Rate | M4: Base Cost | N4: Base Cost EUR | O4: Estimate Basis | P4: Accuracy Low % | Q4: Accuracy High % | R4: Low Cost | S4: Most Likely Cost | T4: High Cost | U4: Contingency Eligible | V4: Escalation Eligible | W4: Spend Category | X4: Phase | Y4: Start Month | Z4: End Month | AA4: Spend Curve | AB4: Notes
A5: EQ-001 | B5: Process mixer package | C5: =IF($D5="","",IFERROR(INDEX(WBS_CBS!$E$5:$E$16,MATCH($D5,WBS_CBS!$A$5:$A$16,0)),"")) | D5: 4.0 | E5: =IF($D5="","",IFERROR(INDEX(WBS_CBS!$C$5:$C$16,MATCH($D5,WBS_CBS!$A$5:$A$16,0)),"")) | F5: =IF($D5="","",IFERROR(INDEX(WBS_CBS!$J$5:$J$16,MATCH($D5,WBS_CBS!$A$5:$A$16,0)),"")) | G5: Equipment | H5: 1 | I5: lot | J5: 2800000 | K5: EUR | L5: =IF($K5="","",IFERROR(INDEX(FX_Rates!$B$5:$B$14,MATCH($K5,FX_Rates!$A$5:$A$14,0)),"")) | M5: =IF(OR($H5="",$J5=""),"",$H5*$J5) | N5: =IF(OR($M5="",$L5=""),"",$M5*$L5) | O5: Class 3 | P5: =IF($O5="","",IFERROR(INDEX(Basis_of_Estimate!$C$5:$C$9,MATCH($O5,Basis_of_Estimate!$A$5:$A$9,0)),"")) | Q5: =IF($O5="","",IFERROR(INDEX(Basis_of_Estimate!$D$5:$D$9,MATCH($O5,Basis_of_Estimate!$A$5:$A$9,0)),"")) | R5: =IF($N5="","",$N5*(1+$P5)) | S5: =IF($N5="","",$N5) | T5: =IF($N5="","",$N5*(1+$Q5)) | U5: =IF($D5="","",IFERROR(INDEX(WBS_CBS!$M$5:$M$16,MATCH($D5,WBS_CBS!$A$5:$A$16,0)),"Yes")) | V5: =IF($D5="","",IFERROR(INDEX(WBS_CBS!$N$5:$N$16,MATCH($D5,WBS_CBS!$A$5:$A$16,0)),"Yes")) | W5: =IF($D5="","",IFERROR(INDEX(WBS_CBS!$K$5:$K$16,MATCH($D5,WBS_CBS!$A$5:$A$16,0)),"")) | X5: =IF($D5="","",IFERROR(INDEX(WBS_CBS!$F$5:$F$16,MATCH($D5,WBS_CBS!$A$5:$A$16,0)),"")) | Y5: 8 | Z5: 18 | AA5: =IF($D5="","",IFERROR(INDEX(WBS_CBS!$L$5:$L$16,MATCH($D5,WBS_CBS!$A$5:$A$16,0)),""))
A6: EQ-002 | B6: Process vessels and tanks | C6: =IF($D6="","",IFERROR(INDEX(WBS_CBS!$E$5:$E$16,MATCH($D6,WBS_CBS!$A$5:$A$16,0)),"")) | D6: 4.0 | E6: =IF($D6="","",IFERROR(INDEX(WBS_CBS!$C$5:$C$16,MATCH($D6,WBS_CBS!$A$5:$A$16,0)),"")) | F6: =IF($D6="","",IFERROR(INDEX(WBS_CBS!$J$5:$J$16,MATCH($D6,WBS_CBS!$A$5:$A$16,0)),"")) | G6: Equipment | H6: 1 | I6: lot | J6: 3200000 | K6: EUR | L6: =IF($K6="","",IFERROR(INDEX(FX_Rates!$B$5:$B$14,MATCH($K6,FX_Rates!$A$5:$A$14,0)),"")) | M6: =IF(OR($H6="",$J6=""),"",$H6*$J6) | N6: =IF(OR($M6="",$L6=""),"",$M6*$L6) | O6: Class 3 | P6: =IF($O6="","",IFERROR(INDEX(Basis_of_Estimate!$C$5:$C$9,MATCH($O6,Basis_of_Estimate!$A$5:$A$9,0)),"")) | Q6: =IF($O6="","",IFERROR(INDEX(Basis_of_Estimate!$D$5:$D$9,MATCH($O6,Basis_of_Estimate!$A$5:$A$9,0)),"")) | R6: =IF($N6="","",$N6*(1+$P6)) | S6: =IF($N6="","",$N6) | T6: =IF($N6="","",$N6*(1+$Q6)) | U6: =IF($D6="","",IFERROR(INDEX(WBS_CBS!$M$5:$M$16,MATCH($D6,WBS_CBS!$A$5:$A$16,0)),"Yes")) | V6: =IF($D6="","",IFERROR(INDEX(WBS_CBS!$N$5:$N$16,MATCH($D6,WBS_CBS!$A$5:$A$16,0)),"Yes")) | W6: =IF($D6="","",IFERROR(INDEX(WBS_CBS!$K$5:$K$16,MATCH($D6,WBS_CBS!$A$5:$A$16,0)),"")) | X6: =IF($D6="","",IFERROR(INDEX(WBS_CBS!$F$5:$F$16,MATCH($D6,WBS_CBS!$A$5:$A$16,0)),"")) | Y6: 6 | Z6: 18 | AA6: =IF($D6="","",IFERROR(INDEX(WBS_CBS!$L$5:$L$16,MATCH($D6,WBS_CBS!$A$5:$A$16,0)),""))
A7: EQ-003 | B7: Pumping and transfer skids | C7: =IF($D7="","",IFERROR(INDEX(WBS_CBS!$E$5:$E$16,MATCH($D7,WBS_CBS!$A$5:$A$16,0)),"")) | D7: 4.0 | E7: =IF($D7="","",IFERROR(INDEX(WBS_CBS!$C$5:$C$16,MATCH($D7,WBS_CBS!$A$5:$A$16,0)),"")) | F7: =IF($D7="","",IFERROR(INDEX(WBS_CBS!$J$5:$J$16,MATCH($D7,WBS_CBS!$A$5:$A$16,0)),"")) | G7: Equipment | H7: 1 | I7: lot | J7: 2000000 | K7: EUR | L7: =IF($K7="","",IFERROR(INDEX(FX_Rates!$B$5:$B$14,MATCH($K7,FX_Rates!$A$5:$A$14,0)),"")) | M7: =IF(OR($H7="",$J7=""),"",$H7*$J7) | N7: =IF(OR($M7="",$L7=""),"",$M7*$L7) | O7: Class 3 | P7: =IF($O7="","",IFERROR(INDEX(Basis_of_Estimate!$C$5:$C$9,MATCH($O7,Basis_of_Estimate!$A$5:$A$9,0)),"")) | Q7: =IF($O7="","",IFERROR(INDEX(Basis_of_Estimate!$D$5:$D$9,MATCH($O7,Basis_of_Estimate!$A$5:$A$9,0)),"")) | R7: =IF($N7="","",$N7*(1+$P7)) | S7: =IF($N7="","",$N7) | T7: =IF($N7="","",$N7*(1+$Q7)) | U7: =IF($D7="","",IFERROR(INDEX(WBS_CBS!$M$5:$M$16,MATCH($D7,WBS_CBS!$A$5:$A$16,0)),"Yes")) | V7: =IF($D7="","",IFERROR(INDEX(WBS_CBS!$N$5:$N$16,MATCH($D7,WBS_CBS!$A$5:$A$16,0)),"Yes")) | W7: =IF($D7="","",IFERROR(INDEX(WBS_CBS!$K$5:$K$16,MATCH($D7,WBS_CBS!$A$5:$A$16,0)),"")) | X7: =IF($D7="","",IFERROR(INDEX(WBS_CBS!$F$5:$F$16,MATCH($D7,WBS_CBS!$A$5:$A$16,0)),"")) | Y7: 10 | Z7: 20 | AA7: =IF($D7="","",IFERROR(INDEX(WBS_CBS!$L$5:$L$16,MATCH($D7,WBS_CBS!$A$5:$A$16,0)),""))
A8: EQ-004 | B8: Heat exchangers and utility skids | C8: =IF($D8="","",IFERROR(INDEX(WBS_CBS!$E$5:$E$16,MATCH($D8,WBS_CBS!$A$5:$A$16,0)),"")) | D8: 4.0 | E8: =IF($D8="","",IFERROR(INDEX(WBS_CBS!$C$5:$C$16,MATCH($D8,WBS_CBS!$A$5:$A$16,0)),"")) | F8: =IF($D8="","",IFERROR(INDEX(WBS_CBS!$J$5:$J$16,MATCH($D8,WBS_CBS!$A$5:$A$16,0)),"")) | G8: Equipment | H8: 1 | I8: lot | J8: 2400000 | K8: EUR | L8: =IF($K8="","",IFERROR(INDEX(FX_Rates!$B$5:$B$14,MATCH($K8,FX_Rates!$A$5:$A$14,0)),"")) | M8: =IF(OR($H8="",$J8=""),"",$H8*$J8) | N8: =IF(OR($M8="",$L8=""),"",$M8*$L8) | O8: Class 3 | P8: =IF($O8="","",IFERROR(INDEX(Basis_of_Estimate!$C$5:$C$9,MATCH($O8,Basis_of_Estimate!$A$5:$A$9,0)),"")) | Q8: =IF($O8="","",IFERROR(INDEX(Basis_of_Estimate!$D$5:$D$9,MATCH($O8,Basis_of_Estimate!$A$5:$A$9,0)),"")) | R8: =IF($N8="","",$N8*(1+$P8)) | S8: =IF($N8="","",$N8) | T8: =IF($N8="","",$N8*(1+$Q8)) | U8: =IF($D8="","",IFERROR(INDEX(WBS_CBS!$M$5:$M$16,MATCH($D8,WBS_CBS!$A$5:$A$16,0)),"Yes")) | V8: =IF($D8="","",IFERROR(INDEX(WBS_CBS!$N$5:$N$16,MATCH($D8,WBS_CBS!$A$5:$A$16,0)),"Yes")) | W8: =IF($D8="","",IFERROR(INDEX(WBS_CBS!$K$5:$K$16,MATCH($D8,WBS_CBS!$A$5:$A$16,0)),"")) | X8: =IF($D8="","",IFERROR(INDEX(WBS_CBS!$F$5:$F$16,MATCH($D8,WBS_CBS!$A$5:$A$16,0)),"")) | Y8: 9 | Z8: 21 | AA8: =IF($D8="","",IFERROR(INDEX(WBS_CBS!$L$5:$L$16,MATCH($D8,WBS_CBS!$A$5:$A$16,0)),""))
A9: EQ-005 | B9: Equipment installation auxiliaries | C9: =IF($D9="","",IFERROR(INDEX(WBS_CBS!$E$5:$E$16,MATCH($D9,WBS_CBS!$A$5:$A$16,0)),"")) | D9: 4.0 | E9: =IF($D9="","",IFERROR(INDEX(WBS_CBS!$C$5:$C$16,MATCH($D9,WBS_CBS!$A$5:$A$16,0)),"")) | F9: =IF($D9="","",IFERROR(INDEX(WBS_CBS!$J$5:$J$16,MATCH($D9,WBS_CBS!$A$5:$A$16,0)),"")) | G9: Equipment | H9: 1 | I9: lot | J9: 1600000 | K9: EUR | L9: =IF($K9="","",IFERROR(INDEX(FX_Rates!$B$5:$B$14,MATCH($K9,FX_Rates!$A$5:$A$14,0)),"")) | M9: =IF(OR($H9="",$J9=""),"",$H9*$J9) | N9: =IF(OR($M9="",$L9=""),"",$M9*$L9) | O9: Class 3 | P9: =IF($O9="","",IFERROR(INDEX(Basis_of_Estimate!$C$5:$C$9,MATCH($O9,Basis_of_Estimate!$A$5:$A$9,0)),"")) | Q9: =IF($O9="","",IFERROR(INDEX(Basis_of_Estimate!$D$5:$D$9,MATCH($O9,Basis_of_Estimate!$A$5:$A$9,0)),"")) | R9: =IF($N9="","",$N9*(1+$P9)) | S9: =IF($N9="","",$N9) | T9: =IF($N9="","",$N9*(1+$Q9)) | U9: =IF($D9="","",IFERROR(INDEX(WBS_CBS!$M$5:$M$16,MATCH($D9,WBS_CBS!$A$5:$A$16,0)),"Yes")) | V9: =IF($D9="","",IFERROR(INDEX(WBS_CBS!$N$5:$N$16,MATCH($D9,WBS_CBS!$A$5:$A$16,0)),"Yes")) | W9: =IF($D9="","",IFERROR(INDEX(WBS_CBS!$K$5:$K$16,MATCH($D9,WBS_CBS!$A$5:$A$16,0)),"")) | X9: =IF($D9="","",IFERROR(INDEX(WBS_CBS!$F$5:$F$16,MATCH($D9,WBS_CBS!$A$5:$A$16,0)),"")) | Y9: 14 | Z9: 27 | AA9: =IF($D9="","",IFERROR(INDEX(WBS_CBS!$L$5:$L$16,MATCH($D9,WBS_CBS!$A$5:$A$16,0)),""))
C10: =IF($D10="","",IFERROR(INDEX(WBS_CBS!$E$5:$E$16,MATCH($D10,WBS_CBS!$A$5:$A$16,0)),"")) | E10: =IF($D10="","",IFERROR(INDEX(WBS_CBS!$C$5:$C$16,MATCH($D10,WBS_CBS!$A$5:$A$16,0)),"")) | F10: =IF($D10="","",IFERROR(INDEX(WBS_CBS!$J$5:$J$16,MATCH($D10,WBS_CBS!$A$5:$A$16,0)),"")) | L10: =IF($K10="","",IFERROR(INDEX(FX_Rates!$B$5:$B$14,MATCH($K10,FX_Rates!$A$5:$A$14,0)),"")) | M10: =IF(OR($H10="",$J10=""),"",$H10*$J10) | N10: =IF(OR($M10="",$L10=""),"",$M10*$L10) | P10: =IF($O10="","",IFERROR(INDEX(Basis_of_Estimate!$C$5:$C$9,MATCH($O10,Basis_of_Estimate!$A$5:$A$9,0)),"")) | Q10: =IF($O10="","",IFERROR(INDEX(Basis_of_Estimate!$D$5:$D$9,MATCH($O10,Basis_of_Estimate!$A$5:$A$9,0)),"")) | R10: =IF($N10="","",$N10*(1+$P10)) | S10: =IF($N10="","",$N10) | T10: =IF($N10="","",$N10*(1+$Q10)) | U10: =IF($D10="","",IFERROR(INDEX(WBS_CBS!$M$5:$M$16,MATCH($D10,WBS_CBS!$A$5:$A$16,0)),"Yes")) | V10: =IF($D10="","",IFERROR(INDEX(WBS_CBS!$N$5:$N$16,MATCH($D10,WBS_CBS!$A$5:$A$16,0)),"Yes")) | W10: =IF($D10="","",IFERROR(INDEX(WBS_CBS!$K$5:$K$16,MATCH($D10,WBS_CBS!$A$5:$A$16,0)),"")) | X10: =IF($D10="","",IFERROR(INDEX(WBS_CBS!$F$5:$F$16,MATCH($D10,WBS_CBS!$A$5:$A$16,0)),"")) | AA10: =IF($D10="","",IFERROR(INDEX(WBS_CBS!$L$5:$L$16,MATCH($D10,WBS_CBS!$A$5:$A$16,0)),""))
C11: =IF($D11="","",IFERROR(INDEX(WBS_CBS!$E$5:$E$16,MATCH($D11,WBS_CBS!$A$5:$A$16,0)),"")) | E11: =IF($D11="","",IFERROR(INDEX(WBS_CBS!$C$5:$C$16,MATCH($D11,WBS_CBS!$A$5:$A$16,0)),"")) | F11: =IF($D11="","",IFERROR(INDEX(WBS_CBS!$J$5:$J$16,MATCH($D11,WBS_CBS!$A$5:$A$16,0)),"")) | L11: =IF($K11="","",IFERROR(INDEX(FX_Rates!$B$5:$B$14,MATCH($K11,FX_Rates!$A$5:$A$14,0)),"")) | M11: =IF(OR($H11="",$J11=""),"",$H11*$J11) | N11: =IF(OR($M11="",$L11=""),"",$M11*$L11) | P11: =IF($O11="","",IFERROR(INDEX(Basis_of_Estimate!$C$5:$C$9,MATCH($O11,Basis_of_Estimate!$A$5:$A$9,0)),"")) | Q11: =IF($O11="","",IFERROR(INDEX(Basis_of_Estimate!$D$5:$D$9,MATCH($O11,Basis_of_Estimate!$A$5:$A$9,0)),"")) | R11: =IF($N11="","",$N11*(1+$P11)) | S11: =IF($N11="","",$N11) | T11: =IF($N11="","",$N11*(1+$Q11)) | U11: =IF($D11="","",IFERROR(INDEX(WBS_CBS!$M$5:$M$16,MATCH($D11,WBS_CBS!$A$5:$A$16,0)),"Yes")) | V11: =IF($D11="","",IFERROR(INDEX(WBS_CBS!$N$5:$N$16,MATCH($D11,WBS_CBS!$A$5:$A$16,0)),"Yes")) | W11: =IF($D11="","",IFERROR(INDEX(WBS_CBS!$K$5:$K$16,MATCH($D11,WBS_CBS!$A$5:$A$16,0)),"")) | X11: =IF($D11="","",IFERROR(INDEX(WBS_CBS!$F$5:$F$16,MATCH($D11,WBS_CBS!$A$5:$A$16,0)),"")) | AA11: =IF($D11="","",IFERROR(INDEX(WBS_CBS!$L$5:$L$16,MATCH($D11,WBS_CBS!$A$5:$A$16,0)),""))
C12: =IF($D12="","",IFERROR(INDEX(WBS_CBS!$E$5:$E$16,MATCH($D12,WBS_CBS!$A$5:$A$16,0)),"")) | E12: =IF($D12="","",IFERROR(INDEX(WBS_CBS!$C$5:$C$16,MATCH($D12,WBS_CBS!$A$5:$A$16,0)),"")) | F12: =IF($D12="","",IFERROR(INDEX(WBS_CBS!$J$5:$J$16,MATCH($D12,WBS_CBS!$A$5:$A$16,0)),"")) | L12: =IF($K12="","",IFERROR(INDEX(FX_Rates!$B$5:$B$14,MATCH($K12,FX_Rates!$A$5:$A$14,0)),"")) | M12: =IF(OR($H12="",$J12=""),"",$H12*$J12) | N12: =IF(OR($M12="",$L12=""),"",$M12*$L12) | P12: =IF($O12="","",IFERROR(INDEX(Basis_of_Estimate!$C$5:$C$9,MATCH($O12,Basis_of_Estimate!$A$5:$A$9,0)),"")) | Q12: =IF($O12="","",IFERROR(INDEX(Basis_of_Estimate!$D$5:$D$9,MATCH($O12,Basis_of_Estimate!$A$5:$A$9,0)),"")) | R12: =IF($N12="","",$N12*(1+$P12)) | S12: =IF($N12="","",$N12) | T12: =IF($N12="","",$N12*(1+$Q12)) | U12: =IF($D12="","",IFERROR(INDEX(WBS_CBS!$M$5:$M$16,MATCH($D12,WBS_CBS!$A$5:$A$16,0)),"Yes")) | V12: =IF($D12="","",IFERROR(INDEX(WBS_CBS!$N$5:$N$16,MATCH($D12,WBS_CBS!$A$5:$A$16,0)),"Yes")) | W12: =IF($D12="","",IFERROR(INDEX(WBS_CBS!$K$5:$K$16,MATCH($D12,WBS_CBS!$A$5:$A$16,0)),"")) | X12: =IF($D12="","",IFERROR(INDEX(WBS_CBS!$F$5:$F$16,MATCH($D12,WBS_CBS!$A$5:$A$16,0)),"")) | AA12: =IF($D12="","",IFERROR(INDEX(WBS_CBS!$L$5:$L$16,MATCH($D12,WBS_CBS!$A$5:$A$16,0)),""))
C13: =IF($D13="","",IFERROR(INDEX(WBS_CBS!$E$5:$E$16,MATCH($D13,WBS_CBS!$A$5:$A$16,0)),"")) | E13: =IF($D13="","",IFERROR(INDEX(WBS_CBS!$C$5:$C$16,MATCH($D13,WBS_CBS!$A$5:$A$16,0)),"")) | F13: =IF($D13="","",IFERROR(INDEX(WBS_CBS!$J$5:$J$16,MATCH($D13,WBS_CBS!$A$5:$A$16,0)),"")) | L13: =IF($K13="","",IFERROR(INDEX(FX_Rates!$B$5:$B$14,MATCH($K13,FX_Rates!$A$5:$A$14,0)),"")) | M13: =IF(OR($H13="",$J13=""),"",$H13*$J13) | N13: =IF(OR($M13="",$L13=""),"",$M13*$L13) | P13: =IF($O13="","",IFERROR(INDEX(Basis_of_Estimate!$C$5:$C$9,MATCH($O13,Basis_of_Estimate!$A$5:$A$9,0)),"")) | Q13: =IF($O13="","",IFERROR(INDEX(Basis_of_Estimate!$D$5:$D$9,MATCH($O13,Basis_of_Estimate!$A$5:$A$9,0)),"")) | R13: =IF($N13="","",$N13*(1+$P13)) | S13: =IF($N13="","",$N13) | T13: =IF($N13="","",$N13*(1+$Q13)) | U13: =IF($D13="","",IFERROR(INDEX(WBS_CBS!$M$5:$M$16,MATCH($D13,WBS_CBS!$A$5:$A$16,0)),"Yes")) | V13: =IF($D13="","",IFERROR(INDEX(WBS_CBS!$N$5:$N$16,MATCH($D13,WBS_CBS!$A$5:$A$16,0)),"Yes")) | W13: =IF($D13="","",IFERROR(INDEX(WBS_CBS!$K$5:$K$16,MATCH($D13,WBS_CBS!$A$5:$A$16,0)),"")) | X13: =IF($D13="","",IFERROR(INDEX(WBS_CBS!$F$5:$F$16,MATCH($D13,WBS_CBS!$A$5:$A$16,0)),"")) | AA13: =IF($D13="","",IFERROR(INDEX(WBS_CBS!$L$5:$L$16,MATCH($D13,WBS_CBS!$A$5:$A$16,0)),""))
C14: =IF($D14="","",IFERROR(INDEX(WBS_CBS!$E$5:$E$16,MATCH($D14,WBS_CBS!$A$5:$A$16,0)),"")) | E14: =IF($D14="","",IFERROR(INDEX(WBS_CBS!$C$5:$C$16,MATCH($D14,WBS_CBS!$A$5:$A$16,0)),"")) | F14: =IF($D14="","",IFERROR(INDEX(WBS_CBS!$J$5:$J$16,MATCH($D14,WBS_CBS!$A$5:$A$16,0)),"")) | L14: =IF($K14="","",IFERROR(INDEX(FX_Rates!$B$5:$B$14,MATCH($K14,FX_Rates!$A$5:$A$14,0)),"")) | M14: =IF(OR($H14="",$J14=""),"",$H14*$J14) | N14: =IF(OR($M14="",$L14=""),"",$M14*$L14) | P14: =IF($O14="","",IFERROR(INDEX(Basis_of_Estimate!$C$5:$C$9,MATCH($O14,Basis_of_Estimate!$A$5:$A$9,0)),"")) | Q14: =IF($O14="","",IFERROR(INDEX(Basis_of_Estimate!$D$5:$D$9,MATCH($O14,Basis_of_Estimate!$A$5:$A$9,0)),"")) | R14: =IF($N14="","",$N14*(1+$P14)) | S14: =IF($N14="","",$N14) | T14: =IF($N14="","",$N14*(1+$Q14)) | U14: =IF($D14="","",IFERROR(INDEX(WBS_CBS!$M$5:$M$16,MATCH($D14,WBS_CBS!$A$5:$A$16,0)),"Yes")) | V14: =IF($D14="","",IFERROR(INDEX(WBS_CBS!$N$5:$N$16,MATCH($D14,WBS_CBS!$A$5:$A$16,0)),"Yes")) | W14: =IF($D14="","",IFERROR(INDEX(WBS_CBS!$K$5:$K$16,MATCH($D14,WBS_CBS!$A$5:$A$16,0)),"")) | X14: =IF($D14="","",IFERROR(INDEX(WBS_CBS!$F$5:$F$16,MATCH($D14,WBS_CBS!$A$5:$A$16,0)),"")) | AA14: =IF($D14="","",IFERROR(INDEX(WBS_CBS!$L$5:$L$16,MATCH($D14,WBS_CBS!$A$5:$A$16,0)),""))
C15: =IF($D15="","",IFERROR(INDEX(WBS_CBS!$E$5:$E$16,MATCH($D15,WBS_CBS!$A$5:$A$16,0)),"")) | E15: =IF($D15="","",IFERROR(INDEX(WBS_CBS!$C$5:$C$16,MATCH($D15,WBS_CBS!$A$5:$A$16,0)),"")) | F15: =IF($D15="","",IFERROR(INDEX(WBS_CBS!$J$5:$J$16,MATCH($D15,WBS_CBS!$A$5:$A$16,0)),"")) | L15: =IF($K15="","",IFERROR(INDEX(FX_Rates!$B$5:$B$14,MATCH($K15,FX_Rates!$A$5:$A$14,0)),"")) | M15: =IF(OR($H15="",$J15=""),"",$H15*$J15) | N15: =IF(OR($M15="",$L15=""),"",$M15*$L15) | P15: =IF($O15="","",IFERROR(INDEX(Basis_of_Estimate!$C$5:$C$9,MATCH($O15,Basis_of_Estimate!$A$5:$A$9,0)),"")) | Q15: =IF($O15="","",IFERROR(INDEX(Basis_of_Estimate!$D$5:$D$9,MATCH($O15,Basis_of_Estimate!$A$5:$A$9,0)),"")) | R15: =IF($N15="","",$N15*(1+$P15)) | S15: =IF($N15="","",$N15) | T15: =IF($N15="","",$N15*(1+$Q15)) | U15: =IF($D15="","",IFERROR(INDEX(WBS_CBS!$M$5:$M$16,MATCH($D15,WBS_CBS!$A$5:$A$16,0)),"Yes")) | V15: =IF($D15="","",IFERROR(INDEX(WBS_CBS!$N$5:$N$16,MATCH($D15,WBS_CBS!$A$5:$A$16,0)),"Yes")) | W15: =IF($D15="","",IFERROR(INDEX(WBS_CBS!$K$5:$K$16,MATCH($D15,WBS_CBS!$A$5:$A$16,0)),"")) | X15: =IF($D15="","",IFERROR(INDEX(WBS_CBS!$F$5:$F$16,MATCH($D15,WBS_CBS!$A$5:$A$16,0)),"")) | AA15: =IF($D15="","",IFERROR(INDEX(WBS_CBS!$L$5:$L$16,MATCH($D15,WBS_CBS!$A$5:$A$16,0)),""))
C16: =IF($D16="","",IFERROR(INDEX(WBS_CBS!$E$5:$E$16,MATCH($D16,WBS_CBS!$A$5:$A$16,0)),"")) | E16: =IF($D16="","",IFERROR(INDEX(WBS_CBS!$C$5:$C$16,MATCH($D16,WBS_CBS!$A$5:$A$16,0)),"")) | F16: =IF($D16="","",IFERROR(INDEX(WBS_CBS!$J$5:$J$16,MATCH($D16,WBS_CBS!$A$5:$A$16,0)),"")) | L16: =IF($K16="","",IFERROR(INDEX(FX_Rates!$B$5:$B$14,MATCH($K16,FX_Rates!$A$5:$A$14,0)),"")) | M16: =IF(OR($H16="",$J16=""),"",$H16*$J16) | N16: =IF(OR($M16="",$L16=""),"",$M16*$L16) | P16: =IF($O16="","",IFERROR(INDEX(Basis_of_Estimate!$C$5:$C$9,MATCH($O16,Basis_of_Estimate!$A$5:$A$9,0)),"")) | Q16: =IF($O16="","",IFERROR(INDEX(Basis_of_Estimate!$D$5:$D$9,MATCH($O16,Basis_of_Estimate!$A$5:$A$9,0)),"")) | R16: =IF($N16="","",$N16*(1+$P16)) | S16: =IF($N16="","",$N16) | T16: =IF($N16="","",$N16*(1+$Q16)) | U16: =IF($D16="","",IFERROR(INDEX(WBS_CBS!$M$5:$M$16,MATCH($D16,WBS_CBS!$A$5:$A$16,0)),"Yes")) | V16: =IF($D16="","",IFERROR(INDEX(WBS_CBS!$N$5:$N$16,MATCH($D16,WBS_CBS!$A$5:$A$16,0)),"Yes")) | W16: =IF($D16="","",IFERROR(INDEX(WBS_CBS!$K$5:$K$16,MATCH($D16,WBS_CBS!$A$5:$A$16,0)),"")) | X16: =IF($D16="","",IFERROR(INDEX(WBS_CBS!$F$5:$F$16,MATCH($D16,WBS_CBS!$A$5:$A$16,0)),"")) | AA16: =IF($D16="","",IFERROR(INDEX(WBS_CBS!$L$5:$L$16,MATCH($D16,WBS_CBS!$A$5:$A$16,0)),""))
C17: =IF($D17="","",IFERROR(INDEX(WBS_CBS!$E$5:$E$16,MATCH($D17,WBS_CBS!$A$5:$A$16,0)),"")) | E17: =IF($D17="","",IFERROR(INDEX(WBS_CBS!$C$5:$C$16,MATCH($D17,WBS_CBS!$A$5:$A$16,0)),"")) | F17: =IF($D17="","",IFERROR(INDEX(WBS_CBS!$J$5:$J$16,MATCH($D17,WBS_CBS!$A$5:$A$16,0)),"")) | L17: =IF($K17="","",IFERROR(INDEX(FX_Rates!$B$5:$B$14,MATCH($K17,FX_Rates!$A$5:$A$14,0)),"")) | M17: =IF(OR($H17="",$J17=""),"",$H17*$J17) | N17: =IF(OR($M17="",$L17=""),"",$M17*$L17) | P17: =IF($O17="","",IFERROR(INDEX(Basis_of_Estimate!$C$5:$C$9,MATCH($O17,Basis_of_Estimate!$A$5:$A$9,0)),"")) | Q17: =IF($O17="","",IFERROR(INDEX(Basis_of_Estimate!$D$5:$D$9,MATCH($O17,Basis_of_Estimate!$A$5:$A$9,0)),"")) | R17: =IF($N17="","",$N17*(1+$P17)) | S17: =IF($N17="","",$N17) | T17: =IF($N17="","",$N17*(1+$Q17)) | U17: =IF($D17="","",IFERROR(INDEX(WBS_CBS!$M$5:$M$16,MATCH($D17,WBS_CBS!$A$5:$A$16,0)),"Yes")) | V17: =IF($D17="","",IFERROR(INDEX(WBS_CBS!$N$5:$N$16,MATCH($D17,WBS_CBS!$A$5:$A$16,0)),"Yes")) | W17: =IF($D17="","",IFERROR(INDEX(WBS_CBS!$K$5:$K$16,MATCH($D17,WBS_CBS!$A$5:$A$16,0)),"")) | X17: =IF($D17="","",IFERROR(INDEX(WBS_CBS!$F$5:$F$16,MATCH($D17,WBS_CBS!$A$5:$A$16,0)),"")) | AA17: =IF($D17="","",IFERROR(INDEX(WBS_CBS!$L$5:$L$16,MATCH($D17,WBS_CBS!$A$5:$A$16,0)),""))
C18: =IF($D18="","",IFERROR(INDEX(WBS_CBS!$E$5:$E$16,MATCH($D18,WBS_CBS!$A$5:$A$16,0)),"")) | E18: =IF($D18="","",IFERROR(INDEX(WBS_CBS!$C$5:$C$16,MATCH($D18,WBS_CBS!$A$5:$A$16,0)),"")) | F18: =IF($D18="","",IFERROR(INDEX(WBS_CBS!$J$5:$J$16,MATCH($D18,WBS_CBS!$A$5:$A$16,0)),"")) | L18: =IF($K18="","",IFERROR(INDEX(FX_Rates!$B$5:$B$14,MATCH($K18,FX_Rates!$A$5:$A$14,0)),"")) | M18: =IF(OR($H18="",$J18=""),"",$H18*$J18) | N18: =IF(OR($M18="",$L18=""),"",$M18*$L18) | P18: =IF($O18="","",IFERROR(INDEX(Basis_of_Estimate!$C$5:$C$9,MATCH($O18,Basis_of_Estimate!$A$5:$A$9,0)),"")) | Q18: =IF($O18="","",IFERROR(INDEX(Basis_of_Estimate!$D$5:$D$9,MATCH($O18,Basis_of_Estimate!$A$5:$A$9,0)),"")) | R18: =IF($N18="","",$N18*(1+$P18)) | S18: =IF($N18="","",$N18) | T18: =IF($N18="","",$N18*(1+$Q18)) | U18: =IF($D18="","",IFERROR(INDEX(WBS_CBS!$M$5:$M$16,MATCH($D18,WBS_CBS!$A$5:$A$16,0)),"Yes")) | V18: =IF($D18="","",IFERROR(INDEX(WBS_CBS!$N$5:$N$16,MATCH($D18,WBS_CBS!$A$5:$A$16,0)),"Yes")) | W18: =IF($D18="","",IFERROR(INDEX(WBS_CBS!$K$5:$K$16,MATCH($D18,WBS_CBS!$A$5:$A$16,0)),"")) | X18: =IF($D18="","",IFERROR(INDEX(WBS_CBS!$F$5:$F$16,MATCH($D18,WBS_CBS!$A$5:$A$16,0)),"")) | AA18: =IF($D18="","",IFERROR(INDEX(WBS_CBS!$L$5:$L$16,MATCH($D18,WBS_CBS!$A$5:$A$16,0)),""))
C19: =IF($D19="","",IFERROR(INDEX(WBS_CBS!$E$5:$E$16,MATCH($D19,WBS_CBS!$A$5:$A$16,0)),"")) | E19: =IF($D19="","",IFERROR(INDEX(WBS_CBS!$C$5:$C$16,MATCH($D19,WBS_CBS!$A$5:$A$16,0)),"")) | F19: =IF($D19="","",IFERROR(INDEX(WBS_CBS!$J$5:$J$16,MATCH($D19,WBS_CBS!$A$5:$A$16,0)),"")) | L19: =IF($K19="","",IFERROR(INDEX(FX_Rates!$B$5:$B$14,MATCH($K19,FX_Rates!$A$5:$A$14,0)),"")) | M19: =IF(OR($H19="",$J19=""),"",$H19*$J19) | N19: =IF(OR($M19="",$L19=""),"",$M19*$L19) | P19: =IF($O19="","",IFERROR(INDEX(Basis_of_Estimate!$C$5:$C$9,MATCH($O19,Basis_of_Estimate!$A$5:$A$9,0)),"")) | Q19: =IF($O19="","",IFERROR(INDEX(Basis_of_Estimate!$D$5:$D$9,MATCH($O19,Basis_of_Estimate!$A$5:$A$9,0)),"")) | R19: =IF($N19="","",$N19*(1+$P19)) | S19: =IF($N19="","",$N19) | T19: =IF($N19="","",$N19*(1+$Q19)) | U19: =IF($D19="","",IFERROR(INDEX(WBS_CBS!$M$5:$M$16,MATCH($D19,WBS_CBS!$A$5:$A$16,0)),"Yes")) | V19: =IF($D19="","",IFERROR(INDEX(WBS_CBS!$N$5:$N$16,MATCH($D19,WBS_CBS!$A$5:$A$16,0)),"Yes")) | W19: =IF($D19="","",IFERROR(INDEX(WBS_CBS!$K$5:$K$16,MATCH($D19,WBS_CBS!$A$5:$A$16,0)),"")) | X19: =IF($D19="","",IFERROR(INDEX(WBS_CBS!$F$5:$F$16,MATCH($D19,WBS_CBS!$A$5:$A$16,0)),"")) | AA19: =IF($D19="","",IFERROR(INDEX(WBS_CBS!$L$5:$L$16,MATCH($D19,WBS_CBS!$A$5:$A$16,0)),""))
C20: =IF($D20="","",IFERROR(INDEX(WBS_CBS!$E$5:$E$16,MATCH($D20,WBS_CBS!$A$5:$A$16,0)),"")) | E20: =IF($D20="","",IFERROR(INDEX(WBS_CBS!$C$5:$C$16,MATCH($D20,WBS_CBS!$A$5:$A$16,0)),"")) | F20: =IF($D20="","",IFERROR(INDEX(WBS_CBS!$J$5:$J$16,MATCH($D20,WBS_CBS!$A$5:$A$16,0)),"")) | L20: =IF($K20="","",IFERROR(INDEX(FX_Rates!$B$5:$B$14,MATCH($K20,FX_Rates!$A$5:$A$14,0)),"")) | M20: =IF(OR($H20="",$J20=""),"",$H20*$J20) | N20: =IF(OR($M20="",$L20=""),"",$M20*$L20) | P20: =IF($O20="","",IFERROR(INDEX(Basis_of_Estimate!$C$5:$C$9,MATCH($O20,Basis_of_Estimate!$A$5:$A$9,0)),"")) | Q20: =IF($O20="","",IFERROR(INDEX(Basis_of_Estimate!$D$5:$D$9,MATCH($O20,Basis_of_Estimate!$A$5:$A$9,0)),"")) | R20: =IF($N20="","",$N20*(1+$P20)) | S20: =IF($N20="","",$N20) | T20: =IF($N20="","",$N20*(1+$Q20)) | U20: =IF($D20="","",IFERROR(INDEX(WBS_CBS!$M$5:$M$16,MATCH($D20,WBS_CBS!$A$5:$A$16,0)),"Yes")) | V20: =IF($D20="","",IFERROR(INDEX(WBS_CBS!$N$5:$N$16,MATCH($D20,WBS_CBS!$A$5:$A$16,0)),"Yes")) | W20: =IF($D20="","",IFERROR(INDEX(WBS_CBS!$K$5:$K$16,MATCH($D20,WBS_CBS!$A$5:$A$16,0)),"")) | X20: =IF($D20="","",IFERROR(INDEX(WBS_CBS!$F$5:$F$16,MATCH($D20,WBS_CBS!$A$5:$A$16,0)),"")) | AA20: =IF($D20="","",IFERROR(INDEX(WBS_CBS!$L$5:$L$16,MATCH($D20,WBS_CBS!$A$5:$A$16,0)),""))
C21: =IF($D21="","",IFERROR(INDEX(WBS_CBS!$E$5:$E$16,MATCH($D21,WBS_CBS!$A$5:$A$16,0)),"")) | E21: =IF($D21="","",IFERROR(INDEX(WBS_CBS!$C$5:$C$16,MATCH($D21,WBS_CBS!$A$5:$A$16,0)),"")) | F21: =IF($D21="","",IFERROR(INDEX(WBS_CBS!$J$5:$J$16,MATCH($D21,WBS_CBS!$A$5:$A$16,0)),"")) | L21: =IF($K21="","",IFERROR(INDEX(FX_Rates!$B$5:$B$14,MATCH($K21,FX_Rates!$A$5:$A$14,0)),"")) | M21: =IF(OR($H21="",$J21=""),"",$H21*$J21) | N21: =IF(OR($M21="",$L21=""),"",$M21*$L21) | P21: =IF($O21="","",IFERROR(INDEX(Basis_of_Estimate!$C$5:$C$9,MATCH($O21,Basis_of_Estimate!$A$5:$A$9,0)),"")) | Q21: =IF($O21="","",IFERROR(INDEX(Basis_of_Estimate!$D$5:$D$9,MATCH($O21,Basis_of_Estimate!$A$5:$A$9,0)),"")) | R21: =IF($N21="","",$N21*(1+$P21)) | S21: =IF($N21="","",$N21) | T21: =IF($N21="","",$N21*(1+$Q21)) | U21: =IF($D21="","",IFERROR(INDEX(WBS_CBS!$M$5:$M$16,MATCH($D21,WBS_CBS!$A$5:$A$16,0)),"Yes")) | V21: =IF($D21="","",IFERROR(INDEX(WBS_CBS!$N$5:$N$16,MATCH($D21,WBS_CBS!$A$5:$A$16,0)),"Yes")) | W21: =IF($D21="","",IFERROR(INDEX(WBS_CBS!$K$5:$K$16,MATCH($D21,WBS_CBS!$A$5:$A$16,0)),"")) | X21: =IF($D21="","",IFERROR(INDEX(WBS_CBS!$F$5:$F$16,MATCH($D21,WBS_CBS!$A$5:$A$16,0)),"")) | AA21: =IF($D21="","",IFERROR(INDEX(WBS_CBS!$L$5:$L$16,MATCH($D21,WBS_CBS!$A$5:$A$16,0)),""))
... C104: =IF($D104="","",IFERROR(INDEX(WBS_CBS!$E$5:$E$16,MATCH($D104,WBS_CBS!$A$5:$A$16,0)),"")) | E104: =IF($D104="","",IFERROR(INDEX(WBS_CBS!$C$5:$C$16,MATCH($D104,WBS_CBS!$A$5:$A$16,0)),"")) | F104: =IF($D104="","",IFERROR(INDEX(WBS_CBS!$J$5:$J$16,MATCH($D104,WBS_CBS!$A$5:$A$16,0)),"")) | L104: =IF($K104="","",IFERROR(INDEX(FX_Rates!$B$5:$B$14,MATCH($K104,FX_Rates!$A$5:$A$14,0)),"")) | M104: =IF(OR($H104="",$J104=""),"",$H104*$J104) | N104: =IF(OR($M104="",$L104=""),"",$M104*$L104) | P104: =IF($O104="","",IFERROR(INDEX(Basis_of_Estimate!$C$5:$C$9,MATCH($O104,Basis_of_Estimate!$A$5:$A$9,0)),"")) | Q104: =IF($O104="","",IFERROR(INDEX(Basis_of_Estimate!$D$5:$D$9,MATCH($O104,Basis_of_Estimate!$A$5:$A$9,0)),"")) | R104: =IF($N104="","",$N104*(1+$P104)) | S104: =IF($N104="","",$N104) | T104: =IF($N104="","",$N104*(1+$Q104)) | U104: =IF($D104="","",IFERROR(INDEX(WBS_CBS!$M$5:$M$16,MATCH($D104,WBS_CBS!$A$5:$A$16,0)),"Yes")) | V104: =IF($D104="","",IFERROR(INDEX(WBS_CBS!$N$5:$N$16,MATCH($D104,WBS_CBS!$A$5:$A$16,0)),"Yes")) | W104: =IF($D104="","",IFERROR(INDEX(WBS_CBS!$K$5:$K$16,MATCH($D104,WBS_CBS!$A$5:$A$16,0)),"")) | X104: =IF($D104="","",IFERROR(INDEX(WBS_CBS!$F$5:$F$16,MATCH($D104,WBS_CBS!$A$5:$A$16,0)),"")) | AA104: =IF($D104="","",IFERROR(INDEX(WBS_CBS!$L$5:$L$16,MATCH($D104,WBS_CBS!$A$5:$A$16,0)),""))

Sheet Electrical_Estimate
A1: Electrical Estimate
A2: User input layer. Cost_Register must be rebuilt from these sheets via BuildCostRegister.
A4: Item ID | B4: Description | C4: Discipline | D4: WBS | E4: CBS | F4: Cost Category | G4: Cost Type | H4: Quantity | I4: Unit | J4: Unit Rate | K4: Currency | L4: FX Rate | M4: Base Cost | N4: Base Cost EUR | O4: Estimate Basis | P4: Accuracy Low % | Q4: Accuracy High % | R4: Low Cost | S4: Most Likely Cost | T4: High Cost | U4: Contingency Eligible | V4: Escalation Eligible | W4: Spend Category | X4: Phase | Y4: Start Month | Z4: End Month | AA4: Spend Curve | AB4: Notes
A5: EL-001 | B5: MV/LV substation package | C5: =IF($D5="","",IFERROR(INDEX(WBS_CBS!$E$5:$E$16,MATCH($D5,WBS_CBS!$A$5:$A$16,0)),"")) | D5: 7.0 | E5: =IF($D5="","",IFERROR(INDEX(WBS_CBS!$C$5:$C$16,MATCH($D5,WBS_CBS!$A$5:$A$16,0)),"")) | F5: =IF($D5="","",IFERROR(INDEX(WBS_CBS!$J$5:$J$16,MATCH($D5,WBS_CBS!$A$5:$A$16,0)),"")) | G5: Equipment | H5: 1 | I5: lot | J5: 1400000 | K5: EUR | L5: =IF($K5="","",IFERROR(INDEX(FX_Rates!$B$5:$B$14,MATCH($K5,FX_Rates!$A$5:$A$14,0)),"")) | M5: =IF(OR($H5="",$J5=""),"",$H5*$J5) | N5: =IF(OR($M5="",$L5=""),"",$M5*$L5) | O5: Class 3 | P5: =IF($O5="","",IFERROR(INDEX(Basis_of_Estimate!$C$5:$C$9,MATCH($O5,Basis_of_Estimate!$A$5:$A$9,0)),"")) | Q5: =IF($O5="","",IFERROR(INDEX(Basis_of_Estimate!$D$5:$D$9,MATCH($O5,Basis_of_Estimate!$A$5:$A$9,0)),"")) | R5: =IF($N5="","",$N5*(1+$P5)) | S5: =IF($N5="","",$N5) | T5: =IF($N5="","",$N5*(1+$Q5)) | U5: =IF($D5="","",IFERROR(INDEX(WBS_CBS!$M$5:$M$16,MATCH($D5,WBS_CBS!$A$5:$A$16,0)),"Yes")) | V5: =IF($D5="","",IFERROR(INDEX(WBS_CBS!$N$5:$N$16,MATCH($D5,WBS_CBS!$A$5:$A$16,0)),"Yes")) | W5: =IF($D5="","",IFERROR(INDEX(WBS_CBS!$K$5:$K$16,MATCH($D5,WBS_CBS!$A$5:$A$16,0)),"")) | X5: =IF($D5="","",IFERROR(INDEX(WBS_CBS!$F$5:$F$16,MATCH($D5,WBS_CBS!$A$5:$A$16,0)),"")) | Y5: 8 | Z5: 18 | AA5: =IF($D5="","",IFERROR(INDEX(WBS_CBS!$L$5:$L$16,MATCH($D5,WBS_CBS!$A$5:$A$16,0)),""))
A6: EL-002 | B6: MCC and distribution boards | C6: =IF($D6="","",IFERROR(INDEX(WBS_CBS!$E$5:$E$16,MATCH($D6,WBS_CBS!$A$5:$A$16,0)),"")) | D6: 7.0 | E6: =IF($D6="","",IFERROR(INDEX(WBS_CBS!$C$5:$C$16,MATCH($D6,WBS_CBS!$A$5:$A$16,0)),"")) | F6: =IF($D6="","",IFERROR(INDEX(WBS_CBS!$J$5:$J$16,MATCH($D6,WBS_CBS!$A$5:$A$16,0)),"")) | G6: Equipment | H6: 1 | I6: lot | J6: 1200000 | K6: EUR | L6: =IF($K6="","",IFERROR(INDEX(FX_Rates!$B$5:$B$14,MATCH($K6,FX_Rates!$A$5:$A$14,0)),"")) | M6: =IF(OR($H6="",$J6=""),"",$H6*$J6) | N6: =IF(OR($M6="",$L6=""),"",$M6*$L6) | O6: Class 3 | P6: =IF($O6="","",IFERROR(INDEX(Basis_of_Estimate!$C$5:$C$9,MATCH($O6,Basis_of_Estimate!$A$5:$A$9,0)),"")) | Q6: =IF($O6="","",IFERROR(INDEX(Basis_of_Estimate!$D$5:$D$9,MATCH($O6,Basis_of_Estimate!$A$5:$A$9,0)),"")) | R6: =IF($N6="","",$N6*(1+$P6)) | S6: =IF($N6="","",$N6) | T6: =IF($N6="","",$N6*(1+$Q6)) | U6: =IF($D6="","",IFERROR(INDEX(WBS_CBS!$M$5:$M$16,MATCH($D6,WBS_CBS!$A$5:$A$16,0)),"Yes")) | V6: =IF($D6="","",IFERROR(INDEX(WBS_CBS!$N$5:$N$16,MATCH($D6,WBS_CBS!$A$5:$A$16,0)),"Yes")) | W6: =IF($D6="","",IFERROR(INDEX(WBS_CBS!$K$5:$K$16,MATCH($D6,WBS_CBS!$A$5:$A$16,0)),"")) | X6: =IF($D6="","",IFERROR(INDEX(WBS_CBS!$F$5:$F$16,MATCH($D6,WBS_CBS!$A$5:$A$16,0)),"")) | Y6: 9 | Z6: 20 | AA6: =IF($D6="","",IFERROR(INDEX(WBS_CBS!$L$5:$L$16,MATCH($D6,WBS_CBS!$A$5:$A$16,0)),""))
A7: EL-003 | B7: Cable trays, cabling and termination | C7: =IF($D7="","",IFERROR(INDEX(WBS_CBS!$E$5:$E$16,MATCH($D7,WBS_CBS!$A$5:$A$16,0)),"")) | D7: 7.0 | E7: =IF($D7="","",IFERROR(INDEX(WBS_CBS!$C$5:$C$16,MATCH($D7,WBS_CBS!$A$5:$A$16,0)),"")) | F7: =IF($D7="","",IFERROR(INDEX(WBS_CBS!$J$5:$J$16,MATCH($D7,WBS_CBS!$A$5:$A$16,0)),"")) | G7: Bulk Material | H7: 1 | I7: lot | J7: 1600000 | K7: EUR | L7: =IF($K7="","",IFERROR(INDEX(FX_Rates!$B$5:$B$14,MATCH($K7,FX_Rates!$A$5:$A$14,0)),"")) | M7: =IF(OR($H7="",$J7=""),"",$H7*$J7) | N7: =IF(OR($M7="",$L7=""),"",$M7*$L7) | O7: Class 3 | P7: =IF($O7="","",IFERROR(INDEX(Basis_of_Estimate!$C$5:$C$9,MATCH($O7,Basis_of_Estimate!$A$5:$A$9,0)),"")) | Q7: =IF($O7="","",IFERROR(INDEX(Basis_of_Estimate!$D$5:$D$9,MATCH($O7,Basis_of_Estimate!$A$5:$A$9,0)),"")) | R7: =IF($N7="","",$N7*(1+$P7)) | S7: =IF($N7="","",$N7) | T7: =IF($N7="","",$N7*(1+$Q7)) | U7: =IF($D7="","",IFERROR(INDEX(WBS_CBS!$M$5:$M$16,MATCH($D7,WBS_CBS!$A$5:$A$16,0)),"Yes")) | V7: =IF($D7="","",IFERROR(INDEX(WBS_CBS!$N$5:$N$16,MATCH($D7,WBS_CBS!$A$5:$A$16,0)),"Yes")) | W7: =IF($D7="","",IFERROR(INDEX(WBS_CBS!$K$5:$K$16,MATCH($D7,WBS_CBS!$A$5:$A$16,0)),"")) | X7: =IF($D7="","",IFERROR(INDEX(WBS_CBS!$F$5:$F$16,MATCH($D7,WBS_CBS!$A$5:$A$16,0)),"")) | Y7: 15 | Z7: 30 | AA7: =IF($D7="","",IFERROR(INDEX(WBS_CBS!$L$5:$L$16,MATCH($D7,WBS_CBS!$A$5:$A$16,0)),""))
A8: EL-004 | B8: Lighting, earthing and small power | C8: =IF($D8="","",IFERROR(INDEX(WBS_CBS!$E$5:$E$16,MATCH($D8,WBS_CBS!$A$5:$A$16,0)),"")) | D8: 7.0 | E8: =IF($D8="","",IFERROR(INDEX(WBS_CBS!$C$5:$C$16,MATCH($D8,WBS_CBS!$A$5:$A$16,0)),"")) | F8: =IF($D8="","",IFERROR(INDEX(WBS_CBS!$J$5:$J$16,MATCH($D8,WBS_CBS!$A$5:$A$16,0)),"")) | G8: Construction | H8: 1 | I8: lot | J8: 800000 | K8: EUR | L8: =IF($K8="","",IFERROR(INDEX(FX_Rates!$B$5:$B$14,MATCH($K8,FX_Rates!$A$5:$A$14,0)),"")) | M8: =IF(OR($H8="",$J8=""),"",$H8*$J8) | N8: =IF(OR($M8="",$L8=""),"",$M8*$L8) | O8: Class 3 | P8: =IF($O8="","",IFERROR(INDEX(Basis_of_Estimate!$C$5:$C$9,MATCH($O8,Basis_of_Estimate!$A$5:$A$9,0)),"")) | Q8: =IF($O8="","",IFERROR(INDEX(Basis_of_Estimate!$D$5:$D$9,MATCH($O8,Basis_of_Estimate!$A$5:$A$9,0)),"")) | R8: =IF($N8="","",$N8*(1+$P8)) | S8: =IF($N8="","",$N8) | T8: =IF($N8="","",$N8*(1+$Q8)) | U8: =IF($D8="","",IFERROR(INDEX(WBS_CBS!$M$5:$M$16,MATCH($D8,WBS_CBS!$A$5:$A$16,0)),"Yes")) | V8: =IF($D8="","",IFERROR(INDEX(WBS_CBS!$N$5:$N$16,MATCH($D8,WBS_CBS!$A$5:$A$16,0)),"Yes")) | W8: =IF($D8="","",IFERROR(INDEX(WBS_CBS!$K$5:$K$16,MATCH($D8,WBS_CBS!$A$5:$A$16,0)),"")) | X8: =IF($D8="","",IFERROR(INDEX(WBS_CBS!$F$5:$F$16,MATCH($D8,WBS_CBS!$A$5:$A$16,0)),"")) | Y8: 18 | Z8: 31 | AA8: =IF($D8="","",IFERROR(INDEX(WBS_CBS!$L$5:$L$16,MATCH($D8,WBS_CBS!$A$5:$A$16,0)),""))
C9: =IF($D9="","",IFERROR(INDEX(WBS_CBS!$E$5:$E$16,MATCH($D9,WBS_CBS!$A$5:$A$16,0)),"")) | E9: =IF($D9="","",IFERROR(INDEX(WBS_CBS!$C$5:$C$16,MATCH($D9,WBS_CBS!$A$5:$A$16,0)),"")) | F9: =IF($D9="","",IFERROR(INDEX(WBS_CBS!$J$5:$J$16,MATCH($D9,WBS_CBS!$A$5:$A$16,0)),"")) | L9: =IF($K9="","",IFERROR(INDEX(FX_Rates!$B$5:$B$14,MATCH($K9,FX_Rates!$A$5:$A$14,0)),"")) | M9: =IF(OR($H9="",$J9=""),"",$H9*$J9) | N9: =IF(OR($M9="",$L9=""),"",$M9*$L9) | P9: =IF($O9="","",IFERROR(INDEX(Basis_of_Estimate!$C$5:$C$9,MATCH($O9,Basis_of_Estimate!$A$5:$A$9,0)),"")) | Q9: =IF($O9="","",IFERROR(INDEX(Basis_of_Estimate!$D$5:$D$9,MATCH($O9,Basis_of_Estimate!$A$5:$A$9,0)),"")) | R9: =IF($N9="","",$N9*(1+$P9)) | S9: =IF($N9="","",$N9) | T9: =IF($N9="","",$N9*(1+$Q9)) | U9: =IF($D9="","",IFERROR(INDEX(WBS_CBS!$M$5:$M$16,MATCH($D9,WBS_CBS!$A$5:$A$16,0)),"Yes")) | V9: =IF($D9="","",IFERROR(INDEX(WBS_CBS!$N$5:$N$16,MATCH($D9,WBS_CBS!$A$5:$A$16,0)),"Yes")) | W9: =IF($D9="","",IFERROR(INDEX(WBS_CBS!$K$5:$K$16,MATCH($D9,WBS_CBS!$A$5:$A$16,0)),"")) | X9: =IF($D9="","",IFERROR(INDEX(WBS_CBS!$F$5:$F$16,MATCH($D9,WBS_CBS!$A$5:$A$16,0)),"")) | AA9: =IF($D9="","",IFERROR(INDEX(WBS_CBS!$L$5:$L$16,MATCH($D9,WBS_CBS!$A$5:$A$16,0)),""))
C10: =IF($D10="","",IFERROR(INDEX(WBS_CBS!$E$5:$E$16,MATCH($D10,WBS_CBS!$A$5:$A$16,0)),"")) | E10: =IF($D10="","",IFERROR(INDEX(WBS_CBS!$C$5:$C$16,MATCH($D10,WBS_CBS!$A$5:$A$16,0)),"")) | F10: =IF($D10="","",IFERROR(INDEX(WBS_CBS!$J$5:$J$16,MATCH($D10,WBS_CBS!$A$5:$A$16,0)),"")) | L10: =IF($K10="","",IFERROR(INDEX(FX_Rates!$B$5:$B$14,MATCH($K10,FX_Rates!$A$5:$A$14,0)),"")) | M10: =IF(OR($H10="",$J10=""),"",$H10*$J10) | N10: =IF(OR($M10="",$L10=""),"",$M10*$L10) | P10: =IF($O10="","",IFERROR(INDEX(Basis_of_Estimate!$C$5:$C$9,MATCH($O10,Basis_of_Estimate!$A$5:$A$9,0)),"")) | Q10: =IF($O10="","",IFERROR(INDEX(Basis_of_Estimate!$D$5:$D$9,MATCH($O10,Basis_of_Estimate!$A$5:$A$9,0)),"")) | R10: =IF($N10="","",$N10*(1+$P10)) | S10: =IF($N10="","",$N10) | T10: =IF($N10="","",$N10*(1+$Q10)) | U10: =IF($D10="","",IFERROR(INDEX(WBS_CBS!$M$5:$M$16,MATCH($D10,WBS_CBS!$A$5:$A$16,0)),"Yes")) | V10: =IF($D10="","",IFERROR(INDEX(WBS_CBS!$N$5:$N$16,MATCH($D10,WBS_CBS!$A$5:$A$16,0)),"Yes")) | W10: =IF($D10="","",IFERROR(INDEX(WBS_CBS!$K$5:$K$16,MATCH($D10,WBS_CBS!$A$5:$A$16,0)),"")) | X10: =IF($D10="","",IFERROR(INDEX(WBS_CBS!$F$5:$F$16,MATCH($D10,WBS_CBS!$A$5:$A$16,0)),"")) | AA10: =IF($D10="","",IFERROR(INDEX(WBS_CBS!$L$5:$L$16,MATCH($D10,WBS_CBS!$A$5:$A$16,0)),""))
C11: =IF($D11="","",IFERROR(INDEX(WBS_CBS!$E$5:$E$16,MATCH($D11,WBS_CBS!$A$5:$A$16,0)),"")) | E11: =IF($D11="","",IFERROR(INDEX(WBS_CBS!$C$5:$C$16,MATCH($D11,WBS_CBS!$A$5:$A$16,0)),"")) | F11: =IF($D11="","",IFERROR(INDEX(WBS_CBS!$J$5:$J$16,MATCH($D11,WBS_CBS!$A$5:$A$16,0)),"")) | L11: =IF($K11="","",IFERROR(INDEX(FX_Rates!$B$5:$B$14,MATCH($K11,FX_Rates!$A$5:$A$14,0)),"")) | M11: =IF(OR($H11="",$J11=""),"",$H11*$J11) | N11: =IF(OR($M11="",$L11=""),"",$M11*$L11) | P11: =IF($O11="","",IFERROR(INDEX(Basis_of_Estimate!$C$5:$C$9,MATCH($O11,Basis_of_Estimate!$A$5:$A$9,0)),"")) | Q11: =IF($O11="","",IFERROR(INDEX(Basis_of_Estimate!$D$5:$D$9,MATCH($O11,Basis_of_Estimate!$A$5:$A$9,0)),"")) | R11: =IF($N11="","",$N11*(1+$P11)) | S11: =IF($N11="","",$N11) | T11: =IF($N11="","",$N11*(1+$Q11)) | U11: =IF($D11="","",IFERROR(INDEX(WBS_CBS!$M$5:$M$16,MATCH($D11,WBS_CBS!$A$5:$A$16,0)),"Yes")) | V11: =IF($D11="","",IFERROR(INDEX(WBS_CBS!$N$5:$N$16,MATCH($D11,WBS_CBS!$A$5:$A$16,0)),"Yes")) | W11: =IF($D11="","",IFERROR(INDEX(WBS_CBS!$K$5:$K$16,MATCH($D11,WBS_CBS!$A$5:$A$16,0)),"")) | X11: =IF($D11="","",IFERROR(INDEX(WBS_CBS!$F$5:$F$16,MATCH($D11,WBS_CBS!$A$5:$A$16,0)),"")) | AA11: =IF($D11="","",IFERROR(INDEX(WBS_CBS!$L$5:$L$16,MATCH($D11,WBS_CBS!$A$5:$A$16,0)),""))
C12: =IF($D12="","",IFERROR(INDEX(WBS_CBS!$E$5:$E$16,MATCH($D12,WBS_CBS!$A$5:$A$16,0)),"")) | E12: =IF($D12="","",IFERROR(INDEX(WBS_CBS!$C$5:$C$16,MATCH($D12,WBS_CBS!$A$5:$A$16,0)),"")) | F12: =IF($D12="","",IFERROR(INDEX(WBS_CBS!$J$5:$J$16,MATCH($D12,WBS_CBS!$A$5:$A$16,0)),"")) | L12: =IF($K12="","",IFERROR(INDEX(FX_Rates!$B$5:$B$14,MATCH($K12,FX_Rates!$A$5:$A$14,0)),"")) | M12: =IF(OR($H12="",$J12=""),"",$H12*$J12) | N12: =IF(OR($M12="",$L12=""),"",$M12*$L12) | P12: =IF($O12="","",IFERROR(INDEX(Basis_of_Estimate!$C$5:$C$9,MATCH($O12,Basis_of_Estimate!$A$5:$A$9,0)),"")) | Q12: =IF($O12="","",IFERROR(INDEX(Basis_of_Estimate!$D$5:$D$9,MATCH($O12,Basis_of_Estimate!$A$5:$A$9,0)),"")) | R12: =IF($N12="","",$N12*(1+$P12)) | S12: =IF($N12="","",$N12) | T12: =IF($N12="","",$N12*(1+$Q12)) | U12: =IF($D12="","",IFERROR(INDEX(WBS_CBS!$M$5:$M$16,MATCH($D12,WBS_CBS!$A$5:$A$16,0)),"Yes")) | V12: =IF($D12="","",IFERROR(INDEX(WBS_CBS!$N$5:$N$16,MATCH($D12,WBS_CBS!$A$5:$A$16,0)),"Yes")) | W12: =IF($D12="","",IFERROR(INDEX(WBS_CBS!$K$5:$K$16,MATCH($D12,WBS_CBS!$A$5:$A$16,0)),"")) | X12: =IF($D12="","",IFERROR(INDEX(WBS_CBS!$F$5:$F$16,MATCH($D12,WBS_CBS!$A$5:$A$16,0)),"")) | AA12: =IF($D12="","",IFERROR(INDEX(WBS_CBS!$L$5:$L$16,MATCH($D12,WBS_CBS!$A$5:$A$16,0)),""))
C13: =IF($D13="","",IFERROR(INDEX(WBS_CBS!$E$5:$E$16,MATCH($D13,WBS_CBS!$A$5:$A$16,0)),"")) | E13: =IF($D13="","",IFERROR(INDEX(WBS_CBS!$C$5:$C$16,MATCH($D13,WBS_CBS!$A$5:$A$16,0)),"")) | F13: =IF($D13="","",IFERROR(INDEX(WBS_CBS!$J$5:$J$16,MATCH($D13,WBS_CBS!$A$5:$A$16,0)),"")) | L13: =IF($K13="","",IFERROR(INDEX(FX_Rates!$B$5:$B$14,MATCH($K13,FX_Rates!$A$5:$A$14,0)),"")) | M13: =IF(OR($H13="",$J13=""),"",$H13*$J13) | N13: =IF(OR($M13="",$L13=""),"",$M13*$L13) | P13: =IF($O13="","",IFERROR(INDEX(Basis_of_Estimate!$C$5:$C$9,MATCH($O13,Basis_of_Estimate!$A$5:$A$9,0)),"")) | Q13: =IF($O13="","",IFERROR(INDEX(Basis_of_Estimate!$D$5:$D$9,MATCH($O13,Basis_of_Estimate!$A$5:$A$9,0)),"")) | R13: =IF($N13="","",$N13*(1+$P13)) | S13: =IF($N13="","",$N13) | T13: =IF($N13="","",$N13*(1+$Q13)) | U13: =IF($D13="","",IFERROR(INDEX(WBS_CBS!$M$5:$M$16,MATCH($D13,WBS_CBS!$A$5:$A$16,0)),"Yes")) | V13: =IF($D13="","",IFERROR(INDEX(WBS_CBS!$N$5:$N$16,MATCH($D13,WBS_CBS!$A$5:$A$16,0)),"Yes")) | W13: =IF($D13="","",IFERROR(INDEX(WBS_CBS!$K$5:$K$16,MATCH($D13,WBS_CBS!$A$5:$A$16,0)),"")) | X13: =IF($D13="","",IFERROR(INDEX(WBS_CBS!$F$5:$F$16,MATCH($D13,WBS_CBS!$A$5:$A$16,0)),"")) | AA13: =IF($D13="","",IFERROR(INDEX(WBS_CBS!$L$5:$L$16,MATCH($D13,WBS_CBS!$A$5:$A$16,0)),""))
C14: =IF($D14="","",IFERROR(INDEX(WBS_CBS!$E$5:$E$16,MATCH($D14,WBS_CBS!$A$5:$A$16,0)),"")) | E14: =IF($D14="","",IFERROR(INDEX(WBS_CBS!$C$5:$C$16,MATCH($D14,WBS_CBS!$A$5:$A$16,0)),"")) | F14: =IF($D14="","",IFERROR(INDEX(WBS_CBS!$J$5:$J$16,MATCH($D14,WBS_CBS!$A$5:$A$16,0)),"")) | L14: =IF($K14="","",IFERROR(INDEX(FX_Rates!$B$5:$B$14,MATCH($K14,FX_Rates!$A$5:$A$14,0)),"")) | M14: =IF(OR($H14="",$J14=""),"",$H14*$J14) | N14: =IF(OR($M14="",$L14=""),"",$M14*$L14) | P14: =IF($O14="","",IFERROR(INDEX(Basis_of_Estimate!$C$5:$C$9,MATCH($O14,Basis_of_Estimate!$A$5:$A$9,0)),"")) | Q14: =IF($O14="","",IFERROR(INDEX(Basis_of_Estimate!$D$5:$D$9,MATCH($O14,Basis_of_Estimate!$A$5:$A$9,0)),"")) | R14: =IF($N14="","",$N14*(1+$P14)) | S14: =IF($N14="","",$N14) | T14: =IF($N14="","",$N14*(1+$Q14)) | U14: =IF($D14="","",IFERROR(INDEX(WBS_CBS!$M$5:$M$16,MATCH($D14,WBS_CBS!$A$5:$A$16,0)),"Yes")) | V14: =IF($D14="","",IFERROR(INDEX(WBS_CBS!$N$5:$N$16,MATCH($D14,WBS_CBS!$A$5:$A$16,0)),"Yes")) | W14: =IF($D14="","",IFERROR(INDEX(WBS_CBS!$K$5:$K$16,MATCH($D14,WBS_CBS!$A$5:$A$16,0)),"")) | X14: =IF($D14="","",IFERROR(INDEX(WBS_CBS!$F$5:$F$16,MATCH($D14,WBS_CBS!$A$5:$A$16,0)),"")) | AA14: =IF($D14="","",IFERROR(INDEX(WBS_CBS!$L$5:$L$16,MATCH($D14,WBS_CBS!$A$5:$A$16,0)),""))
C15: =IF($D15="","",IFERROR(INDEX(WBS_CBS!$E$5:$E$16,MATCH($D15,WBS_CBS!$A$5:$A$16,0)),"")) | E15: =IF($D15="","",IFERROR(INDEX(WBS_CBS!$C$5:$C$16,MATCH($D15,WBS_CBS!$A$5:$A$16,0)),"")) | F15: =IF($D15="","",IFERROR(INDEX(WBS_CBS!$J$5:$J$16,MATCH($D15,WBS_CBS!$A$5:$A$16,0)),"")) | L15: =IF($K15="","",IFERROR(INDEX(FX_Rates!$B$5:$B$14,MATCH($K15,FX_Rates!$A$5:$A$14,0)),"")) | M15: =IF(OR($H15="",$J15=""),"",$H15*$J15) | N15: =IF(OR($M15="",$L15=""),"",$M15*$L15) | P15: =IF($O15="","",IFERROR(INDEX(Basis_of_Estimate!$C$5:$C$9,MATCH($O15,Basis_of_Estimate!$A$5:$A$9,0)),"")) | Q15: =IF($O15="","",IFERROR(INDEX(Basis_of_Estimate!$D$5:$D$9,MATCH($O15,Basis_of_Estimate!$A$5:$A$9,0)),"")) | R15: =IF($N15="","",$N15*(1+$P15)) | S15: =IF($N15="","",$N15) | T15: =IF($N15="","",$N15*(1+$Q15)) | U15: =IF($D15="","",IFERROR(INDEX(WBS_CBS!$M$5:$M$16,MATCH($D15,WBS_CBS!$A$5:$A$16,0)),"Yes")) | V15: =IF($D15="","",IFERROR(INDEX(WBS_CBS!$N$5:$N$16,MATCH($D15,WBS_CBS!$A$5:$A$16,0)),"Yes")) | W15: =IF($D15="","",IFERROR(INDEX(WBS_CBS!$K$5:$K$16,MATCH($D15,WBS_CBS!$A$5:$A$16,0)),"")) | X15: =IF($D15="","",IFERROR(INDEX(WBS_CBS!$F$5:$F$16,MATCH($D15,WBS_CBS!$A$5:$A$16,0)),"")) | AA15: =IF($D15="","",IFERROR(INDEX(WBS_CBS!$L$5:$L$16,MATCH($D15,WBS_CBS!$A$5:$A$16,0)),""))
C16: =IF($D16="","",IFERROR(INDEX(WBS_CBS!$E$5:$E$16,MATCH($D16,WBS_CBS!$A$5:$A$16,0)),"")) | E16: =IF($D16="","",IFERROR(INDEX(WBS_CBS!$C$5:$C$16,MATCH($D16,WBS_CBS!$A$5:$A$16,0)),"")) | F16: =IF($D16="","",IFERROR(INDEX(WBS_CBS!$J$5:$J$16,MATCH($D16,WBS_CBS!$A$5:$A$16,0)),"")) | L16: =IF($K16="","",IFERROR(INDEX(FX_Rates!$B$5:$B$14,MATCH($K16,FX_Rates!$A$5:$A$14,0)),"")) | M16: =IF(OR($H16="",$J16=""),"",$H16*$J16) | N16: =IF(OR($M16="",$L16=""),"",$M16*$L16) | P16: =IF($O16="","",IFERROR(INDEX(Basis_of_Estimate!$C$5:$C$9,MATCH($O16,Basis_of_Estimate!$A$5:$A$9,0)),"")) | Q16: =IF($O16="","",IFERROR(INDEX(Basis_of_Estimate!$D$5:$D$9,MATCH($O16,Basis_of_Estimate!$A$5:$A$9,0)),"")) | R16: =IF($N16="","",$N16*(1+$P16)) | S16: =IF($N16="","",$N16) | T16: =IF($N16="","",$N16*(1+$Q16)) | U16: =IF($D16="","",IFERROR(INDEX(WBS_CBS!$M$5:$M$16,MATCH($D16,WBS_CBS!$A$5:$A$16,0)),"Yes")) | V16: =IF($D16="","",IFERROR(INDEX(WBS_CBS!$N$5:$N$16,MATCH($D16,WBS_CBS!$A$5:$A$16,0)),"Yes")) | W16: =IF($D16="","",IFERROR(INDEX(WBS_CBS!$K$5:$K$16,MATCH($D16,WBS_CBS!$A$5:$A$16,0)),"")) | X16: =IF($D16="","",IFERROR(INDEX(WBS_CBS!$F$5:$F$16,MATCH($D16,WBS_CBS!$A$5:$A$16,0)),"")) | AA16: =IF($D16="","",IFERROR(INDEX(WBS_CBS!$L$5:$L$16,MATCH($D16,WBS_CBS!$A$5:$A$16,0)),""))
C17: =IF($D17="","",IFERROR(INDEX(WBS_CBS!$E$5:$E$16,MATCH($D17,WBS_CBS!$A$5:$A$16,0)),"")) | E17: =IF($D17="","",IFERROR(INDEX(WBS_CBS!$C$5:$C$16,MATCH($D17,WBS_CBS!$A$5:$A$16,0)),"")) | F17: =IF($D17="","",IFERROR(INDEX(WBS_CBS!$J$5:$J$16,MATCH($D17,WBS_CBS!$A$5:$A$16,0)),"")) | L17: =IF($K17="","",IFERROR(INDEX(FX_Rates!$B$5:$B$14,MATCH($K17,FX_Rates!$A$5:$A$14,0)),"")) | M17: =IF(OR($H17="",$J17=""),"",$H17*$J17) | N17: =IF(OR($M17="",$L17=""),"",$M17*$L17) | P17: =IF($O17="","",IFERROR(INDEX(Basis_of_Estimate!$C$5:$C$9,MATCH($O17,Basis_of_Estimate!$A$5:$A$9,0)),"")) | Q17: =IF($O17="","",IFERROR(INDEX(Basis_of_Estimate!$D$5:$D$9,MATCH($O17,Basis_of_Estimate!$A$5:$A$9,0)),"")) | R17: =IF($N17="","",$N17*(1+$P17)) | S17: =IF($N17="","",$N17) | T17: =IF($N17="","",$N17*(1+$Q17)) | U17: =IF($D17="","",IFERROR(INDEX(WBS_CBS!$M$5:$M$16,MATCH($D17,WBS_CBS!$A$5:$A$16,0)),"Yes")) | V17: =IF($D17="","",IFERROR(INDEX(WBS_CBS!$N$5:$N$16,MATCH($D17,WBS_CBS!$A$5:$A$16,0)),"Yes")) | W17: =IF($D17="","",IFERROR(INDEX(WBS_CBS!$K$5:$K$16,MATCH($D17,WBS_CBS!$A$5:$A$16,0)),"")) | X17: =IF($D17="","",IFERROR(INDEX(WBS_CBS!$F$5:$F$16,MATCH($D17,WBS_CBS!$A$5:$A$16,0)),"")) | AA17: =IF($D17="","",IFERROR(INDEX(WBS_CBS!$L$5:$L$16,MATCH($D17,WBS_CBS!$A$5:$A$16,0)),""))
C18: =IF($D18="","",IFERROR(INDEX(WBS_CBS!$E$5:$E$16,MATCH($D18,WBS_CBS!$A$5:$A$16,0)),"")) | E18: =IF($D18="","",IFERROR(INDEX(WBS_CBS!$C$5:$C$16,MATCH($D18,WBS_CBS!$A$5:$A$16,0)),"")) | F18: =IF($D18="","",IFERROR(INDEX(WBS_CBS!$J$5:$J$16,MATCH($D18,WBS_CBS!$A$5:$A$16,0)),"")) | L18: =IF($K18="","",IFERROR(INDEX(FX_Rates!$B$5:$B$14,MATCH($K18,FX_Rates!$A$5:$A$14,0)),"")) | M18: =IF(OR($H18="",$J18=""),"",$H18*$J18) | N18: =IF(OR($M18="",$L18=""),"",$M18*$L18) | P18: =IF($O18="","",IFERROR(INDEX(Basis_of_Estimate!$C$5:$C$9,MATCH($O18,Basis_of_Estimate!$A$5:$A$9,0)),"")) | Q18: =IF($O18="","",IFERROR(INDEX(Basis_of_Estimate!$D$5:$D$9,MATCH($O18,Basis_of_Estimate!$A$5:$A$9,0)),"")) | R18: =IF($N18="","",$N18*(1+$P18)) | S18: =IF($N18="","",$N18) | T18: =IF($N18="","",$N18*(1+$Q18)) | U18: =IF($D18="","",IFERROR(INDEX(WBS_CBS!$M$5:$M$16,MATCH($D18,WBS_CBS!$A$5:$A$16,0)),"Yes")) | V18: =IF($D18="","",IFERROR(INDEX(WBS_CBS!$N$5:$N$16,MATCH($D18,WBS_CBS!$A$5:$A$16,0)),"Yes")) | W18: =IF($D18="","",IFERROR(INDEX(WBS_CBS!$K$5:$K$16,MATCH($D18,WBS_CBS!$A$5:$A$16,0)),"")) | X18: =IF($D18="","",IFERROR(INDEX(WBS_CBS!$F$5:$F$16,MATCH($D18,WBS_CBS!$A$5:$A$16,0)),"")) | AA18: =IF($D18="","",IFERROR(INDEX(WBS_CBS!$L$5:$L$16,MATCH($D18,WBS_CBS!$A$5:$A$16,0)),""))
C19: =IF($D19="","",IFERROR(INDEX(WBS_CBS!$E$5:$E$16,MATCH($D19,WBS_CBS!$A$5:$A$16,0)),"")) | E19: =IF($D19="","",IFERROR(INDEX(WBS_CBS!$C$5:$C$16,MATCH($D19,WBS_CBS!$A$5:$A$16,0)),"")) | F19: =IF($D19="","",IFERROR(INDEX(WBS_CBS!$J$5:$J$16,MATCH($D19,WBS_CBS!$A$5:$A$16,0)),"")) | L19: =IF($K19="","",IFERROR(INDEX(FX_Rates!$B$5:$B$14,MATCH($K19,FX_Rates!$A$5:$A$14,0)),"")) | M19: =IF(OR($H19="",$J19=""),"",$H19*$J19) | N19: =IF(OR($M19="",$L19=""),"",$M19*$L19) | P19: =IF($O19="","",IFERROR(INDEX(Basis_of_Estimate!$C$5:$C$9,MATCH($O19,Basis_of_Estimate!$A$5:$A$9,0)),"")) | Q19: =IF($O19="","",IFERROR(INDEX(Basis_of_Estimate!$D$5:$D$9,MATCH($O19,Basis_of_Estimate!$A$5:$A$9,0)),"")) | R19: =IF($N19="","",$N19*(1+$P19)) | S19: =IF($N19="","",$N19) | T19: =IF($N19="","",$N19*(1+$Q19)) | U19: =IF($D19="","",IFERROR(INDEX(WBS_CBS!$M$5:$M$16,MATCH($D19,WBS_CBS!$A$5:$A$16,0)),"Yes")) | V19: =IF($D19="","",IFERROR(INDEX(WBS_CBS!$N$5:$N$16,MATCH($D19,WBS_CBS!$A$5:$A$16,0)),"Yes")) | W19: =IF($D19="","",IFERROR(INDEX(WBS_CBS!$K$5:$K$16,MATCH($D19,WBS_CBS!$A$5:$A$16,0)),"")) | X19: =IF($D19="","",IFERROR(INDEX(WBS_CBS!$F$5:$F$16,MATCH($D19,WBS_CBS!$A$5:$A$16,0)),"")) | AA19: =IF($D19="","",IFERROR(INDEX(WBS_CBS!$L$5:$L$16,MATCH($D19,WBS_CBS!$A$5:$A$16,0)),""))
C20: =IF($D20="","",IFERROR(INDEX(WBS_CBS!$E$5:$E$16,MATCH($D20,WBS_CBS!$A$5:$A$16,0)),"")) | E20: =IF($D20="","",IFERROR(INDEX(WBS_CBS!$C$5:$C$16,MATCH($D20,WBS_CBS!$A$5:$A$16,0)),"")) | F20: =IF($D20="","",IFERROR(INDEX(WBS_CBS!$J$5:$J$16,MATCH($D20,WBS_CBS!$A$5:$A$16,0)),"")) | L20: =IF($K20="","",IFERROR(INDEX(FX_Rates!$B$5:$B$14,MATCH($K20,FX_Rates!$A$5:$A$14,0)),"")) | M20: =IF(OR($H20="",$J20=""),"",$H20*$J20) | N20: =IF(OR($M20="",$L20=""),"",$M20*$L20) | P20: =IF($O20="","",IFERROR(INDEX(Basis_of_Estimate!$C$5:$C$9,MATCH($O20,Basis_of_Estimate!$A$5:$A$9,0)),"")) | Q20: =IF($O20="","",IFERROR(INDEX(Basis_of_Estimate!$D$5:$D$9,MATCH($O20,Basis_of_Estimate!$A$5:$A$9,0)),"")) | R20: =IF($N20="","",$N20*(1+$P20)) | S20: =IF($N20="","",$N20) | T20: =IF($N20="","",$N20*(1+$Q20)) | U20: =IF($D20="","",IFERROR(INDEX(WBS_CBS!$M$5:$M$16,MATCH($D20,WBS_CBS!$A$5:$A$16,0)),"Yes")) | V20: =IF($D20="","",IFERROR(INDEX(WBS_CBS!$N$5:$N$16,MATCH($D20,WBS_CBS!$A$5:$A$16,0)),"Yes")) | W20: =IF($D20="","",IFERROR(INDEX(WBS_CBS!$K$5:$K$16,MATCH($D20,WBS_CBS!$A$5:$A$16,0)),"")) | X20: =IF($D20="","",IFERROR(INDEX(WBS_CBS!$F$5:$F$16,MATCH($D20,WBS_CBS!$A$5:$A$16,0)),"")) | AA20: =IF($D20="","",IFERROR(INDEX(WBS_CBS!$L$5:$L$16,MATCH($D20,WBS_CBS!$A$5:$A$16,0)),""))
... C104: =IF($D104="","",IFERROR(INDEX(WBS_CBS!$E$5:$E$16,MATCH($D104,WBS_CBS!$A$5:$A$16,0)),"")) | E104: =IF($D104="","",IFERROR(INDEX(WBS_CBS!$C$5:$C$16,MATCH($D104,WBS_CBS!$A$5:$A$16,0)),"")) | F104: =IF($D104="","",IFERROR(INDEX(WBS_CBS!$J$5:$J$16,MATCH($D104,WBS_CBS!$A$5:$A$16,0)),"")) | L104: =IF($K104="","",IFERROR(INDEX(FX_Rates!$B$5:$B$14,MATCH($K104,FX_Rates!$A$5:$A$14,0)),"")) | M104: =IF(OR($H104="",$J104=""),"",$H104*$J104) | N104: =IF(OR($M104="",$L104=""),"",$M104*$L104) | P104: =IF($O104="","",IFERROR(INDEX(Basis_of_Estimate!$C$5:$C$9,MATCH($O104,Basis_of_Estimate!$A$5:$A$9,0)),"")) | Q104: =IF($O104="","",IFERROR(INDEX(Basis_of_Estimate!$D$5:$D$9,MATCH($O104,Basis_of_Estimate!$A$5:$A$9,0)),"")) | R104: =IF($N104="","",$N104*(1+$P104)) | S104: =IF($N104="","",$N104) | T104: =IF($N104="","",$N104*(1+$Q104)) | U104: =IF($D104="","",IFERROR(INDEX(WBS_CBS!$M$5:$M$16,MATCH($D104,WBS_CBS!$A$5:$A$16,0)),"Yes")) | V104: =IF($D104="","",IFERROR(INDEX(WBS_CBS!$N$5:$N$16,MATCH($D104,WBS_CBS!$A$5:$A$16,0)),"Yes")) | W104: =IF($D104="","",IFERROR(INDEX(WBS_CBS!$K$5:$K$16,MATCH($D104,WBS_CBS!$A$5:$A$16,0)),"")) | X104: =IF($D104="","",IFERROR(INDEX(WBS_CBS!$F$5:$F$16,MATCH($D104,WBS_CBS!$A$5:$A$16,0)),"")) | AA104: =IF($D104="","",IFERROR(INDEX(WBS_CBS!$L$5:$L$16,MATCH($D104,WBS_CBS!$A$5:$A$16,0)),""))

Sheet Instrumentation_Automation
A1: Instrumentation Automation
A2: User input layer. Cost_Register must be rebuilt from these sheets via BuildCostRegister.
A4: Item ID | B4: Description | C4: Discipline | D4: WBS | E4: CBS | F4: Cost Category | G4: Cost Type | H4: Quantity | I4: Unit | J4: Unit Rate | K4: Currency | L4: FX Rate | M4: Base Cost | N4: Base Cost EUR | O4: Estimate Basis | P4: Accuracy Low % | Q4: Accuracy High % | R4: Low Cost | S4: Most Likely Cost | T4: High Cost | U4: Contingency Eligible | V4: Escalation Eligible | W4: Spend Category | X4: Phase | Y4: Start Month | Z4: End Month | AA4: Spend Curve | AB4: Notes
A5: IA-001 | B5: PLC/DCS hardware and software | C5: =IF($D5="","",IFERROR(INDEX(WBS_CBS!$E$5:$E$16,MATCH($D5,WBS_CBS!$A$5:$A$16,0)),"")) | D5: 8.0 | E5: =IF($D5="","",IFERROR(INDEX(WBS_CBS!$C$5:$C$16,MATCH($D5,WBS_CBS!$A$5:$A$16,0)),"")) | F5: =IF($D5="","",IFERROR(INDEX(WBS_CBS!$J$5:$J$16,MATCH($D5,WBS_CBS!$A$5:$A$16,0)),"")) | G5: Equipment | H5: 1 | I5: lot | J5: 1200000 | K5: EUR | L5: =IF($K5="","",IFERROR(INDEX(FX_Rates!$B$5:$B$14,MATCH($K5,FX_Rates!$A$5:$A$14,0)),"")) | M5: =IF(OR($H5="",$J5=""),"",$H5*$J5) | N5: =IF(OR($M5="",$L5=""),"",$M5*$L5) | O5: Class 3 | P5: =IF($O5="","",IFERROR(INDEX(Basis_of_Estimate!$C$5:$C$9,MATCH($O5,Basis_of_Estimate!$A$5:$A$9,0)),"")) | Q5: =IF($O5="","",IFERROR(INDEX(Basis_of_Estimate!$D$5:$D$9,MATCH($O5,Basis_of_Estimate!$A$5:$A$9,0)),"")) | R5: =IF($N5="","",$N5*(1+$P5)) | S5: =IF($N5="","",$N5) | T5: =IF($N5="","",$N5*(1+$Q5)) | U5: =IF($D5="","",IFERROR(INDEX(WBS_CBS!$M$5:$M$16,MATCH($D5,WBS_CBS!$A$5:$A$16,0)),"Yes")) | V5: =IF($D5="","",IFERROR(INDEX(WBS_CBS!$N$5:$N$16,MATCH($D5,WBS_CBS!$A$5:$A$16,0)),"Yes")) | W5: =IF($D5="","",IFERROR(INDEX(WBS_CBS!$K$5:$K$16,MATCH($D5,WBS_CBS!$A$5:$A$16,0)),"")) | X5: =IF($D5="","",IFERROR(INDEX(WBS_CBS!$F$5:$F$16,MATCH($D5,WBS_CBS!$A$5:$A$16,0)),"")) | Y5: 8 | Z5: 22 | AA5: =IF($D5="","",IFERROR(INDEX(WBS_CBS!$L$5:$L$16,MATCH($D5,WBS_CBS!$A$5:$A$16,0)),""))
A6: IA-002 | B6: Field instrumentation and valves | C6: =IF($D6="","",IFERROR(INDEX(WBS_CBS!$E$5:$E$16,MATCH($D6,WBS_CBS!$A$5:$A$16,0)),"")) | D6: 8.0 | E6: =IF($D6="","",IFERROR(INDEX(WBS_CBS!$C$5:$C$16,MATCH($D6,WBS_CBS!$A$5:$A$16,0)),"")) | F6: =IF($D6="","",IFERROR(INDEX(WBS_CBS!$J$5:$J$16,MATCH($D6,WBS_CBS!$A$5:$A$16,0)),"")) | G6: Equipment | H6: 1 | I6: lot | J6: 1000000 | K6: EUR | L6: =IF($K6="","",IFERROR(INDEX(FX_Rates!$B$5:$B$14,MATCH($K6,FX_Rates!$A$5:$A$14,0)),"")) | M6: =IF(OR($H6="",$J6=""),"",$H6*$J6) | N6: =IF(OR($M6="",$L6=""),"",$M6*$L6) | O6: Class 3 | P6: =IF($O6="","",IFERROR(INDEX(Basis_of_Estimate!$C$5:$C$9,MATCH($O6,Basis_of_Estimate!$A$5:$A$9,0)),"")) | Q6: =IF($O6="","",IFERROR(INDEX(Basis_of_Estimate!$D$5:$D$9,MATCH($O6,Basis_of_Estimate!$A$5:$A$9,0)),"")) | R6: =IF($N6="","",$N6*(1+$P6)) | S6: =IF($N6="","",$N6) | T6: =IF($N6="","",$N6*(1+$Q6)) | U6: =IF($D6="","",IFERROR(INDEX(WBS_CBS!$M$5:$M$16,MATCH($D6,WBS_CBS!$A$5:$A$16,0)),"Yes")) | V6: =IF($D6="","",IFERROR(INDEX(WBS_CBS!$N$5:$N$16,MATCH($D6,WBS_CBS!$A$5:$A$16,0)),"Yes")) | W6: =IF($D6="","",IFERROR(INDEX(WBS_CBS!$K$5:$K$16,MATCH($D6,WBS_CBS!$A$5:$A$16,0)),"")) | X6: =IF($D6="","",IFERROR(INDEX(WBS_CBS!$F$5:$F$16,MATCH($D6,WBS_CBS!$A$5:$A$16,0)),"")) | Y6: 10 | Z6: 25 | AA6: =IF($D6="","",IFERROR(INDEX(WBS_CBS!$L$5:$L$16,MATCH($D6,WBS_CBS!$A$5:$A$16,0)),""))
A7: IA-003 | B7: Automation engineering and commissioning | C7: =IF($D7="","",IFERROR(INDEX(WBS_CBS!$E$5:$E$16,MATCH($D7,WBS_CBS!$A$5:$A$16,0)),"")) | D7: 8.0 | E7: =IF($D7="","",IFERROR(INDEX(WBS_CBS!$C$5:$C$16,MATCH($D7,WBS_CBS!$A$5:$A$16,0)),"")) | F7: =IF($D7="","",IFERROR(INDEX(WBS_CBS!$J$5:$J$16,MATCH($D7,WBS_CBS!$A$5:$A$16,0)),"")) | G7: Engineering | H7: 1 | I7: lot | J7: 800000 | K7: EUR | L7: =IF($K7="","",IFERROR(INDEX(FX_Rates!$B$5:$B$14,MATCH($K7,FX_Rates!$A$5:$A$14,0)),"")) | M7: =IF(OR($H7="",$J7=""),"",$H7*$J7) | N7: =IF(OR($M7="",$L7=""),"",$M7*$L7) | O7: Class 3 | P7: =IF($O7="","",IFERROR(INDEX(Basis_of_Estimate!$C$5:$C$9,MATCH($O7,Basis_of_Estimate!$A$5:$A$9,0)),"")) | Q7: =IF($O7="","",IFERROR(INDEX(Basis_of_Estimate!$D$5:$D$9,MATCH($O7,Basis_of_Estimate!$A$5:$A$9,0)),"")) | R7: =IF($N7="","",$N7*(1+$P7)) | S7: =IF($N7="","",$N7) | T7: =IF($N7="","",$N7*(1+$Q7)) | U7: =IF($D7="","",IFERROR(INDEX(WBS_CBS!$M$5:$M$16,MATCH($D7,WBS_CBS!$A$5:$A$16,0)),"Yes")) | V7: =IF($D7="","",IFERROR(INDEX(WBS_CBS!$N$5:$N$16,MATCH($D7,WBS_CBS!$A$5:$A$16,0)),"Yes")) | W7: =IF($D7="","",IFERROR(INDEX(WBS_CBS!$K$5:$K$16,MATCH($D7,WBS_CBS!$A$5:$A$16,0)),"")) | X7: =IF($D7="","",IFERROR(INDEX(WBS_CBS!$F$5:$F$16,MATCH($D7,WBS_CBS!$A$5:$A$16,0)),"")) | Y7: 4 | Z7: 35 | AA7: =IF($D7="","",IFERROR(INDEX(WBS_CBS!$L$5:$L$16,MATCH($D7,WBS_CBS!$A$5:$A$16,0)),""))
C8: =IF($D8="","",IFERROR(INDEX(WBS_CBS!$E$5:$E$16,MATCH($D8,WBS_CBS!$A$5:$A$16,0)),"")) | E8: =IF($D8="","",IFERROR(INDEX(WBS_CBS!$C$5:$C$16,MATCH($D8,WBS_CBS!$A$5:$A$16,0)),"")) | F8: =IF($D8="","",IFERROR(INDEX(WBS_CBS!$J$5:$J$16,MATCH($D8,WBS_CBS!$A$5:$A$16,0)),"")) | L8: =IF($K8="","",IFERROR(INDEX(FX_Rates!$B$5:$B$14,MATCH($K8,FX_Rates!$A$5:$A$14,0)),"")) | M8: =IF(OR($H8="",$J8=""),"",$H8*$J8) | N8: =IF(OR($M8="",$L8=""),"",$M8*$L8) | P8: =IF($O8="","",IFERROR(INDEX(Basis_of_Estimate!$C$5:$C$9,MATCH($O8,Basis_of_Estimate!$A$5:$A$9,0)),"")) | Q8: =IF($O8="","",IFERROR(INDEX(Basis_of_Estimate!$D$5:$D$9,MATCH($O8,Basis_of_Estimate!$A$5:$A$9,0)),"")) | R8: =IF($N8="","",$N8*(1+$P8)) | S8: =IF($N8="","",$N8) | T8: =IF($N8="","",$N8*(1+$Q8)) | U8: =IF($D8="","",IFERROR(INDEX(WBS_CBS!$M$5:$M$16,MATCH($D8,WBS_CBS!$A$5:$A$16,0)),"Yes")) | V8: =IF($D8="","",IFERROR(INDEX(WBS_CBS!$N$5:$N$16,MATCH($D8,WBS_CBS!$A$5:$A$16,0)),"Yes")) | W8: =IF($D8="","",IFERROR(INDEX(WBS_CBS!$K$5:$K$16,MATCH($D8,WBS_CBS!$A$5:$A$16,0)),"")) | X8: =IF($D8="","",IFERROR(INDEX(WBS_CBS!$F$5:$F$16,MATCH($D8,WBS_CBS!$A$5:$A$16,0)),"")) | AA8: =IF($D8="","",IFERROR(INDEX(WBS_CBS!$L$5:$L$16,MATCH($D8,WBS_CBS!$A$5:$A$16,0)),""))
C9: =IF($D9="","",IFERROR(INDEX(WBS_CBS!$E$5:$E$16,MATCH($D9,WBS_CBS!$A$5:$A$16,0)),"")) | E9: =IF($D9="","",IFERROR(INDEX(WBS_CBS!$C$5:$C$16,MATCH($D9,WBS_CBS!$A$5:$A$16,0)),"")) | F9: =IF($D9="","",IFERROR(INDEX(WBS_CBS!$J$5:$J$16,MATCH($D9,WBS_CBS!$A$5:$A$16,0)),"")) | L9: =IF($K9="","",IFERROR(INDEX(FX_Rates!$B$5:$B$14,MATCH($K9,FX_Rates!$A$5:$A$14,0)),"")) | M9: =IF(OR($H9="",$J9=""),"",$H9*$J9) | N9: =IF(OR($M9="",$L9=""),"",$M9*$L9) | P9: =IF($O9="","",IFERROR(INDEX(Basis_of_Estimate!$C$5:$C$9,MATCH($O9,Basis_of_Estimate!$A$5:$A$9,0)),"")) | Q9: =IF($O9="","",IFERROR(INDEX(Basis_of_Estimate!$D$5:$D$9,MATCH($O9,Basis_of_Estimate!$A$5:$A$9,0)),"")) | R9: =IF($N9="","",$N9*(1+$P9)) | S9: =IF($N9="","",$N9) | T9: =IF($N9="","",$N9*(1+$Q9)) | U9: =IF($D9="","",IFERROR(INDEX(WBS_CBS!$M$5:$M$16,MATCH($D9,WBS_CBS!$A$5:$A$16,0)),"Yes")) | V9: =IF($D9="","",IFERROR(INDEX(WBS_CBS!$N$5:$N$16,MATCH($D9,WBS_CBS!$A$5:$A$16,0)),"Yes")) | W9: =IF($D9="","",IFERROR(INDEX(WBS_CBS!$K$5:$K$16,MATCH($D9,WBS_CBS!$A$5:$A$16,0)),"")) | X9: =IF($D9="","",IFERROR(INDEX(WBS_CBS!$F$5:$F$16,MATCH($D9,WBS_CBS!$A$5:$A$16,0)),"")) | AA9: =IF($D9="","",IFERROR(INDEX(WBS_CBS!$L$5:$L$16,MATCH($D9,WBS_CBS!$A$5:$A$16,0)),""))
C10: =IF($D10="","",IFERROR(INDEX(WBS_CBS!$E$5:$E$16,MATCH($D10,WBS_CBS!$A$5:$A$16,0)),"")) | E10: =IF($D10="","",IFERROR(INDEX(WBS_CBS!$C$5:$C$16,MATCH($D10,WBS_CBS!$A$5:$A$16,0)),"")) | F10: =IF($D10="","",IFERROR(INDEX(WBS_CBS!$J$5:$J$16,MATCH($D10,WBS_CBS!$A$5:$A$16,0)),"")) | L10: =IF($K10="","",IFERROR(INDEX(FX_Rates!$B$5:$B$14,MATCH($K10,FX_Rates!$A$5:$A$14,0)),"")) | M10: =IF(OR($H10="",$J10=""),"",$H10*$J10) | N10: =IF(OR($M10="",$L10=""),"",$M10*$L10) | P10: =IF($O10="","",IFERROR(INDEX(Basis_of_Estimate!$C$5:$C$9,MATCH($O10,Basis_of_Estimate!$A$5:$A$9,0)),"")) | Q10: =IF($O10="","",IFERROR(INDEX(Basis_of_Estimate!$D$5:$D$9,MATCH($O10,Basis_of_Estimate!$A$5:$A$9,0)),"")) | R10: =IF($N10="","",$N10*(1+$P10)) | S10: =IF($N10="","",$N10) | T10: =IF($N10="","",$N10*(1+$Q10)) | U10: =IF($D10="","",IFERROR(INDEX(WBS_CBS!$M$5:$M$16,MATCH($D10,WBS_CBS!$A$5:$A$16,0)),"Yes")) | V10: =IF($D10="","",IFERROR(INDEX(WBS_CBS!$N$5:$N$16,MATCH($D10,WBS_CBS!$A$5:$A$16,0)),"Yes")) | W10: =IF($D10="","",IFERROR(INDEX(WBS_CBS!$K$5:$K$16,MATCH($D10,WBS_CBS!$A$5:$A$16,0)),"")) | X10: =IF($D10="","",IFERROR(INDEX(WBS_CBS!$F$5:$F$16,MATCH($D10,WBS_CBS!$A$5:$A$16,0)),"")) | AA10: =IF($D10="","",IFERROR(INDEX(WBS_CBS!$L$5:$L$16,MATCH($D10,WBS_CBS!$A$5:$A$16,0)),""))
C11: =IF($D11="","",IFERROR(INDEX(WBS_CBS!$E$5:$E$16,MATCH($D11,WBS_CBS!$A$5:$A$16,0)),"")) | E11: =IF($D11="","",IFERROR(INDEX(WBS_CBS!$C$5:$C$16,MATCH($D11,WBS_CBS!$A$5:$A$16,0)),"")) | F11: =IF($D11="","",IFERROR(INDEX(WBS_CBS!$J$5:$J$16,MATCH($D11,WBS_CBS!$A$5:$A$16,0)),"")) | L11: =IF($K11="","",IFERROR(INDEX(FX_Rates!$B$5:$B$14,MATCH($K11,FX_Rates!$A$5:$A$14,0)),"")) | M11: =IF(OR($H11="",$J11=""),"",$H11*$J11) | N11: =IF(OR($M11="",$L11=""),"",$M11*$L11) | P11: =IF($O11="","",IFERROR(INDEX(Basis_of_Estimate!$C$5:$C$9,MATCH($O11,Basis_of_Estimate!$A$5:$A$9,0)),"")) | Q11: =IF($O11="","",IFERROR(INDEX(Basis_of_Estimate!$D$5:$D$9,MATCH($O11,Basis_of_Estimate!$A$5:$A$9,0)),"")) | R11: =IF($N11="","",$N11*(1+$P11)) | S11: =IF($N11="","",$N11) | T11: =IF($N11="","",$N11*(1+$Q11)) | U11: =IF($D11="","",IFERROR(INDEX(WBS_CBS!$M$5:$M$16,MATCH($D11,WBS_CBS!$A$5:$A$16,0)),"Yes")) | V11: =IF($D11="","",IFERROR(INDEX(WBS_CBS!$N$5:$N$16,MATCH($D11,WBS_CBS!$A$5:$A$16,0)),"Yes")) | W11: =IF($D11="","",IFERROR(INDEX(WBS_CBS!$K$5:$K$16,MATCH($D11,WBS_CBS!$A$5:$A$16,0)),"")) | X11: =IF($D11="","",IFERROR(INDEX(WBS_CBS!$F$5:$F$16,MATCH($D11,WBS_CBS!$A$5:$A$16,0)),"")) | AA11: =IF($D11="","",IFERROR(INDEX(WBS_CBS!$L$5:$L$16,MATCH($D11,WBS_CBS!$A$5:$A$16,0)),""))
C12: =IF($D12="","",IFERROR(INDEX(WBS_CBS!$E$5:$E$16,MATCH($D12,WBS_CBS!$A$5:$A$16,0)),"")) | E12: =IF($D12="","",IFERROR(INDEX(WBS_CBS!$C$5:$C$16,MATCH($D12,WBS_CBS!$A$5:$A$16,0)),"")) | F12: =IF($D12="","",IFERROR(INDEX(WBS_CBS!$J$5:$J$16,MATCH($D12,WBS_CBS!$A$5:$A$16,0)),"")) | L12: =IF($K12="","",IFERROR(INDEX(FX_Rates!$B$5:$B$14,MATCH($K12,FX_Rates!$A$5:$A$14,0)),"")) | M12: =IF(OR($H12="",$J12=""),"",$H12*$J12) | N12: =IF(OR($M12="",$L12=""),"",$M12*$L12) | P12: =IF($O12="","",IFERROR(INDEX(Basis_of_Estimate!$C$5:$C$9,MATCH($O12,Basis_of_Estimate!$A$5:$A$9,0)),"")) | Q12: =IF($O12="","",IFERROR(INDEX(Basis_of_Estimate!$D$5:$D$9,MATCH($O12,Basis_of_Estimate!$A$5:$A$9,0)),"")) | R12: =IF($N12="","",$N12*(1+$P12)) | S12: =IF($N12="","",$N12) | T12: =IF($N12="","",$N12*(1+$Q12)) | U12: =IF($D12="","",IFERROR(INDEX(WBS_CBS!$M$5:$M$16,MATCH($D12,WBS_CBS!$A$5:$A$16,0)),"Yes")) | V12: =IF($D12="","",IFERROR(INDEX(WBS_CBS!$N$5:$N$16,MATCH($D12,WBS_CBS!$A$5:$A$16,0)),"Yes")) | W12: =IF($D12="","",IFERROR(INDEX(WBS_CBS!$K$5:$K$16,MATCH($D12,WBS_CBS!$A$5:$A$16,0)),"")) | X12: =IF($D12="","",IFERROR(INDEX(WBS_CBS!$F$5:$F$16,MATCH($D12,WBS_CBS!$A$5:$A$16,0)),"")) | AA12: =IF($D12="","",IFERROR(INDEX(WBS_CBS!$L$5:$L$16,MATCH($D12,WBS_CBS!$A$5:$A$16,0)),""))
C13: =IF($D13="","",IFERROR(INDEX(WBS_CBS!$E$5:$E$16,MATCH($D13,WBS_CBS!$A$5:$A$16,0)),"")) | E13: =IF($D13="","",IFERROR(INDEX(WBS_CBS!$C$5:$C$16,MATCH($D13,WBS_CBS!$A$5:$A$16,0)),"")) | F13: =IF($D13="","",IFERROR(INDEX(WBS_CBS!$J$5:$J$16,MATCH($D13,WBS_CBS!$A$5:$A$16,0)),"")) | L13: =IF($K13="","",IFERROR(INDEX(FX_Rates!$B$5:$B$14,MATCH($K13,FX_Rates!$A$5:$A$14,0)),"")) | M13: =IF(OR($H13="",$J13=""),"",$H13*$J13) | N13: =IF(OR($M13="",$L13=""),"",$M13*$L13) | P13: =IF($O13="","",IFERROR(INDEX(Basis_of_Estimate!$C$5:$C$9,MATCH($O13,Basis_of_Estimate!$A$5:$A$9,0)),"")) | Q13: =IF($O13="","",IFERROR(INDEX(Basis_of_Estimate!$D$5:$D$9,MATCH($O13,Basis_of_Estimate!$A$5:$A$9,0)),"")) | R13: =IF($N13="","",$N13*(1+$P13)) | S13: =IF($N13="","",$N13) | T13: =IF($N13="","",$N13*(1+$Q13)) | U13: =IF($D13="","",IFERROR(INDEX(WBS_CBS!$M$5:$M$16,MATCH($D13,WBS_CBS!$A$5:$A$16,0)),"Yes")) | V13: =IF($D13="","",IFERROR(INDEX(WBS_CBS!$N$5:$N$16,MATCH($D13,WBS_CBS!$A$5:$A$16,0)),"Yes")) | W13: =IF($D13="","",IFERROR(INDEX(WBS_CBS!$K$5:$K$16,MATCH($D13,WBS_CBS!$A$5:$A$16,0)),"")) | X13: =IF($D13="","",IFERROR(INDEX(WBS_CBS!$F$5:$F$16,MATCH($D13,WBS_CBS!$A$5:$A$16,0)),"")) | AA13: =IF($D13="","",IFERROR(INDEX(WBS_CBS!$L$5:$L$16,MATCH($D13,WBS_CBS!$A$5:$A$16,0)),""))
C14: =IF($D14="","",IFERROR(INDEX(WBS_CBS!$E$5:$E$16,MATCH($D14,WBS_CBS!$A$5:$A$16,0)),"")) | E14: =IF($D14="","",IFERROR(INDEX(WBS_CBS!$C$5:$C$16,MATCH($D14,WBS_CBS!$A$5:$A$16,0)),"")) | F14: =IF($D14="","",IFERROR(INDEX(WBS_CBS!$J$5:$J$16,MATCH($D14,WBS_CBS!$A$5:$A$16,0)),"")) | L14: =IF($K14="","",IFERROR(INDEX(FX_Rates!$B$5:$B$14,MATCH($K14,FX_Rates!$A$5:$A$14,0)),"")) | M14: =IF(OR($H14="",$J14=""),"",$H14*$J14) | N14: =IF(OR($M14="",$L14=""),"",$M14*$L14) | P14: =IF($O14="","",IFERROR(INDEX(Basis_of_Estimate!$C$5:$C$9,MATCH($O14,Basis_of_Estimate!$A$5:$A$9,0)),"")) | Q14: =IF($O14="","",IFERROR(INDEX(Basis_of_Estimate!$D$5:$D$9,MATCH($O14,Basis_of_Estimate!$A$5:$A$9,0)),"")) | R14: =IF($N14="","",$N14*(1+$P14)) | S14: =IF($N14="","",$N14) | T14: =IF($N14="","",$N14*(1+$Q14)) | U14: =IF($D14="","",IFERROR(INDEX(WBS_CBS!$M$5:$M$16,MATCH($D14,WBS_CBS!$A$5:$A$16,0)),"Yes")) | V14: =IF($D14="","",IFERROR(INDEX(WBS_CBS!$N$5:$N$16,MATCH($D14,WBS_CBS!$A$5:$A$16,0)),"Yes")) | W14: =IF($D14="","",IFERROR(INDEX(WBS_CBS!$K$5:$K$16,MATCH($D14,WBS_CBS!$A$5:$A$16,0)),"")) | X14: =IF($D14="","",IFERROR(INDEX(WBS_CBS!$F$5:$F$16,MATCH($D14,WBS_CBS!$A$5:$A$16,0)),"")) | AA14: =IF($D14="","",IFERROR(INDEX(WBS_CBS!$L$5:$L$16,MATCH($D14,WBS_CBS!$A$5:$A$16,0)),""))
C15: =IF($D15="","",IFERROR(INDEX(WBS_CBS!$E$5:$E$16,MATCH($D15,WBS_CBS!$A$5:$A$16,0)),"")) | E15: =IF($D15="","",IFERROR(INDEX(WBS_CBS!$C$5:$C$16,MATCH($D15,WBS_CBS!$A$5:$A$16,0)),"")) | F15: =IF($D15="","",IFERROR(INDEX(WBS_CBS!$J$5:$J$16,MATCH($D15,WBS_CBS!$A$5:$A$16,0)),"")) | L15: =IF($K15="","",IFERROR(INDEX(FX_Rates!$B$5:$B$14,MATCH($K15,FX_Rates!$A$5:$A$14,0)),"")) | M15: =IF(OR($H15="",$J15=""),"",$H15*$J15) | N15: =IF(OR($M15="",$L15=""),"",$M15*$L15) | P15: =IF($O15="","",IFERROR(INDEX(Basis_of_Estimate!$C$5:$C$9,MATCH($O15,Basis_of_Estimate!$A$5:$A$9,0)),"")) | Q15: =IF($O15="","",IFERROR(INDEX(Basis_of_Estimate!$D$5:$D$9,MATCH($O15,Basis_of_Estimate!$A$5:$A$9,0)),"")) | R15: =IF($N15="","",$N15*(1+$P15)) | S15: =IF($N15="","",$N15) | T15: =IF($N15="","",$N15*(1+$Q15)) | U15: =IF($D15="","",IFERROR(INDEX(WBS_CBS!$M$5:$M$16,MATCH($D15,WBS_CBS!$A$5:$A$16,0)),"Yes")) | V15: =IF($D15="","",IFERROR(INDEX(WBS_CBS!$N$5:$N$16,MATCH($D15,WBS_CBS!$A$5:$A$16,0)),"Yes")) | W15: =IF($D15="","",IFERROR(INDEX(WBS_CBS!$K$5:$K$16,MATCH($D15,WBS_CBS!$A$5:$A$16,0)),"")) | X15: =IF($D15="","",IFERROR(INDEX(WBS_CBS!$F$5:$F$16,MATCH($D15,WBS_CBS!$A$5:$A$16,0)),"")) | AA15: =IF($D15="","",IFERROR(INDEX(WBS_CBS!$L$5:$L$16,MATCH($D15,WBS_CBS!$A$5:$A$16,0)),""))
C16: =IF($D16="","",IFERROR(INDEX(WBS_CBS!$E$5:$E$16,MATCH($D16,WBS_CBS!$A$5:$A$16,0)),"")) | E16: =IF($D16="","",IFERROR(INDEX(WBS_CBS!$C$5:$C$16,MATCH($D16,WBS_CBS!$A$5:$A$16,0)),"")) | F16: =IF($D16="","",IFERROR(INDEX(WBS_CBS!$J$5:$J$16,MATCH($D16,WBS_CBS!$A$5:$A$16,0)),"")) | L16: =IF($K16="","",IFERROR(INDEX(FX_Rates!$B$5:$B$14,MATCH($K16,FX_Rates!$A$5:$A$14,0)),"")) | M16: =IF(OR($H16="",$J16=""),"",$H16*$J16) | N16: =IF(OR($M16="",$L16=""),"",$M16*$L16) | P16: =IF($O16="","",IFERROR(INDEX(Basis_of_Estimate!$C$5:$C$9,MATCH($O16,Basis_of_Estimate!$A$5:$A$9,0)),"")) | Q16: =IF($O16="","",IFERROR(INDEX(Basis_of_Estimate!$D$5:$D$9,MATCH($O16,Basis_of_Estimate!$A$5:$A$9,0)),"")) | R16: =IF($N16="","",$N16*(1+$P16)) | S16: =IF($N16="","",$N16) | T16: =IF($N16="","",$N16*(1+$Q16)) | U16: =IF($D16="","",IFERROR(INDEX(WBS_CBS!$M$5:$M$16,MATCH($D16,WBS_CBS!$A$5:$A$16,0)),"Yes")) | V16: =IF($D16="","",IFERROR(INDEX(WBS_CBS!$N$5:$N$16,MATCH($D16,WBS_CBS!$A$5:$A$16,0)),"Yes")) | W16: =IF($D16="","",IFERROR(INDEX(WBS_CBS!$K$5:$K$16,MATCH($D16,WBS_CBS!$A$5:$A$16,0)),"")) | X16: =IF($D16="","",IFERROR(INDEX(WBS_CBS!$F$5:$F$16,MATCH($D16,WBS_CBS!$A$5:$A$16,0)),"")) | AA16: =IF($D16="","",IFERROR(INDEX(WBS_CBS!$L$5:$L$16,MATCH($D16,WBS_CBS!$A$5:$A$16,0)),""))
C17: =IF($D17="","",IFERROR(INDEX(WBS_CBS!$E$5:$E$16,MATCH($D17,WBS_CBS!$A$5:$A$16,0)),"")) | E17: =IF($D17="","",IFERROR(INDEX(WBS_CBS!$C$5:$C$16,MATCH($D17,WBS_CBS!$A$5:$A$16,0)),"")) | F17: =IF($D17="","",IFERROR(INDEX(WBS_CBS!$J$5:$J$16,MATCH($D17,WBS_CBS!$A$5:$A$16,0)),"")) | L17: =IF($K17="","",IFERROR(INDEX(FX_Rates!$B$5:$B$14,MATCH($K17,FX_Rates!$A$5:$A$14,0)),"")) | M17: =IF(OR($H17="",$J17=""),"",$H17*$J17) | N17: =IF(OR($M17="",$L17=""),"",$M17*$L17) | P17: =IF($O17="","",IFERROR(INDEX(Basis_of_Estimate!$C$5:$C$9,MATCH($O17,Basis_of_Estimate!$A$5:$A$9,0)),"")) | Q17: =IF($O17="","",IFERROR(INDEX(Basis_of_Estimate!$D$5:$D$9,MATCH($O17,Basis_of_Estimate!$A$5:$A$9,0)),"")) | R17: =IF($N17="","",$N17*(1+$P17)) | S17: =IF($N17="","",$N17) | T17: =IF($N17="","",$N17*(1+$Q17)) | U17: =IF($D17="","",IFERROR(INDEX(WBS_CBS!$M$5:$M$16,MATCH($D17,WBS_CBS!$A$5:$A$16,0)),"Yes")) | V17: =IF($D17="","",IFERROR(INDEX(WBS_CBS!$N$5:$N$16,MATCH($D17,WBS_CBS!$A$5:$A$16,0)),"Yes")) | W17: =IF($D17="","",IFERROR(INDEX(WBS_CBS!$K$5:$K$16,MATCH($D17,WBS_CBS!$A$5:$A$16,0)),"")) | X17: =IF($D17="","",IFERROR(INDEX(WBS_CBS!$F$5:$F$16,MATCH($D17,WBS_CBS!$A$5:$A$16,0)),"")) | AA17: =IF($D17="","",IFERROR(INDEX(WBS_CBS!$L$5:$L$16,MATCH($D17,WBS_CBS!$A$5:$A$16,0)),""))
C18: =IF($D18="","",IFERROR(INDEX(WBS_CBS!$E$5:$E$16,MATCH($D18,WBS_CBS!$A$5:$A$16,0)),"")) | E18: =IF($D18="","",IFERROR(INDEX(WBS_CBS!$C$5:$C$16,MATCH($D18,WBS_CBS!$A$5:$A$16,0)),"")) | F18: =IF($D18="","",IFERROR(INDEX(WBS_CBS!$J$5:$J$16,MATCH($D18,WBS_CBS!$A$5:$A$16,0)),"")) | L18: =IF($K18="","",IFERROR(INDEX(FX_Rates!$B$5:$B$14,MATCH($K18,FX_Rates!$A$5:$A$14,0)),"")) | M18: =IF(OR($H18="",$J18=""),"",$H18*$J18) | N18: =IF(OR($M18="",$L18=""),"",$M18*$L18) | P18: =IF($O18="","",IFERROR(INDEX(Basis_of_Estimate!$C$5:$C$9,MATCH($O18,Basis_of_Estimate!$A$5:$A$9,0)),"")) | Q18: =IF($O18="","",IFERROR(INDEX(Basis_of_Estimate!$D$5:$D$9,MATCH($O18,Basis_of_Estimate!$A$5:$A$9,0)),"")) | R18: =IF($N18="","",$N18*(1+$P18)) | S18: =IF($N18="","",$N18) | T18: =IF($N18="","",$N18*(1+$Q18)) | U18: =IF($D18="","",IFERROR(INDEX(WBS_CBS!$M$5:$M$16,MATCH($D18,WBS_CBS!$A$5:$A$16,0)),"Yes")) | V18: =IF($D18="","",IFERROR(INDEX(WBS_CBS!$N$5:$N$16,MATCH($D18,WBS_CBS!$A$5:$A$16,0)),"Yes")) | W18: =IF($D18="","",IFERROR(INDEX(WBS_CBS!$K$5:$K$16,MATCH($D18,WBS_CBS!$A$5:$A$16,0)),"")) | X18: =IF($D18="","",IFERROR(INDEX(WBS_CBS!$F$5:$F$16,MATCH($D18,WBS_CBS!$A$5:$A$16,0)),"")) | AA18: =IF($D18="","",IFERROR(INDEX(WBS_CBS!$L$5:$L$16,MATCH($D18,WBS_CBS!$A$5:$A$16,0)),""))
C19: =IF($D19="","",IFERROR(INDEX(WBS_CBS!$E$5:$E$16,MATCH($D19,WBS_CBS!$A$5:$A$16,0)),"")) | E19: =IF($D19="","",IFERROR(INDEX(WBS_CBS!$C$5:$C$16,MATCH($D19,WBS_CBS!$A$5:$A$16,0)),"")) | F19: =IF($D19="","",IFERROR(INDEX(WBS_CBS!$J$5:$J$16,MATCH($D19,WBS_CBS!$A$5:$A$16,0)),"")) | L19: =IF($K19="","",IFERROR(INDEX(FX_Rates!$B$5:$B$14,MATCH($K19,FX_Rates!$A$5:$A$14,0)),"")) | M19: =IF(OR($H19="",$J19=""),"",$H19*$J19) | N19: =IF(OR($M19="",$L19=""),"",$M19*$L19) | P19: =IF($O19="","",IFERROR(INDEX(Basis_of_Estimate!$C$5:$C$9,MATCH($O19,Basis_of_Estimate!$A$5:$A$9,0)),"")) | Q19: =IF($O19="","",IFERROR(INDEX(Basis_of_Estimate!$D$5:$D$9,MATCH($O19,Basis_of_Estimate!$A$5:$A$9,0)),"")) | R19: =IF($N19="","",$N19*(1+$P19)) | S19: =IF($N19="","",$N19) | T19: =IF($N19="","",$N19*(1+$Q19)) | U19: =IF($D19="","",IFERROR(INDEX(WBS_CBS!$M$5:$M$16,MATCH($D19,WBS_CBS!$A$5:$A$16,0)),"Yes")) | V19: =IF($D19="","",IFERROR(INDEX(WBS_CBS!$N$5:$N$16,MATCH($D19,WBS_CBS!$A$5:$A$16,0)),"Yes")) | W19: =IF($D19="","",IFERROR(INDEX(WBS_CBS!$K$5:$K$16,MATCH($D19,WBS_CBS!$A$5:$A$16,0)),"")) | X19: =IF($D19="","",IFERROR(INDEX(WBS_CBS!$F$5:$F$16,MATCH($D19,WBS_CBS!$A$5:$A$16,0)),"")) | AA19: =IF($D19="","",IFERROR(INDEX(WBS_CBS!$L$5:$L$16,MATCH($D19,WBS_CBS!$A$5:$A$16,0)),""))
... C104: =IF($D104="","",IFERROR(INDEX(WBS_CBS!$E$5:$E$16,MATCH($D104,WBS_CBS!$A$5:$A$16,0)),"")) | E104: =IF($D104="","",IFERROR(INDEX(WBS_CBS!$C$5:$C$16,MATCH($D104,WBS_CBS!$A$5:$A$16,0)),"")) | F104: =IF($D104="","",IFERROR(INDEX(WBS_CBS!$J$5:$J$16,MATCH($D104,WBS_CBS!$A$5:$A$16,0)),"")) | L104: =IF($K104="","",IFERROR(INDEX(FX_Rates!$B$5:$B$14,MATCH($K104,FX_Rates!$A$5:$A$14,0)),"")) | M104: =IF(OR($H104="",$J104=""),"",$H104*$J104) | N104: =IF(OR($M104="",$L104=""),"",$M104*$L104) | P104: =IF($O104="","",IFERROR(INDEX(Basis_of_Estimate!$C$5:$C$9,MATCH($O104,Basis_of_Estimate!$A$5:$A$9,0)),"")) | Q104: =IF($O104="","",IFERROR(INDEX(Basis_of_Estimate!$D$5:$D$9,MATCH($O104,Basis_of_Estimate!$A$5:$A$9,0)),"")) | R104: =IF($N104="","",$N104*(1+$P104)) | S104: =IF($N104="","",$N104) | T104: =IF($N104="","",$N104*(1+$Q104)) | U104: =IF($D104="","",IFERROR(INDEX(WBS_CBS!$M$5:$M$16,MATCH($D104,WBS_CBS!$A$5:$A$16,0)),"Yes")) | V104: =IF($D104="","",IFERROR(INDEX(WBS_CBS!$N$5:$N$16,MATCH($D104,WBS_CBS!$A$5:$A$16,0)),"Yes")) | W104: =IF($D104="","",IFERROR(INDEX(WBS_CBS!$K$5:$K$16,MATCH($D104,WBS_CBS!$A$5:$A$16,0)),"")) | X104: =IF($D104="","",IFERROR(INDEX(WBS_CBS!$F$5:$F$16,MATCH($D104,WBS_CBS!$A$5:$A$16,0)),"")) | AA104: =IF($D104="","",IFERROR(INDEX(WBS_CBS!$L$5:$L$16,MATCH($D104,WBS_CBS!$A$5:$A$16,0)),""))

Sheet Bulk_Materials_QTO
A1: Bulk Materials QTO
A2: User input layer. Cost_Register must be rebuilt from these sheets via BuildCostRegister.
A4: Item ID | B4: Description | C4: Discipline | D4: WBS | E4: CBS | F4: Cost Category | G4: Cost Type | H4: Quantity | I4: Unit | J4: Unit Rate | K4: Currency | L4: FX Rate | M4: Base Cost | N4: Base Cost EUR | O4: Estimate Basis | P4: Accuracy Low % | Q4: Accuracy High % | R4: Low Cost | S4: Most Likely Cost | T4: High Cost | U4: Contingency Eligible | V4: Escalation Eligible | W4: Spend Category | X4: Phase | Y4: Start Month | Z4: End Month | AA4: Spend Curve | AB4: Notes
A5: BM-001 | B5: Process piping supply | C5: =IF($D5="","",IFERROR(INDEX(WBS_CBS!$E$5:$E$16,MATCH($D5,WBS_CBS!$A$5:$A$16,0)),"")) | D5: 5.0 | E5: =IF($D5="","",IFERROR(INDEX(WBS_CBS!$C$5:$C$16,MATCH($D5,WBS_CBS!$A$5:$A$16,0)),"")) | F5: =IF($D5="","",IFERROR(INDEX(WBS_CBS!$J$5:$J$16,MATCH($D5,WBS_CBS!$A$5:$A$16,0)),"")) | G5: Bulk Material | H5: 1 | I5: lot | J5: 2100000 | K5: EUR | L5: =IF($K5="","",IFERROR(INDEX(FX_Rates!$B$5:$B$14,MATCH($K5,FX_Rates!$A$5:$A$14,0)),"")) | M5: =IF(OR($H5="",$J5=""),"",$H5*$J5) | N5: =IF(OR($M5="",$L5=""),"",$M5*$L5) | O5: Class 3 | P5: =IF($O5="","",IFERROR(INDEX(Basis_of_Estimate!$C$5:$C$9,MATCH($O5,Basis_of_Estimate!$A$5:$A$9,0)),"")) | Q5: =IF($O5="","",IFERROR(INDEX(Basis_of_Estimate!$D$5:$D$9,MATCH($O5,Basis_of_Estimate!$A$5:$A$9,0)),"")) | R5: =IF($N5="","",$N5*(1+$P5)) | S5: =IF($N5="","",$N5) | T5: =IF($N5="","",$N5*(1+$Q5)) | U5: =IF($D5="","",IFERROR(INDEX(WBS_CBS!$M$5:$M$16,MATCH($D5,WBS_CBS!$A$5:$A$16,0)),"Yes")) | V5: =IF($D5="","",IFERROR(INDEX(WBS_CBS!$N$5:$N$16,MATCH($D5,WBS_CBS!$A$5:$A$16,0)),"Yes")) | W5: =IF($D5="","",IFERROR(INDEX(WBS_CBS!$K$5:$K$16,MATCH($D5,WBS_CBS!$A$5:$A$16,0)),"")) | X5: =IF($D5="","",IFERROR(INDEX(WBS_CBS!$F$5:$F$16,MATCH($D5,WBS_CBS!$A$5:$A$16,0)),"")) | Y5: 10 | Z5: 25 | AA5: =IF($D5="","",IFERROR(INDEX(WBS_CBS!$L$5:$L$16,MATCH($D5,WBS_CBS!$A$5:$A$16,0)),""))
A6: BM-002 | B6: Manual and control valves | C6: =IF($D6="","",IFERROR(INDEX(WBS_CBS!$E$5:$E$16,MATCH($D6,WBS_CBS!$A$5:$A$16,0)),"")) | D6: 5.0 | E6: =IF($D6="","",IFERROR(INDEX(WBS_CBS!$C$5:$C$16,MATCH($D6,WBS_CBS!$A$5:$A$16,0)),"")) | F6: =IF($D6="","",IFERROR(INDEX(WBS_CBS!$J$5:$J$16,MATCH($D6,WBS_CBS!$A$5:$A$16,0)),"")) | G6: Bulk Material | H6: 1 | I6: lot | J6: 1100000 | K6: EUR | L6: =IF($K6="","",IFERROR(INDEX(FX_Rates!$B$5:$B$14,MATCH($K6,FX_Rates!$A$5:$A$14,0)),"")) | M6: =IF(OR($H6="",$J6=""),"",$H6*$J6) | N6: =IF(OR($M6="",$L6=""),"",$M6*$L6) | O6: Class 3 | P6: =IF($O6="","",IFERROR(INDEX(Basis_of_Estimate!$C$5:$C$9,MATCH($O6,Basis_of_Estimate!$A$5:$A$9,0)),"")) | Q6: =IF($O6="","",IFERROR(INDEX(Basis_of_Estimate!$D$5:$D$9,MATCH($O6,Basis_of_Estimate!$A$5:$A$9,0)),"")) | R6: =IF($N6="","",$N6*(1+$P6)) | S6: =IF($N6="","",$N6) | T6: =IF($N6="","",$N6*(1+$Q6)) | U6: =IF($D6="","",IFERROR(INDEX(WBS_CBS!$M$5:$M$16,MATCH($D6,WBS_CBS!$A$5:$A$16,0)),"Yes")) | V6: =IF($D6="","",IFERROR(INDEX(WBS_CBS!$N$5:$N$16,MATCH($D6,WBS_CBS!$A$5:$A$16,0)),"Yes")) | W6: =IF($D6="","",IFERROR(INDEX(WBS_CBS!$K$5:$K$16,MATCH($D6,WBS_CBS!$A$5:$A$16,0)),"")) | X6: =IF($D6="","",IFERROR(INDEX(WBS_CBS!$F$5:$F$16,MATCH($D6,WBS_CBS!$A$5:$A$16,0)),"")) | Y6: 9 | Z6: 24 | AA6: =IF($D6="","",IFERROR(INDEX(WBS_CBS!$L$5:$L$16,MATCH($D6,WBS_CBS!$A$5:$A$16,0)),""))
A7: BM-003 | B7: Insulation, painting and tracing | C7: =IF($D7="","",IFERROR(INDEX(WBS_CBS!$E$5:$E$16,MATCH($D7,WBS_CBS!$A$5:$A$16,0)),"")) | D7: 5.0 | E7: =IF($D7="","",IFERROR(INDEX(WBS_CBS!$C$5:$C$16,MATCH($D7,WBS_CBS!$A$5:$A$16,0)),"")) | F7: =IF($D7="","",IFERROR(INDEX(WBS_CBS!$J$5:$J$16,MATCH($D7,WBS_CBS!$A$5:$A$16,0)),"")) | G7: Bulk Material | H7: 1 | I7: lot | J7: 800000 | K7: EUR | L7: =IF($K7="","",IFERROR(INDEX(FX_Rates!$B$5:$B$14,MATCH($K7,FX_Rates!$A$5:$A$14,0)),"")) | M7: =IF(OR($H7="",$J7=""),"",$H7*$J7) | N7: =IF(OR($M7="",$L7=""),"",$M7*$L7) | O7: Class 3 | P7: =IF($O7="","",IFERROR(INDEX(Basis_of_Estimate!$C$5:$C$9,MATCH($O7,Basis_of_Estimate!$A$5:$A$9,0)),"")) | Q7: =IF($O7="","",IFERROR(INDEX(Basis_of_Estimate!$D$5:$D$9,MATCH($O7,Basis_of_Estimate!$A$5:$A$9,0)),"")) | R7: =IF($N7="","",$N7*(1+$P7)) | S7: =IF($N7="","",$N7) | T7: =IF($N7="","",$N7*(1+$Q7)) | U7: =IF($D7="","",IFERROR(INDEX(WBS_CBS!$M$5:$M$16,MATCH($D7,WBS_CBS!$A$5:$A$16,0)),"Yes")) | V7: =IF($D7="","",IFERROR(INDEX(WBS_CBS!$N$5:$N$16,MATCH($D7,WBS_CBS!$A$5:$A$16,0)),"Yes")) | W7: =IF($D7="","",IFERROR(INDEX(WBS_CBS!$K$5:$K$16,MATCH($D7,WBS_CBS!$A$5:$A$16,0)),"")) | X7: =IF($D7="","",IFERROR(INDEX(WBS_CBS!$F$5:$F$16,MATCH($D7,WBS_CBS!$A$5:$A$16,0)),"")) | Y7: 18 | Z7: 33 | AA7: =IF($D7="","",IFERROR(INDEX(WBS_CBS!$L$5:$L$16,MATCH($D7,WBS_CBS!$A$5:$A$16,0)),""))
C8: =IF($D8="","",IFERROR(INDEX(WBS_CBS!$E$5:$E$16,MATCH($D8,WBS_CBS!$A$5:$A$16,0)),"")) | E8: =IF($D8="","",IFERROR(INDEX(WBS_CBS!$C$5:$C$16,MATCH($D8,WBS_CBS!$A$5:$A$16,0)),"")) | F8: =IF($D8="","",IFERROR(INDEX(WBS_CBS!$J$5:$J$16,MATCH($D8,WBS_CBS!$A$5:$A$16,0)),"")) | L8: =IF($K8="","",IFERROR(INDEX(FX_Rates!$B$5:$B$14,MATCH($K8,FX_Rates!$A$5:$A$14,0)),"")) | M8: =IF(OR($H8="",$J8=""),"",$H8*$J8) | N8: =IF(OR($M8="",$L8=""),"",$M8*$L8) | P8: =IF($O8="","",IFERROR(INDEX(Basis_of_Estimate!$C$5:$C$9,MATCH($O8,Basis_of_Estimate!$A$5:$A$9,0)),"")) | Q8: =IF($O8="","",IFERROR(INDEX(Basis_of_Estimate!$D$5:$D$9,MATCH($O8,Basis_of_Estimate!$A$5:$A$9,0)),"")) | R8: =IF($N8="","",$N8*(1+$P8)) | S8: =IF($N8="","",$N8) | T8: =IF($N8="","",$N8*(1+$Q8)) | U8: =IF($D8="","",IFERROR(INDEX(WBS_CBS!$M$5:$M$16,MATCH($D8,WBS_CBS!$A$5:$A$16,0)),"Yes")) | V8: =IF($D8="","",IFERROR(INDEX(WBS_CBS!$N$5:$N$16,MATCH($D8,WBS_CBS!$A$5:$A$16,0)),"Yes")) | W8: =IF($D8="","",IFERROR(INDEX(WBS_CBS!$K$5:$K$16,MATCH($D8,WBS_CBS!$A$5:$A$16,0)),"")) | X8: =IF($D8="","",IFERROR(INDEX(WBS_CBS!$F$5:$F$16,MATCH($D8,WBS_CBS!$A$5:$A$16,0)),"")) | AA8: =IF($D8="","",IFERROR(INDEX(WBS_CBS!$L$5:$L$16,MATCH($D8,WBS_CBS!$A$5:$A$16,0)),""))
C9: =IF($D9="","",IFERROR(INDEX(WBS_CBS!$E$5:$E$16,MATCH($D9,WBS_CBS!$A$5:$A$16,0)),"")) | E9: =IF($D9="","",IFERROR(INDEX(WBS_CBS!$C$5:$C$16,MATCH($D9,WBS_CBS!$A$5:$A$16,0)),"")) | F9: =IF($D9="","",IFERROR(INDEX(WBS_CBS!$J$5:$J$16,MATCH($D9,WBS_CBS!$A$5:$A$16,0)),"")) | L9: =IF($K9="","",IFERROR(INDEX(FX_Rates!$B$5:$B$14,MATCH($K9,FX_Rates!$A$5:$A$14,0)),"")) | M9: =IF(OR($H9="",$J9=""),"",$H9*$J9) | N9: =IF(OR($M9="",$L9=""),"",$M9*$L9) | P9: =IF($O9="","",IFERROR(INDEX(Basis_of_Estimate!$C$5:$C$9,MATCH($O9,Basis_of_Estimate!$A$5:$A$9,0)),"")) | Q9: =IF($O9="","",IFERROR(INDEX(Basis_of_Estimate!$D$5:$D$9,MATCH($O9,Basis_of_Estimate!$A$5:$A$9,0)),"")) | R9: =IF($N9="","",$N9*(1+$P9)) | S9: =IF($N9="","",$N9) | T9: =IF($N9="","",$N9*(1+$Q9)) | U9: =IF($D9="","",IFERROR(INDEX(WBS_CBS!$M$5:$M$16,MATCH($D9,WBS_CBS!$A$5:$A$16,0)),"Yes")) | V9: =IF($D9="","",IFERROR(INDEX(WBS_CBS!$N$5:$N$16,MATCH($D9,WBS_CBS!$A$5:$A$16,0)),"Yes")) | W9: =IF($D9="","",IFERROR(INDEX(WBS_CBS!$K$5:$K$16,MATCH($D9,WBS_CBS!$A$5:$A$16,0)),"")) | X9: =IF($D9="","",IFERROR(INDEX(WBS_CBS!$F$5:$F$16,MATCH($D9,WBS_CBS!$A$5:$A$16,0)),"")) | AA9: =IF($D9="","",IFERROR(INDEX(WBS_CBS!$L$5:$L$16,MATCH($D9,WBS_CBS!$A$5:$A$16,0)),""))
C10: =IF($D10="","",IFERROR(INDEX(WBS_CBS!$E$5:$E$16,MATCH($D10,WBS_CBS!$A$5:$A$16,0)),"")) | E10: =IF($D10="","",IFERROR(INDEX(WBS_CBS!$C$5:$C$16,MATCH($D10,WBS_CBS!$A$5:$A$16,0)),"")) | F10: =IF($D10="","",IFERROR(INDEX(WBS_CBS!$J$5:$J$16,MATCH($D10,WBS_CBS!$A$5:$A$16,0)),"")) | L10: =IF($K10="","",IFERROR(INDEX(FX_Rates!$B$5:$B$14,MATCH($K10,FX_Rates!$A$5:$A$14,0)),"")) | M10: =IF(OR($H10="",$J10=""),"",$H10*$J10) | N10: =IF(OR($M10="",$L10=""),"",$M10*$L10) | P10: =IF($O10="","",IFERROR(INDEX(Basis_of_Estimate!$C$5:$C$9,MATCH($O10,Basis_of_Estimate!$A$5:$A$9,0)),"")) | Q10: =IF($O10="","",IFERROR(INDEX(Basis_of_Estimate!$D$5:$D$9,MATCH($O10,Basis_of_Estimate!$A$5:$A$9,0)),"")) | R10: =IF($N10="","",$N10*(1+$P10)) | S10: =IF($N10="","",$N10) | T10: =IF($N10="","",$N10*(1+$Q10)) | U10: =IF($D10="","",IFERROR(INDEX(WBS_CBS!$M$5:$M$16,MATCH($D10,WBS_CBS!$A$5:$A$16,0)),"Yes")) | V10: =IF($D10="","",IFERROR(INDEX(WBS_CBS!$N$5:$N$16,MATCH($D10,WBS_CBS!$A$5:$A$16,0)),"Yes")) | W10: =IF($D10="","",IFERROR(INDEX(WBS_CBS!$K$5:$K$16,MATCH($D10,WBS_CBS!$A$5:$A$16,0)),"")) | X10: =IF($D10="","",IFERROR(INDEX(WBS_CBS!$F$5:$F$16,MATCH($D10,WBS_CBS!$A$5:$A$16,0)),"")) | AA10: =IF($D10="","",IFERROR(INDEX(WBS_CBS!$L$5:$L$16,MATCH($D10,WBS_CBS!$A$5:$A$16,0)),""))
C11: =IF($D11="","",IFERROR(INDEX(WBS_CBS!$E$5:$E$16,MATCH($D11,WBS_CBS!$A$5:$A$16,0)),"")) | E11: =IF($D11="","",IFERROR(INDEX(WBS_CBS!$C$5:$C$16,MATCH($D11,WBS_CBS!$A$5:$A$16,0)),"")) | F11: =IF($D11="","",IFERROR(INDEX(WBS_CBS!$J$5:$J$16,MATCH($D11,WBS_CBS!$A$5:$A$16,0)),"")) | L11: =IF($K11="","",IFERROR(INDEX(FX_Rates!$B$5:$B$14,MATCH($K11,FX_Rates!$A$5:$A$14,0)),"")) | M11: =IF(OR($H11="",$J11=""),"",$H11*$J11) | N11: =IF(OR($M11="",$L11=""),"",$M11*$L11) | P11: =IF($O11="","",IFERROR(INDEX(Basis_of_Estimate!$C$5:$C$9,MATCH($O11,Basis_of_Estimate!$A$5:$A$9,0)),"")) | Q11: =IF($O11="","",IFERROR(INDEX(Basis_of_Estimate!$D$5:$D$9,MATCH($O11,Basis_of_Estimate!$A$5:$A$9,0)),"")) | R11: =IF($N11="","",$N11*(1+$P11)) | S11: =IF($N11="","",$N11) | T11: =IF($N11="","",$N11*(1+$Q11)) | U11: =IF($D11="","",IFERROR(INDEX(WBS_CBS!$M$5:$M$16,MATCH($D11,WBS_CBS!$A$5:$A$16,0)),"Yes")) | V11: =IF($D11="","",IFERROR(INDEX(WBS_CBS!$N$5:$N$16,MATCH($D11,WBS_CBS!$A$5:$A$16,0)),"Yes")) | W11: =IF($D11="","",IFERROR(INDEX(WBS_CBS!$K$5:$K$16,MATCH($D11,WBS_CBS!$A$5:$A$16,0)),"")) | X11: =IF($D11="","",IFERROR(INDEX(WBS_CBS!$F$5:$F$16,MATCH($D11,WBS_CBS!$A$5:$A$16,0)),"")) | AA11: =IF($D11="","",IFERROR(INDEX(WBS_CBS!$L$5:$L$16,MATCH($D11,WBS_CBS!$A$5:$A$16,0)),""))
C12: =IF($D12="","",IFERROR(INDEX(WBS_CBS!$E$5:$E$16,MATCH($D12,WBS_CBS!$A$5:$A$16,0)),"")) | E12: =IF($D12="","",IFERROR(INDEX(WBS_CBS!$C$5:$C$16,MATCH($D12,WBS_CBS!$A$5:$A$16,0)),"")) | F12: =IF($D12="","",IFERROR(INDEX(WBS_CBS!$J$5:$J$16,MATCH($D12,WBS_CBS!$A$5:$A$16,0)),"")) | L12: =IF($K12="","",IFERROR(INDEX(FX_Rates!$B$5:$B$14,MATCH($K12,FX_Rates!$A$5:$A$14,0)),"")) | M12: =IF(OR($H12="",$J12=""),"",$H12*$J12) | N12: =IF(OR($M12="",$L12=""),"",$M12*$L12) | P12: =IF($O12="","",IFERROR(INDEX(Basis_of_Estimate!$C$5:$C$9,MATCH($O12,Basis_of_Estimate!$A$5:$A$9,0)),"")) | Q12: =IF($O12="","",IFERROR(INDEX(Basis_of_Estimate!$D$5:$D$9,MATCH($O12,Basis_of_Estimate!$A$5:$A$9,0)),"")) | R12: =IF($N12="","",$N12*(1+$P12)) | S12: =IF($N12="","",$N12) | T12: =IF($N12="","",$N12*(1+$Q12)) | U12: =IF($D12="","",IFERROR(INDEX(WBS_CBS!$M$5:$M$16,MATCH($D12,WBS_CBS!$A$5:$A$16,0)),"Yes")) | V12: =IF($D12="","",IFERROR(INDEX(WBS_CBS!$N$5:$N$16,MATCH($D12,WBS_CBS!$A$5:$A$16,0)),"Yes")) | W12: =IF($D12="","",IFERROR(INDEX(WBS_CBS!$K$5:$K$16,MATCH($D12,WBS_CBS!$A$5:$A$16,0)),"")) | X12: =IF($D12="","",IFERROR(INDEX(WBS_CBS!$F$5:$F$16,MATCH($D12,WBS_CBS!$A$5:$A$16,0)),"")) | AA12: =IF($D12="","",IFERROR(INDEX(WBS_CBS!$L$5:$L$16,MATCH($D12,WBS_CBS!$A$5:$A$16,0)),""))
C13: =IF($D13="","",IFERROR(INDEX(WBS_CBS!$E$5:$E$16,MATCH($D13,WBS_CBS!$A$5:$A$16,0)),"")) | E13: =IF($D13="","",IFERROR(INDEX(WBS_CBS!$C$5:$C$16,MATCH($D13,WBS_CBS!$A$5:$A$16,0)),"")) | F13: =IF($D13="","",IFERROR(INDEX(WBS_CBS!$J$5:$J$16,MATCH($D13,WBS_CBS!$A$5:$A$16,0)),"")) | L13: =IF($K13="","",IFERROR(INDEX(FX_Rates!$B$5:$B$14,MATCH($K13,FX_Rates!$A$5:$A$14,0)),"")) | M13: =IF(OR($H13="",$J13=""),"",$H13*$J13) | N13: =IF(OR($M13="",$L13=""),"",$M13*$L13) | P13: =IF($O13="","",IFERROR(INDEX(Basis_of_Estimate!$C$5:$C$9,MATCH($O13,Basis_of_Estimate!$A$5:$A$9,0)),"")) | Q13: =IF($O13="","",IFERROR(INDEX(Basis_of_Estimate!$D$5:$D$9,MATCH($O13,Basis_of_Estimate!$A$5:$A$9,0)),"")) | R13: =IF($N13="","",$N13*(1+$P13)) | S13: =IF($N13="","",$N13) | T13: =IF($N13="","",$N13*(1+$Q13)) | U13: =IF($D13="","",IFERROR(INDEX(WBS_CBS!$M$5:$M$16,MATCH($D13,WBS_CBS!$A$5:$A$16,0)),"Yes")) | V13: =IF($D13="","",IFERROR(INDEX(WBS_CBS!$N$5:$N$16,MATCH($D13,WBS_CBS!$A$5:$A$16,0)),"Yes")) | W13: =IF($D13="","",IFERROR(INDEX(WBS_CBS!$K$5:$K$16,MATCH($D13,WBS_CBS!$A$5:$A$16,0)),"")) | X13: =IF($D13="","",IFERROR(INDEX(WBS_CBS!$F$5:$F$16,MATCH($D13,WBS_CBS!$A$5:$A$16,0)),"")) | AA13: =IF($D13="","",IFERROR(INDEX(WBS_CBS!$L$5:$L$16,MATCH($D13,WBS_CBS!$A$5:$A$16,0)),""))
C14: =IF($D14="","",IFERROR(INDEX(WBS_CBS!$E$5:$E$16,MATCH($D14,WBS_CBS!$A$5:$A$16,0)),"")) | E14: =IF($D14="","",IFERROR(INDEX(WBS_CBS!$C$5:$C$16,MATCH($D14,WBS_CBS!$A$5:$A$16,0)),"")) | F14: =IF($D14="","",IFERROR(INDEX(WBS_CBS!$J$5:$J$16,MATCH($D14,WBS_CBS!$A$5:$A$16,0)),"")) | L14: =IF($K14="","",IFERROR(INDEX(FX_Rates!$B$5:$B$14,MATCH($K14,FX_Rates!$A$5:$A$14,0)),"")) | M14: =IF(OR($H14="",$J14=""),"",$H14*$J14) | N14: =IF(OR($M14="",$L14=""),"",$M14*$L14) | P14: =IF($O14="","",IFERROR(INDEX(Basis_of_Estimate!$C$5:$C$9,MATCH($O14,Basis_of_Estimate!$A$5:$A$9,0)),"")) | Q14: =IF($O14="","",IFERROR(INDEX(Basis_of_Estimate!$D$5:$D$9,MATCH($O14,Basis_of_Estimate!$A$5:$A$9,0)),"")) | R14: =IF($N14="","",$N14*(1+$P14)) | S14: =IF($N14="","",$N14) | T14: =IF($N14="","",$N14*(1+$Q14)) | U14: =IF($D14="","",IFERROR(INDEX(WBS_CBS!$M$5:$M$16,MATCH($D14,WBS_CBS!$A$5:$A$16,0)),"Yes")) | V14: =IF($D14="","",IFERROR(INDEX(WBS_CBS!$N$5:$N$16,MATCH($D14,WBS_CBS!$A$5:$A$16,0)),"Yes")) | W14: =IF($D14="","",IFERROR(INDEX(WBS_CBS!$K$5:$K$16,MATCH($D14,WBS_CBS!$A$5:$A$16,0)),"")) | X14: =IF($D14="","",IFERROR(INDEX(WBS_CBS!$F$5:$F$16,MATCH($D14,WBS_CBS!$A$5:$A$16,0)),"")) | AA14: =IF($D14="","",IFERROR(INDEX(WBS_CBS!$L$5:$L$16,MATCH($D14,WBS_CBS!$A$5:$A$16,0)),""))
C15: =IF($D15="","",IFERROR(INDEX(WBS_CBS!$E$5:$E$16,MATCH($D15,WBS_CBS!$A$5:$A$16,0)),"")) | E15: =IF($D15="","",IFERROR(INDEX(WBS_CBS!$C$5:$C$16,MATCH($D15,WBS_CBS!$A$5:$A$16,0)),"")) | F15: =IF($D15="","",IFERROR(INDEX(WBS_CBS!$J$5:$J$16,MATCH($D15,WBS_CBS!$A$5:$A$16,0)),"")) | L15: =IF($K15="","",IFERROR(INDEX(FX_Rates!$B$5:$B$14,MATCH($K15,FX_Rates!$A$5:$A$14,0)),"")) | M15: =IF(OR($H15="",$J15=""),"",$H15*$J15) | N15: =IF(OR($M15="",$L15=""),"",$M15*$L15) | P15: =IF($O15="","",IFERROR(INDEX(Basis_of_Estimate!$C$5:$C$9,MATCH($O15,Basis_of_Estimate!$A$5:$A$9,0)),"")) | Q15: =IF($O15="","",IFERROR(INDEX(Basis_of_Estimate!$D$5:$D$9,MATCH($O15,Basis_of_Estimate!$A$5:$A$9,0)),"")) | R15: =IF($N15="","",$N15*(1+$P15)) | S15: =IF($N15="","",$N15) | T15: =IF($N15="","",$N15*(1+$Q15)) | U15: =IF($D15="","",IFERROR(INDEX(WBS_CBS!$M$5:$M$16,MATCH($D15,WBS_CBS!$A$5:$A$16,0)),"Yes")) | V15: =IF($D15="","",IFERROR(INDEX(WBS_CBS!$N$5:$N$16,MATCH($D15,WBS_CBS!$A$5:$A$16,0)),"Yes")) | W15: =IF($D15="","",IFERROR(INDEX(WBS_CBS!$K$5:$K$16,MATCH($D15,WBS_CBS!$A$5:$A$16,0)),"")) | X15: =IF($D15="","",IFERROR(INDEX(WBS_CBS!$F$5:$F$16,MATCH($D15,WBS_CBS!$A$5:$A$16,0)),"")) | AA15: =IF($D15="","",IFERROR(INDEX(WBS_CBS!$L$5:$L$16,MATCH($D15,WBS_CBS!$A$5:$A$16,0)),""))
C16: =IF($D16="","",IFERROR(INDEX(WBS_CBS!$E$5:$E$16,MATCH($D16,WBS_CBS!$A$5:$A$16,0)),"")) | E16: =IF($D16="","",IFERROR(INDEX(WBS_CBS!$C$5:$C$16,MATCH($D16,WBS_CBS!$A$5:$A$16,0)),"")) | F16: =IF($D16="","",IFERROR(INDEX(WBS_CBS!$J$5:$J$16,MATCH($D16,WBS_CBS!$A$5:$A$16,0)),"")) | L16: =IF($K16="","",IFERROR(INDEX(FX_Rates!$B$5:$B$14,MATCH($K16,FX_Rates!$A$5:$A$14,0)),"")) | M16: =IF(OR($H16="",$J16=""),"",$H16*$J16) | N16: =IF(OR($M16="",$L16=""),"",$M16*$L16) | P16: =IF($O16="","",IFERROR(INDEX(Basis_of_Estimate!$C$5:$C$9,MATCH($O16,Basis_of_Estimate!$A$5:$A$9,0)),"")) | Q16: =IF($O16="","",IFERROR(INDEX(Basis_of_Estimate!$D$5:$D$9,MATCH($O16,Basis_of_Estimate!$A$5:$A$9,0)),"")) | R16: =IF($N16="","",$N16*(1+$P16)) | S16: =IF($N16="","",$N16) | T16: =IF($N16="","",$N16*(1+$Q16)) | U16: =IF($D16="","",IFERROR(INDEX(WBS_CBS!$M$5:$M$16,MATCH($D16,WBS_CBS!$A$5:$A$16,0)),"Yes")) | V16: =IF($D16="","",IFERROR(INDEX(WBS_CBS!$N$5:$N$16,MATCH($D16,WBS_CBS!$A$5:$A$16,0)),"Yes")) | W16: =IF($D16="","",IFERROR(INDEX(WBS_CBS!$K$5:$K$16,MATCH($D16,WBS_CBS!$A$5:$A$16,0)),"")) | X16: =IF($D16="","",IFERROR(INDEX(WBS_CBS!$F$5:$F$16,MATCH($D16,WBS_CBS!$A$5:$A$16,0)),"")) | AA16: =IF($D16="","",IFERROR(INDEX(WBS_CBS!$L$5:$L$16,MATCH($D16,WBS_CBS!$A$5:$A$16,0)),""))
C17: =IF($D17="","",IFERROR(INDEX(WBS_CBS!$E$5:$E$16,MATCH($D17,WBS_CBS!$A$5:$A$16,0)),"")) | E17: =IF($D17="","",IFERROR(INDEX(WBS_CBS!$C$5:$C$16,MATCH($D17,WBS_CBS!$A$5:$A$16,0)),"")) | F17: =IF($D17="","",IFERROR(INDEX(WBS_CBS!$J$5:$J$16,MATCH($D17,WBS_CBS!$A$5:$A$16,0)),"")) | L17: =IF($K17="","",IFERROR(INDEX(FX_Rates!$B$5:$B$14,MATCH($K17,FX_Rates!$A$5:$A$14,0)),"")) | M17: =IF(OR($H17="",$J17=""),"",$H17*$J17) | N17: =IF(OR($M17="",$L17=""),"",$M17*$L17) | P17: =IF($O17="","",IFERROR(INDEX(Basis_of_Estimate!$C$5:$C$9,MATCH($O17,Basis_of_Estimate!$A$5:$A$9,0)),"")) | Q17: =IF($O17="","",IFERROR(INDEX(Basis_of_Estimate!$D$5:$D$9,MATCH($O17,Basis_of_Estimate!$A$5:$A$9,0)),"")) | R17: =IF($N17="","",$N17*(1+$P17)) | S17: =IF($N17="","",$N17) | T17: =IF($N17="","",$N17*(1+$Q17)) | U17: =IF($D17="","",IFERROR(INDEX(WBS_CBS!$M$5:$M$16,MATCH($D17,WBS_CBS!$A$5:$A$16,0)),"Yes")) | V17: =IF($D17="","",IFERROR(INDEX(WBS_CBS!$N$5:$N$16,MATCH($D17,WBS_CBS!$A$5:$A$16,0)),"Yes")) | W17: =IF($D17="","",IFERROR(INDEX(WBS_CBS!$K$5:$K$16,MATCH($D17,WBS_CBS!$A$5:$A$16,0)),"")) | X17: =IF($D17="","",IFERROR(INDEX(WBS_CBS!$F$5:$F$16,MATCH($D17,WBS_CBS!$A$5:$A$16,0)),"")) | AA17: =IF($D17="","",IFERROR(INDEX(WBS_CBS!$L$5:$L$16,MATCH($D17,WBS_CBS!$A$5:$A$16,0)),""))
C18: =IF($D18="","",IFERROR(INDEX(WBS_CBS!$E$5:$E$16,MATCH($D18,WBS_CBS!$A$5:$A$16,0)),"")) | E18: =IF($D18="","",IFERROR(INDEX(WBS_CBS!$C$5:$C$16,MATCH($D18,WBS_CBS!$A$5:$A$16,0)),"")) | F18: =IF($D18="","",IFERROR(INDEX(WBS_CBS!$J$5:$J$16,MATCH($D18,WBS_CBS!$A$5:$A$16,0)),"")) | L18: =IF($K18="","",IFERROR(INDEX(FX_Rates!$B$5:$B$14,MATCH($K18,FX_Rates!$A$5:$A$14,0)),"")) | M18: =IF(OR($H18="",$J18=""),"",$H18*$J18) | N18: =IF(OR($M18="",$L18=""),"",$M18*$L18) | P18: =IF($O18="","",IFERROR(INDEX(Basis_of_Estimate!$C$5:$C$9,MATCH($O18,Basis_of_Estimate!$A$5:$A$9,0)),"")) | Q18: =IF($O18="","",IFERROR(INDEX(Basis_of_Estimate!$D$5:$D$9,MATCH($O18,Basis_of_Estimate!$A$5:$A$9,0)),"")) | R18: =IF($N18="","",$N18*(1+$P18)) | S18: =IF($N18="","",$N18) | T18: =IF($N18="","",$N18*(1+$Q18)) | U18: =IF($D18="","",IFERROR(INDEX(WBS_CBS!$M$5:$M$16,MATCH($D18,WBS_CBS!$A$5:$A$16,0)),"Yes")) | V18: =IF($D18="","",IFERROR(INDEX(WBS_CBS!$N$5:$N$16,MATCH($D18,WBS_CBS!$A$5:$A$16,0)),"Yes")) | W18: =IF($D18="","",IFERROR(INDEX(WBS_CBS!$K$5:$K$16,MATCH($D18,WBS_CBS!$A$5:$A$16,0)),"")) | X18: =IF($D18="","",IFERROR(INDEX(WBS_CBS!$F$5:$F$16,MATCH($D18,WBS_CBS!$A$5:$A$16,0)),"")) | AA18: =IF($D18="","",IFERROR(INDEX(WBS_CBS!$L$5:$L$16,MATCH($D18,WBS_CBS!$A$5:$A$16,0)),""))
C19: =IF($D19="","",IFERROR(INDEX(WBS_CBS!$E$5:$E$16,MATCH($D19,WBS_CBS!$A$5:$A$16,0)),"")) | E19: =IF($D19="","",IFERROR(INDEX(WBS_CBS!$C$5:$C$16,MATCH($D19,WBS_CBS!$A$5:$A$16,0)),"")) | F19: =IF($D19="","",IFERROR(INDEX(WBS_CBS!$J$5:$J$16,MATCH($D19,WBS_CBS!$A$5:$A$16,0)),"")) | L19: =IF($K19="","",IFERROR(INDEX(FX_Rates!$B$5:$B$14,MATCH($K19,FX_Rates!$A$5:$A$14,0)),"")) | M19: =IF(OR($H19="",$J19=""),"",$H19*$J19) | N19: =IF(OR($M19="",$L19=""),"",$M19*$L19) | P19: =IF($O19="","",IFERROR(INDEX(Basis_of_Estimate!$C$5:$C$9,MATCH($O19,Basis_of_Estimate!$A$5:$A$9,0)),"")) | Q19: =IF($O19="","",IFERROR(INDEX(Basis_of_Estimate!$D$5:$D$9,MATCH($O19,Basis_of_Estimate!$A$5:$A$9,0)),"")) | R19: =IF($N19="","",$N19*(1+$P19)) | S19: =IF($N19="","",$N19) | T19: =IF($N19="","",$N19*(1+$Q19)) | U19: =IF($D19="","",IFERROR(INDEX(WBS_CBS!$M$5:$M$16,MATCH($D19,WBS_CBS!$A$5:$A$16,0)),"Yes")) | V19: =IF($D19="","",IFERROR(INDEX(WBS_CBS!$N$5:$N$16,MATCH($D19,WBS_CBS!$A$5:$A$16,0)),"Yes")) | W19: =IF($D19="","",IFERROR(INDEX(WBS_CBS!$K$5:$K$16,MATCH($D19,WBS_CBS!$A$5:$A$16,0)),"")) | X19: =IF($D19="","",IFERROR(INDEX(WBS_CBS!$F$5:$F$16,MATCH($D19,WBS_CBS!$A$5:$A$16,0)),"")) | AA19: =IF($D19="","",IFERROR(INDEX(WBS_CBS!$L$5:$L$16,MATCH($D19,WBS_CBS!$A$5:$A$16,0)),""))
... C104: =IF($D104="","",IFERROR(INDEX(WBS_CBS!$E$5:$E$16,MATCH($D104,WBS_CBS!$A$5:$A$16,0)),"")) | E104: =IF($D104="","",IFERROR(INDEX(WBS_CBS!$C$5:$C$16,MATCH($D104,WBS_CBS!$A$5:$A$16,0)),"")) | F104: =IF($D104="","",IFERROR(INDEX(WBS_CBS!$J$5:$J$16,MATCH($D104,WBS_CBS!$A$5:$A$16,0)),"")) | L104: =IF($K104="","",IFERROR(INDEX(FX_Rates!$B$5:$B$14,MATCH($K104,FX_Rates!$A$5:$A$14,0)),"")) | M104: =IF(OR($H104="",$J104=""),"",$H104*$J104) | N104: =IF(OR($M104="",$L104=""),"",$M104*$L104) | P104: =IF($O104="","",IFERROR(INDEX(Basis_of_Estimate!$C$5:$C$9,MATCH($O104,Basis_of_Estimate!$A$5:$A$9,0)),"")) | Q104: =IF($O104="","",IFERROR(INDEX(Basis_of_Estimate!$D$5:$D$9,MATCH($O104,Basis_of_Estimate!$A$5:$A$9,0)),"")) | R104: =IF($N104="","",$N104*(1+$P104)) | S104: =IF($N104="","",$N104) | T104: =IF($N104="","",$N104*(1+$Q104)) | U104: =IF($D104="","",IFERROR(INDEX(WBS_CBS!$M$5:$M$16,MATCH($D104,WBS_CBS!$A$5:$A$16,0)),"Yes")) | V104: =IF($D104="","",IFERROR(INDEX(WBS_CBS!$N$5:$N$16,MATCH($D104,WBS_CBS!$A$5:$A$16,0)),"Yes")) | W104: =IF($D104="","",IFERROR(INDEX(WBS_CBS!$K$5:$K$16,MATCH($D104,WBS_CBS!$A$5:$A$16,0)),"")) | X104: =IF($D104="","",IFERROR(INDEX(WBS_CBS!$F$5:$F$16,MATCH($D104,WBS_CBS!$A$5:$A$16,0)),"")) | AA104: =IF($D104="","",IFERROR(INDEX(WBS_CBS!$L$5:$L$16,MATCH($D104,WBS_CBS!$A$5:$A$16,0)),""))

Sheet Construction_Estimate
A1: Construction Estimate
A2: User input layer. Cost_Register must be rebuilt from these sheets via BuildCostRegister.
A4: Item ID | B4: Description | C4: Discipline | D4: WBS | E4: CBS | F4: Cost Category | G4: Cost Type | H4: Quantity | I4: Unit | J4: Unit Rate | K4: Currency | L4: FX Rate | M4: Base Cost | N4: Base Cost EUR | O4: Estimate Basis | P4: Accuracy Low % | Q4: Accuracy High % | R4: Low Cost | S4: Most Likely Cost | T4: High Cost | U4: Contingency Eligible | V4: Escalation Eligible | W4: Spend Category | X4: Phase | Y4: Start Month | Z4: End Month | AA4: Spend Curve | AB4: Notes
A5: CN-001 | B5: Civil works and foundations | C5: =IF($D5="","",IFERROR(INDEX(WBS_CBS!$E$5:$E$16,MATCH($D5,WBS_CBS!$A$5:$A$16,0)),"")) | D5: 6.0 | E5: =IF($D5="","",IFERROR(INDEX(WBS_CBS!$C$5:$C$16,MATCH($D5,WBS_CBS!$A$5:$A$16,0)),"")) | F5: =IF($D5="","",IFERROR(INDEX(WBS_CBS!$J$5:$J$16,MATCH($D5,WBS_CBS!$A$5:$A$16,0)),"")) | G5: Construction | H5: 1 | I5: lot | J5: 2000000 | K5: EUR | L5: =IF($K5="","",IFERROR(INDEX(FX_Rates!$B$5:$B$14,MATCH($K5,FX_Rates!$A$5:$A$14,0)),"")) | M5: =IF(OR($H5="",$J5=""),"",$H5*$J5) | N5: =IF(OR($M5="",$L5=""),"",$M5*$L5) | O5: Class 3 | P5: =IF($O5="","",IFERROR(INDEX(Basis_of_Estimate!$C$5:$C$9,MATCH($O5,Basis_of_Estimate!$A$5:$A$9,0)),"")) | Q5: =IF($O5="","",IFERROR(INDEX(Basis_of_Estimate!$D$5:$D$9,MATCH($O5,Basis_of_Estimate!$A$5:$A$9,0)),"")) | R5: =IF($N5="","",$N5*(1+$P5)) | S5: =IF($N5="","",$N5) | T5: =IF($N5="","",$N5*(1+$Q5)) | U5: =IF($D5="","",IFERROR(INDEX(WBS_CBS!$M$5:$M$16,MATCH($D5,WBS_CBS!$A$5:$A$16,0)),"Yes")) | V5: =IF($D5="","",IFERROR(INDEX(WBS_CBS!$N$5:$N$16,MATCH($D5,WBS_CBS!$A$5:$A$16,0)),"Yes")) | W5: =IF($D5="","",IFERROR(INDEX(WBS_CBS!$K$5:$K$16,MATCH($D5,WBS_CBS!$A$5:$A$16,0)),"")) | X5: =IF($D5="","",IFERROR(INDEX(WBS_CBS!$F$5:$F$16,MATCH($D5,WBS_CBS!$A$5:$A$16,0)),"")) | Y5: 12 | Z5: 26 | AA5: =IF($D5="","",IFERROR(INDEX(WBS_CBS!$L$5:$L$16,MATCH($D5,WBS_CBS!$A$5:$A$16,0)),""))
A6: CN-002 | B6: Mechanical installation works | C6: =IF($D6="","",IFERROR(INDEX(WBS_CBS!$E$5:$E$16,MATCH($D6,WBS_CBS!$A$5:$A$16,0)),"")) | D6: 9.0 | E6: =IF($D6="","",IFERROR(INDEX(WBS_CBS!$C$5:$C$16,MATCH($D6,WBS_CBS!$A$5:$A$16,0)),"")) | F6: =IF($D6="","",IFERROR(INDEX(WBS_CBS!$J$5:$J$16,MATCH($D6,WBS_CBS!$A$5:$A$16,0)),"")) | G6: Construction | H6: 1 | I6: lot | J6: 2300000 | K6: EUR | L6: =IF($K6="","",IFERROR(INDEX(FX_Rates!$B$5:$B$14,MATCH($K6,FX_Rates!$A$5:$A$14,0)),"")) | M6: =IF(OR($H6="",$J6=""),"",$H6*$J6) | N6: =IF(OR($M6="",$L6=""),"",$M6*$L6) | O6: Class 3 | P6: =IF($O6="","",IFERROR(INDEX(Basis_of_Estimate!$C$5:$C$9,MATCH($O6,Basis_of_Estimate!$A$5:$A$9,0)),"")) | Q6: =IF($O6="","",IFERROR(INDEX(Basis_of_Estimate!$D$5:$D$9,MATCH($O6,Basis_of_Estimate!$A$5:$A$9,0)),"")) | R6: =IF($N6="","",$N6*(1+$P6)) | S6: =IF($N6="","",$N6) | T6: =IF($N6="","",$N6*(1+$Q6)) | U6: =IF($D6="","",IFERROR(INDEX(WBS_CBS!$M$5:$M$16,MATCH($D6,WBS_CBS!$A$5:$A$16,0)),"Yes")) | V6: =IF($D6="","",IFERROR(INDEX(WBS_CBS!$N$5:$N$16,MATCH($D6,WBS_CBS!$A$5:$A$16,0)),"Yes")) | W6: =IF($D6="","",IFERROR(INDEX(WBS_CBS!$K$5:$K$16,MATCH($D6,WBS_CBS!$A$5:$A$16,0)),"")) | X6: =IF($D6="","",IFERROR(INDEX(WBS_CBS!$F$5:$F$16,MATCH($D6,WBS_CBS!$A$5:$A$16,0)),"")) | Y6: 18 | Z6: 31 | AA6: =IF($D6="","",IFERROR(INDEX(WBS_CBS!$L$5:$L$16,MATCH($D6,WBS_CBS!$A$5:$A$16,0)),""))
A7: CN-003 | B7: Electrical installation works | C7: =IF($D7="","",IFERROR(INDEX(WBS_CBS!$E$5:$E$16,MATCH($D7,WBS_CBS!$A$5:$A$16,0)),"")) | D7: 9.0 | E7: =IF($D7="","",IFERROR(INDEX(WBS_CBS!$C$5:$C$16,MATCH($D7,WBS_CBS!$A$5:$A$16,0)),"")) | F7: =IF($D7="","",IFERROR(INDEX(WBS_CBS!$J$5:$J$16,MATCH($D7,WBS_CBS!$A$5:$A$16,0)),"")) | G7: Construction | H7: 1 | I7: lot | J7: 1200000 | K7: EUR | L7: =IF($K7="","",IFERROR(INDEX(FX_Rates!$B$5:$B$14,MATCH($K7,FX_Rates!$A$5:$A$14,0)),"")) | M7: =IF(OR($H7="",$J7=""),"",$H7*$J7) | N7: =IF(OR($M7="",$L7=""),"",$M7*$L7) | O7: Class 3 | P7: =IF($O7="","",IFERROR(INDEX(Basis_of_Estimate!$C$5:$C$9,MATCH($O7,Basis_of_Estimate!$A$5:$A$9,0)),"")) | Q7: =IF($O7="","",IFERROR(INDEX(Basis_of_Estimate!$D$5:$D$9,MATCH($O7,Basis_of_Estimate!$A$5:$A$9,0)),"")) | R7: =IF($N7="","",$N7*(1+$P7)) | S7: =IF($N7="","",$N7) | T7: =IF($N7="","",$N7*(1+$Q7)) | U7: =IF($D7="","",IFERROR(INDEX(WBS_CBS!$M$5:$M$16,MATCH($D7,WBS_CBS!$A$5:$A$16,0)),"Yes")) | V7: =IF($D7="","",IFERROR(INDEX(WBS_CBS!$N$5:$N$16,MATCH($D7,WBS_CBS!$A$5:$A$16,0)),"Yes")) | W7: =IF($D7="","",IFERROR(INDEX(WBS_CBS!$K$5:$K$16,MATCH($D7,WBS_CBS!$A$5:$A$16,0)),"")) | X7: =IF($D7="","",IFERROR(INDEX(WBS_CBS!$F$5:$F$16,MATCH($D7,WBS_CBS!$A$5:$A$16,0)),"")) | Y7: 18 | Z7: 32 | AA7: =IF($D7="","",IFERROR(INDEX(WBS_CBS!$L$5:$L$16,MATCH($D7,WBS_CBS!$A$5:$A$16,0)),""))
A8: CN-004 | B8: Pre-commissioning and start-up support | C8: =IF($D8="","",IFERROR(INDEX(WBS_CBS!$E$5:$E$16,MATCH($D8,WBS_CBS!$A$5:$A$16,0)),"")) | D8: 10.0 | E8: =IF($D8="","",IFERROR(INDEX(WBS_CBS!$C$5:$C$16,MATCH($D8,WBS_CBS!$A$5:$A$16,0)),"")) | F8: =IF($D8="","",IFERROR(INDEX(WBS_CBS!$J$5:$J$16,MATCH($D8,WBS_CBS!$A$5:$A$16,0)),"")) | G8: Construction | H8: 1 | I8: lot | J8: 1500000 | K8: EUR | L8: =IF($K8="","",IFERROR(INDEX(FX_Rates!$B$5:$B$14,MATCH($K8,FX_Rates!$A$5:$A$14,0)),"")) | M8: =IF(OR($H8="",$J8=""),"",$H8*$J8) | N8: =IF(OR($M8="",$L8=""),"",$M8*$L8) | O8: Class 3 | P8: =IF($O8="","",IFERROR(INDEX(Basis_of_Estimate!$C$5:$C$9,MATCH($O8,Basis_of_Estimate!$A$5:$A$9,0)),"")) | Q8: =IF($O8="","",IFERROR(INDEX(Basis_of_Estimate!$D$5:$D$9,MATCH($O8,Basis_of_Estimate!$A$5:$A$9,0)),"")) | R8: =IF($N8="","",$N8*(1+$P8)) | S8: =IF($N8="","",$N8) | T8: =IF($N8="","",$N8*(1+$Q8)) | U8: =IF($D8="","",IFERROR(INDEX(WBS_CBS!$M$5:$M$16,MATCH($D8,WBS_CBS!$A$5:$A$16,0)),"Yes")) | V8: =IF($D8="","",IFERROR(INDEX(WBS_CBS!$N$5:$N$16,MATCH($D8,WBS_CBS!$A$5:$A$16,0)),"Yes")) | W8: =IF($D8="","",IFERROR(INDEX(WBS_CBS!$K$5:$K$16,MATCH($D8,WBS_CBS!$A$5:$A$16,0)),"")) | X8: =IF($D8="","",IFERROR(INDEX(WBS_CBS!$F$5:$F$16,MATCH($D8,WBS_CBS!$A$5:$A$16,0)),"")) | Y8: 30 | Z8: 36 | AA8: =IF($D8="","",IFERROR(INDEX(WBS_CBS!$L$5:$L$16,MATCH($D8,WBS_CBS!$A$5:$A$16,0)),""))
C9: =IF($D9="","",IFERROR(INDEX(WBS_CBS!$E$5:$E$16,MATCH($D9,WBS_CBS!$A$5:$A$16,0)),"")) | E9: =IF($D9="","",IFERROR(INDEX(WBS_CBS!$C$5:$C$16,MATCH($D9,WBS_CBS!$A$5:$A$16,0)),"")) | F9: =IF($D9="","",IFERROR(INDEX(WBS_CBS!$J$5:$J$16,MATCH($D9,WBS_CBS!$A$5:$A$16,0)),"")) | L9: =IF($K9="","",IFERROR(INDEX(FX_Rates!$B$5:$B$14,MATCH($K9,FX_Rates!$A$5:$A$14,0)),"")) | M9: =IF(OR($H9="",$J9=""),"",$H9*$J9) | N9: =IF(OR($M9="",$L9=""),"",$M9*$L9) | P9: =IF($O9="","",IFERROR(INDEX(Basis_of_Estimate!$C$5:$C$9,MATCH($O9,Basis_of_Estimate!$A$5:$A$9,0)),"")) | Q9: =IF($O9="","",IFERROR(INDEX(Basis_of_Estimate!$D$5:$D$9,MATCH($O9,Basis_of_Estimate!$A$5:$A$9,0)),"")) | R9: =IF($N9="","",$N9*(1+$P9)) | S9: =IF($N9="","",$N9) | T9: =IF($N9="","",$N9*(1+$Q9)) | U9: =IF($D9="","",IFERROR(INDEX(WBS_CBS!$M$5:$M$16,MATCH($D9,WBS_CBS!$A$5:$A$16,0)),"Yes")) | V9: =IF($D9="","",IFERROR(INDEX(WBS_CBS!$N$5:$N$16,MATCH($D9,WBS_CBS!$A$5:$A$16,0)),"Yes")) | W9: =IF($D9="","",IFERROR(INDEX(WBS_CBS!$K$5:$K$16,MATCH($D9,WBS_CBS!$A$5:$A$16,0)),"")) | X9: =IF($D9="","",IFERROR(INDEX(WBS_CBS!$F$5:$F$16,MATCH($D9,WBS_CBS!$A$5:$A$16,0)),"")) | AA9: =IF($D9="","",IFERROR(INDEX(WBS_CBS!$L$5:$L$16,MATCH($D9,WBS_CBS!$A$5:$A$16,0)),""))
C10: =IF($D10="","",IFERROR(INDEX(WBS_CBS!$E$5:$E$16,MATCH($D10,WBS_CBS!$A$5:$A$16,0)),"")) | E10: =IF($D10="","",IFERROR(INDEX(WBS_CBS!$C$5:$C$16,MATCH($D10,WBS_CBS!$A$5:$A$16,0)),"")) | F10: =IF($D10="","",IFERROR(INDEX(WBS_CBS!$J$5:$J$16,MATCH($D10,WBS_CBS!$A$5:$A$16,0)),"")) | L10: =IF($K10="","",IFERROR(INDEX(FX_Rates!$B$5:$B$14,MATCH($K10,FX_Rates!$A$5:$A$14,0)),"")) | M10: =IF(OR($H10="",$J10=""),"",$H10*$J10) | N10: =IF(OR($M10="",$L10=""),"",$M10*$L10) | P10: =IF($O10="","",IFERROR(INDEX(Basis_of_Estimate!$C$5:$C$9,MATCH($O10,Basis_of_Estimate!$A$5:$A$9,0)),"")) | Q10: =IF($O10="","",IFERROR(INDEX(Basis_of_Estimate!$D$5:$D$9,MATCH($O10,Basis_of_Estimate!$A$5:$A$9,0)),"")) | R10: =IF($N10="","",$N10*(1+$P10)) | S10: =IF($N10="","",$N10) | T10: =IF($N10="","",$N10*(1+$Q10)) | U10: =IF($D10="","",IFERROR(INDEX(WBS_CBS!$M$5:$M$16,MATCH($D10,WBS_CBS!$A$5:$A$16,0)),"Yes")) | V10: =IF($D10="","",IFERROR(INDEX(WBS_CBS!$N$5:$N$16,MATCH($D10,WBS_CBS!$A$5:$A$16,0)),"Yes")) | W10: =IF($D10="","",IFERROR(INDEX(WBS_CBS!$K$5:$K$16,MATCH($D10,WBS_CBS!$A$5:$A$16,0)),"")) | X10: =IF($D10="","",IFERROR(INDEX(WBS_CBS!$F$5:$F$16,MATCH($D10,WBS_CBS!$A$5:$A$16,0)),"")) | AA10: =IF($D10="","",IFERROR(INDEX(WBS_CBS!$L$5:$L$16,MATCH($D10,WBS_CBS!$A$5:$A$16,0)),""))
C11: =IF($D11="","",IFERROR(INDEX(WBS_CBS!$E$5:$E$16,MATCH($D11,WBS_CBS!$A$5:$A$16,0)),"")) | E11: =IF($D11="","",IFERROR(INDEX(WBS_CBS!$C$5:$C$16,MATCH($D11,WBS_CBS!$A$5:$A$16,0)),"")) | F11: =IF($D11="","",IFERROR(INDEX(WBS_CBS!$J$5:$J$16,MATCH($D11,WBS_CBS!$A$5:$A$16,0)),"")) | L11: =IF($K11="","",IFERROR(INDEX(FX_Rates!$B$5:$B$14,MATCH($K11,FX_Rates!$A$5:$A$14,0)),"")) | M11: =IF(OR($H11="",$J11=""),"",$H11*$J11) | N11: =IF(OR($M11="",$L11=""),"",$M11*$L11) | P11: =IF($O11="","",IFERROR(INDEX(Basis_of_Estimate!$C$5:$C$9,MATCH($O11,Basis_of_Estimate!$A$5:$A$9,0)),"")) | Q11: =IF($O11="","",IFERROR(INDEX(Basis_of_Estimate!$D$5:$D$9,MATCH($O11,Basis_of_Estimate!$A$5:$A$9,0)),"")) | R11: =IF($N11="","",$N11*(1+$P11)) | S11: =IF($N11="","",$N11) | T11: =IF($N11="","",$N11*(1+$Q11)) | U11: =IF($D11="","",IFERROR(INDEX(WBS_CBS!$M$5:$M$16,MATCH($D11,WBS_CBS!$A$5:$A$16,0)),"Yes")) | V11: =IF($D11="","",IFERROR(INDEX(WBS_CBS!$N$5:$N$16,MATCH($D11,WBS_CBS!$A$5:$A$16,0)),"Yes")) | W11: =IF($D11="","",IFERROR(INDEX(WBS_CBS!$K$5:$K$16,MATCH($D11,WBS_CBS!$A$5:$A$16,0)),"")) | X11: =IF($D11="","",IFERROR(INDEX(WBS_CBS!$F$5:$F$16,MATCH($D11,WBS_CBS!$A$5:$A$16,0)),"")) | AA11: =IF($D11="","",IFERROR(INDEX(WBS_CBS!$L$5:$L$16,MATCH($D11,WBS_CBS!$A$5:$A$16,0)),""))
C12: =IF($D12="","",IFERROR(INDEX(WBS_CBS!$E$5:$E$16,MATCH($D12,WBS_CBS!$A$5:$A$16,0)),"")) | E12: =IF($D12="","",IFERROR(INDEX(WBS_CBS!$C$5:$C$16,MATCH($D12,WBS_CBS!$A$5:$A$16,0)),"")) | F12: =IF($D12="","",IFERROR(INDEX(WBS_CBS!$J$5:$J$16,MATCH($D12,WBS_CBS!$A$5:$A$16,0)),"")) | L12: =IF($K12="","",IFERROR(INDEX(FX_Rates!$B$5:$B$14,MATCH($K12,FX_Rates!$A$5:$A$14,0)),"")) | M12: =IF(OR($H12="",$J12=""),"",$H12*$J12) | N12: =IF(OR($M12="",$L12=""),"",$M12*$L12) | P12: =IF($O12="","",IFERROR(INDEX(Basis_of_Estimate!$C$5:$C$9,MATCH($O12,Basis_of_Estimate!$A$5:$A$9,0)),"")) | Q12: =IF($O12="","",IFERROR(INDEX(Basis_of_Estimate!$D$5:$D$9,MATCH($O12,Basis_of_Estimate!$A$5:$A$9,0)),"")) | R12: =IF($N12="","",$N12*(1+$P12)) | S12: =IF($N12="","",$N12) | T12: =IF($N12="","",$N12*(1+$Q12)) | U12: =IF($D12="","",IFERROR(INDEX(WBS_CBS!$M$5:$M$16,MATCH($D12,WBS_CBS!$A$5:$A$16,0)),"Yes")) | V12: =IF($D12="","",IFERROR(INDEX(WBS_CBS!$N$5:$N$16,MATCH($D12,WBS_CBS!$A$5:$A$16,0)),"Yes")) | W12: =IF($D12="","",IFERROR(INDEX(WBS_CBS!$K$5:$K$16,MATCH($D12,WBS_CBS!$A$5:$A$16,0)),"")) | X12: =IF($D12="","",IFERROR(INDEX(WBS_CBS!$F$5:$F$16,MATCH($D12,WBS_CBS!$A$5:$A$16,0)),"")) | AA12: =IF($D12="","",IFERROR(INDEX(WBS_CBS!$L$5:$L$16,MATCH($D12,WBS_CBS!$A$5:$A$16,0)),""))
C13: =IF($D13="","",IFERROR(INDEX(WBS_CBS!$E$5:$E$16,MATCH($D13,WBS_CBS!$A$5:$A$16,0)),"")) | E13: =IF($D13="","",IFERROR(INDEX(WBS_CBS!$C$5:$C$16,MATCH($D13,WBS_CBS!$A$5:$A$16,0)),"")) | F13: =IF($D13="","",IFERROR(INDEX(WBS_CBS!$J$5:$J$16,MATCH($D13,WBS_CBS!$A$5:$A$16,0)),"")) | L13: =IF($K13="","",IFERROR(INDEX(FX_Rates!$B$5:$B$14,MATCH($K13,FX_Rates!$A$5:$A$14,0)),"")) | M13: =IF(OR($H13="",$J13=""),"",$H13*$J13) | N13: =IF(OR($M13="",$L13=""),"",$M13*$L13) | P13: =IF($O13="","",IFERROR(INDEX(Basis_of_Estimate!$C$5:$C$9,MATCH($O13,Basis_of_Estimate!$A$5:$A$9,0)),"")) | Q13: =IF($O13="","",IFERROR(INDEX(Basis_of_Estimate!$D$5:$D$9,MATCH($O13,Basis_of_Estimate!$A$5:$A$9,0)),"")) | R13: =IF($N13="","",$N13*(1+$P13)) | S13: =IF($N13="","",$N13) | T13: =IF($N13="","",$N13*(1+$Q13)) | U13: =IF($D13="","",IFERROR(INDEX(WBS_CBS!$M$5:$M$16,MATCH($D13,WBS_CBS!$A$5:$A$16,0)),"Yes")) | V13: =IF($D13="","",IFERROR(INDEX(WBS_CBS!$N$5:$N$16,MATCH($D13,WBS_CBS!$A$5:$A$16,0)),"Yes")) | W13: =IF($D13="","",IFERROR(INDEX(WBS_CBS!$K$5:$K$16,MATCH($D13,WBS_CBS!$A$5:$A$16,0)),"")) | X13: =IF($D13="","",IFERROR(INDEX(WBS_CBS!$F$5:$F$16,MATCH($D13,WBS_CBS!$A$5:$A$16,0)),"")) | AA13: =IF($D13="","",IFERROR(INDEX(WBS_CBS!$L$5:$L$16,MATCH($D13,WBS_CBS!$A$5:$A$16,0)),""))
C14: =IF($D14="","",IFERROR(INDEX(WBS_CBS!$E$5:$E$16,MATCH($D14,WBS_CBS!$A$5:$A$16,0)),"")) | E14: =IF($D14="","",IFERROR(INDEX(WBS_CBS!$C$5:$C$16,MATCH($D14,WBS_CBS!$A$5:$A$16,0)),"")) | F14: =IF($D14="","",IFERROR(INDEX(WBS_CBS!$J$5:$J$16,MATCH($D14,WBS_CBS!$A$5:$A$16,0)),"")) | L14: =IF($K14="","",IFERROR(INDEX(FX_Rates!$B$5:$B$14,MATCH($K14,FX_Rates!$A$5:$A$14,0)),"")) | M14: =IF(OR($H14="",$J14=""),"",$H14*$J14) | N14: =IF(OR($M14="",$L14=""),"",$M14*$L14) | P14: =IF($O14="","",IFERROR(INDEX(Basis_of_Estimate!$C$5:$C$9,MATCH($O14,Basis_of_Estimate!$A$5:$A$9,0)),"")) | Q14: =IF($O14="","",IFERROR(INDEX(Basis_of_Estimate!$D$5:$D$9,MATCH($O14,Basis_of_Estimate!$A$5:$A$9,0)),"")) | R14: =IF($N14="","",$N14*(1+$P14)) | S14: =IF($N14="","",$N14) | T14: =IF($N14="","",$N14*(1+$Q14)) | U14: =IF($D14="","",IFERROR(INDEX(WBS_CBS!$M$5:$M$16,MATCH($D14,WBS_CBS!$A$5:$A$16,0)),"Yes")) | V14: =IF($D14="","",IFERROR(INDEX(WBS_CBS!$N$5:$N$16,MATCH($D14,WBS_CBS!$A$5:$A$16,0)),"Yes")) | W14: =IF($D14="","",IFERROR(INDEX(WBS_CBS!$K$5:$K$16,MATCH($D14,WBS_CBS!$A$5:$A$16,0)),"")) | X14: =IF($D14="","",IFERROR(INDEX(WBS_CBS!$F$5:$F$16,MATCH($D14,WBS_CBS!$A$5:$A$16,0)),"")) | AA14: =IF($D14="","",IFERROR(INDEX(WBS_CBS!$L$5:$L$16,MATCH($D14,WBS_CBS!$A$5:$A$16,0)),""))
C15: =IF($D15="","",IFERROR(INDEX(WBS_CBS!$E$5:$E$16,MATCH($D15,WBS_CBS!$A$5:$A$16,0)),"")) | E15: =IF($D15="","",IFERROR(INDEX(WBS_CBS!$C$5:$C$16,MATCH($D15,WBS_CBS!$A$5:$A$16,0)),"")) | F15: =IF($D15="","",IFERROR(INDEX(WBS_CBS!$J$5:$J$16,MATCH($D15,WBS_CBS!$A$5:$A$16,0)),"")) | L15: =IF($K15="","",IFERROR(INDEX(FX_Rates!$B$5:$B$14,MATCH($K15,FX_Rates!$A$5:$A$14,0)),"")) | M15: =IF(OR($H15="",$J15=""),"",$H15*$J15) | N15: =IF(OR($M15="",$L15=""),"",$M15*$L15) | P15: =IF($O15="","",IFERROR(INDEX(Basis_of_Estimate!$C$5:$C$9,MATCH($O15,Basis_of_Estimate!$A$5:$A$9,0)),"")) | Q15: =IF($O15="","",IFERROR(INDEX(Basis_of_Estimate!$D$5:$D$9,MATCH($O15,Basis_of_Estimate!$A$5:$A$9,0)),"")) | R15: =IF($N15="","",$N15*(1+$P15)) | S15: =IF($N15="","",$N15) | T15: =IF($N15="","",$N15*(1+$Q15)) | U15: =IF($D15="","",IFERROR(INDEX(WBS_CBS!$M$5:$M$16,MATCH($D15,WBS_CBS!$A$5:$A$16,0)),"Yes")) | V15: =IF($D15="","",IFERROR(INDEX(WBS_CBS!$N$5:$N$16,MATCH($D15,WBS_CBS!$A$5:$A$16,0)),"Yes")) | W15: =IF($D15="","",IFERROR(INDEX(WBS_CBS!$K$5:$K$16,MATCH($D15,WBS_CBS!$A$5:$A$16,0)),"")) | X15: =IF($D15="","",IFERROR(INDEX(WBS_CBS!$F$5:$F$16,MATCH($D15,WBS_CBS!$A$5:$A$16,0)),"")) | AA15: =IF($D15="","",IFERROR(INDEX(WBS_CBS!$L$5:$L$16,MATCH($D15,WBS_CBS!$A$5:$A$16,0)),""))
C16: =IF($D16="","",IFERROR(INDEX(WBS_CBS!$E$5:$E$16,MATCH($D16,WBS_CBS!$A$5:$A$16,0)),"")) | E16: =IF($D16="","",IFERROR(INDEX(WBS_CBS!$C$5:$C$16,MATCH($D16,WBS_CBS!$A$5:$A$16,0)),"")) | F16: =IF($D16="","",IFERROR(INDEX(WBS_CBS!$J$5:$J$16,MATCH($D16,WBS_CBS!$A$5:$A$16,0)),"")) | L16: =IF($K16="","",IFERROR(INDEX(FX_Rates!$B$5:$B$14,MATCH($K16,FX_Rates!$A$5:$A$14,0)),"")) | M16: =IF(OR($H16="",$J16=""),"",$H16*$J16) | N16: =IF(OR($M16="",$L16=""),"",$M16*$L16) | P16: =IF($O16="","",IFERROR(INDEX(Basis_of_Estimate!$C$5:$C$9,MATCH($O16,Basis_of_Estimate!$A$5:$A$9,0)),"")) | Q16: =IF($O16="","",IFERROR(INDEX(Basis_of_Estimate!$D$5:$D$9,MATCH($O16,Basis_of_Estimate!$A$5:$A$9,0)),"")) | R16: =IF($N16="","",$N16*(1+$P16)) | S16: =IF($N16="","",$N16) | T16: =IF($N16="","",$N16*(1+$Q16)) | U16: =IF($D16="","",IFERROR(INDEX(WBS_CBS!$M$5:$M$16,MATCH($D16,WBS_CBS!$A$5:$A$16,0)),"Yes")) | V16: =IF($D16="","",IFERROR(INDEX(WBS_CBS!$N$5:$N$16,MATCH($D16,WBS_CBS!$A$5:$A$16,0)),"Yes")) | W16: =IF($D16="","",IFERROR(INDEX(WBS_CBS!$K$5:$K$16,MATCH($D16,WBS_CBS!$A$5:$A$16,0)),"")) | X16: =IF($D16="","",IFERROR(INDEX(WBS_CBS!$F$5:$F$16,MATCH($D16,WBS_CBS!$A$5:$A$16,0)),"")) | AA16: =IF($D16="","",IFERROR(INDEX(WBS_CBS!$L$5:$L$16,MATCH($D16,WBS_CBS!$A$5:$A$16,0)),""))
C17: =IF($D17="","",IFERROR(INDEX(WBS_CBS!$E$5:$E$16,MATCH($D17,WBS_CBS!$A$5:$A$16,0)),"")) | E17: =IF($D17="","",IFERROR(INDEX(WBS_CBS!$C$5:$C$16,MATCH($D17,WBS_CBS!$A$5:$A$16,0)),"")) | F17: =IF($D17="","",IFERROR(INDEX(WBS_CBS!$J$5:$J$16,MATCH($D17,WBS_CBS!$A$5:$A$16,0)),"")) | L17: =IF($K17="","",IFERROR(INDEX(FX_Rates!$B$5:$B$14,MATCH($K17,FX_Rates!$A$5:$A$14,0)),"")) | M17: =IF(OR($H17="",$J17=""),"",$H17*$J17) | N17: =IF(OR($M17="",$L17=""),"",$M17*$L17) | P17: =IF($O17="","",IFERROR(INDEX(Basis_of_Estimate!$C$5:$C$9,MATCH($O17,Basis_of_Estimate!$A$5:$A$9,0)),"")) | Q17: =IF($O17="","",IFERROR(INDEX(Basis_of_Estimate!$D$5:$D$9,MATCH($O17,Basis_of_Estimate!$A$5:$A$9,0)),"")) | R17: =IF($N17="","",$N17*(1+$P17)) | S17: =IF($N17="","",$N17) | T17: =IF($N17="","",$N17*(1+$Q17)) | U17: =IF($D17="","",IFERROR(INDEX(WBS_CBS!$M$5:$M$16,MATCH($D17,WBS_CBS!$A$5:$A$16,0)),"Yes")) | V17: =IF($D17="","",IFERROR(INDEX(WBS_CBS!$N$5:$N$16,MATCH($D17,WBS_CBS!$A$5:$A$16,0)),"Yes")) | W17: =IF($D17="","",IFERROR(INDEX(WBS_CBS!$K$5:$K$16,MATCH($D17,WBS_CBS!$A$5:$A$16,0)),"")) | X17: =IF($D17="","",IFERROR(INDEX(WBS_CBS!$F$5:$F$16,MATCH($D17,WBS_CBS!$A$5:$A$16,0)),"")) | AA17: =IF($D17="","",IFERROR(INDEX(WBS_CBS!$L$5:$L$16,MATCH($D17,WBS_CBS!$A$5:$A$16,0)),""))
C18: =IF($D18="","",IFERROR(INDEX(WBS_CBS!$E$5:$E$16,MATCH($D18,WBS_CBS!$A$5:$A$16,0)),"")) | E18: =IF($D18="","",IFERROR(INDEX(WBS_CBS!$C$5:$C$16,MATCH($D18,WBS_CBS!$A$5:$A$16,0)),"")) | F18: =IF($D18="","",IFERROR(INDEX(WBS_CBS!$J$5:$J$16,MATCH($D18,WBS_CBS!$A$5:$A$16,0)),"")) | L18: =IF($K18="","",IFERROR(INDEX(FX_Rates!$B$5:$B$14,MATCH($K18,FX_Rates!$A$5:$A$14,0)),"")) | M18: =IF(OR($H18="",$J18=""),"",$H18*$J18) | N18: =IF(OR($M18="",$L18=""),"",$M18*$L18) | P18: =IF($O18="","",IFERROR(INDEX(Basis_of_Estimate!$C$5:$C$9,MATCH($O18,Basis_of_Estimate!$A$5:$A$9,0)),"")) | Q18: =IF($O18="","",IFERROR(INDEX(Basis_of_Estimate!$D$5:$D$9,MATCH($O18,Basis_of_Estimate!$A$5:$A$9,0)),"")) | R18: =IF($N18="","",$N18*(1+$P18)) | S18: =IF($N18="","",$N18) | T18: =IF($N18="","",$N18*(1+$Q18)) | U18: =IF($D18="","",IFERROR(INDEX(WBS_CBS!$M$5:$M$16,MATCH($D18,WBS_CBS!$A$5:$A$16,0)),"Yes")) | V18: =IF($D18="","",IFERROR(INDEX(WBS_CBS!$N$5:$N$16,MATCH($D18,WBS_CBS!$A$5:$A$16,0)),"Yes")) | W18: =IF($D18="","",IFERROR(INDEX(WBS_CBS!$K$5:$K$16,MATCH($D18,WBS_CBS!$A$5:$A$16,0)),"")) | X18: =IF($D18="","",IFERROR(INDEX(WBS_CBS!$F$5:$F$16,MATCH($D18,WBS_CBS!$A$5:$A$16,0)),"")) | AA18: =IF($D18="","",IFERROR(INDEX(WBS_CBS!$L$5:$L$16,MATCH($D18,WBS_CBS!$A$5:$A$16,0)),""))
C19: =IF($D19="","",IFERROR(INDEX(WBS_CBS!$E$5:$E$16,MATCH($D19,WBS_CBS!$A$5:$A$16,0)),"")) | E19: =IF($D19="","",IFERROR(INDEX(WBS_CBS!$C$5:$C$16,MATCH($D19,WBS_CBS!$A$5:$A$16,0)),"")) | F19: =IF($D19="","",IFERROR(INDEX(WBS_CBS!$J$5:$J$16,MATCH($D19,WBS_CBS!$A$5:$A$16,0)),"")) | L19: =IF($K19="","",IFERROR(INDEX(FX_Rates!$B$5:$B$14,MATCH($K19,FX_Rates!$A$5:$A$14,0)),"")) | M19: =IF(OR($H19="",$J19=""),"",$H19*$J19) | N19: =IF(OR($M19="",$L19=""),"",$M19*$L19) | P19: =IF($O19="","",IFERROR(INDEX(Basis_of_Estimate!$C$5:$C$9,MATCH($O19,Basis_of_Estimate!$A$5:$A$9,0)),"")) | Q19: =IF($O19="","",IFERROR(INDEX(Basis_of_Estimate!$D$5:$D$9,MATCH($O19,Basis_of_Estimate!$A$5:$A$9,0)),"")) | R19: =IF($N19="","",$N19*(1+$P19)) | S19: =IF($N19="","",$N19) | T19: =IF($N19="","",$N19*(1+$Q19)) | U19: =IF($D19="","",IFERROR(INDEX(WBS_CBS!$M$5:$M$16,MATCH($D19,WBS_CBS!$A$5:$A$16,0)),"Yes")) | V19: =IF($D19="","",IFERROR(INDEX(WBS_CBS!$N$5:$N$16,MATCH($D19,WBS_CBS!$A$5:$A$16,0)),"Yes")) | W19: =IF($D19="","",IFERROR(INDEX(WBS_CBS!$K$5:$K$16,MATCH($D19,WBS_CBS!$A$5:$A$16,0)),"")) | X19: =IF($D19="","",IFERROR(INDEX(WBS_CBS!$F$5:$F$16,MATCH($D19,WBS_CBS!$A$5:$A$16,0)),"")) | AA19: =IF($D19="","",IFERROR(INDEX(WBS_CBS!$L$5:$L$16,MATCH($D19,WBS_CBS!$A$5:$A$16,0)),""))
C20: =IF($D20="","",IFERROR(INDEX(WBS_CBS!$E$5:$E$16,MATCH($D20,WBS_CBS!$A$5:$A$16,0)),"")) | E20: =IF($D20="","",IFERROR(INDEX(WBS_CBS!$C$5:$C$16,MATCH($D20,WBS_CBS!$A$5:$A$16,0)),"")) | F20: =IF($D20="","",IFERROR(INDEX(WBS_CBS!$J$5:$J$16,MATCH($D20,WBS_CBS!$A$5:$A$16,0)),"")) | L20: =IF($K20="","",IFERROR(INDEX(FX_Rates!$B$5:$B$14,MATCH($K20,FX_Rates!$A$5:$A$14,0)),"")) | M20: =IF(OR($H20="",$J20=""),"",$H20*$J20) | N20: =IF(OR($M20="",$L20=""),"",$M20*$L20) | P20: =IF($O20="","",IFERROR(INDEX(Basis_of_Estimate!$C$5:$C$9,MATCH($O20,Basis_of_Estimate!$A$5:$A$9,0)),"")) | Q20: =IF($O20="","",IFERROR(INDEX(Basis_of_Estimate!$D$5:$D$9,MATCH($O20,Basis_of_Estimate!$A$5:$A$9,0)),"")) | R20: =IF($N20="","",$N20*(1+$P20)) | S20: =IF($N20="","",$N20) | T20: =IF($N20="","",$N20*(1+$Q20)) | U20: =IF($D20="","",IFERROR(INDEX(WBS_CBS!$M$5:$M$16,MATCH($D20,WBS_CBS!$A$5:$A$16,0)),"Yes")) | V20: =IF($D20="","",IFERROR(INDEX(WBS_CBS!$N$5:$N$16,MATCH($D20,WBS_CBS!$A$5:$A$16,0)),"Yes")) | W20: =IF($D20="","",IFERROR(INDEX(WBS_CBS!$K$5:$K$16,MATCH($D20,WBS_CBS!$A$5:$A$16,0)),"")) | X20: =IF($D20="","",IFERROR(INDEX(WBS_CBS!$F$5:$F$16,MATCH($D20,WBS_CBS!$A$5:$A$16,0)),"")) | AA20: =IF($D20="","",IFERROR(INDEX(WBS_CBS!$L$5:$L$16,MATCH($D20,WBS_CBS!$A$5:$A$16,0)),""))
... C104: =IF($D104="","",IFERROR(INDEX(WBS_CBS!$E$5:$E$16,MATCH($D104,WBS_CBS!$A$5:$A$16,0)),"")) | E104: =IF($D104="","",IFERROR(INDEX(WBS_CBS!$C$5:$C$16,MATCH($D104,WBS_CBS!$A$5:$A$16,0)),"")) | F104: =IF($D104="","",IFERROR(INDEX(WBS_CBS!$J$5:$J$16,MATCH($D104,WBS_CBS!$A$5:$A$16,0)),"")) | L104: =IF($K104="","",IFERROR(INDEX(FX_Rates!$B$5:$B$14,MATCH($K104,FX_Rates!$A$5:$A$14,0)),"")) | M104: =IF(OR($H104="",$J104=""),"",$H104*$J104) | N104: =IF(OR($M104="",$L104=""),"",$M104*$L104) | P104: =IF($O104="","",IFERROR(INDEX(Basis_of_Estimate!$C$5:$C$9,MATCH($O104,Basis_of_Estimate!$A$5:$A$9,0)),"")) | Q104: =IF($O104="","",IFERROR(INDEX(Basis_of_Estimate!$D$5:$D$9,MATCH($O104,Basis_of_Estimate!$A$5:$A$9,0)),"")) | R104: =IF($N104="","",$N104*(1+$P104)) | S104: =IF($N104="","",$N104) | T104: =IF($N104="","",$N104*(1+$Q104)) | U104: =IF($D104="","",IFERROR(INDEX(WBS_CBS!$M$5:$M$16,MATCH($D104,WBS_CBS!$A$5:$A$16,0)),"Yes")) | V104: =IF($D104="","",IFERROR(INDEX(WBS_CBS!$N$5:$N$16,MATCH($D104,WBS_CBS!$A$5:$A$16,0)),"Yes")) | W104: =IF($D104="","",IFERROR(INDEX(WBS_CBS!$K$5:$K$16,MATCH($D104,WBS_CBS!$A$5:$A$16,0)),"")) | X104: =IF($D104="","",IFERROR(INDEX(WBS_CBS!$F$5:$F$16,MATCH($D104,WBS_CBS!$A$5:$A$16,0)),"")) | AA104: =IF($D104="","",IFERROR(INDEX(WBS_CBS!$L$5:$L$16,MATCH($D104,WBS_CBS!$A$5:$A$16,0)),""))

Sheet Resource_Rates
A1: Resource Rates
A2: Hourly rate based resource database. Monthly rate = hourly rate × hours/month.
A4: Role | B4: Discipline | C4: Location | D4: Currency | E4: Hourly Rate | F4: Hours per Month | G4: Monthly Rate | H4: FX Rate | I4: Monthly Rate EUR | J4: Notes
A5: Project Manager | B5: Project Management | C5: Spain | D5: EUR | E5: 130 | F5: 160 | G5: =E5*F5 | H5: =IFERROR(VLOOKUP(D5,FX_Rates!$A$5:$B$20,2,FALSE),1) | I5: =G5*H5 | J5: Demo rate
A6: Engineering Manager | B6: Project Management | C6: Spain | D6: EUR | E6: 120 | F6: 160 | G6: =E6*F6 | H6: =IFERROR(VLOOKUP(D6,FX_Rates!$A$5:$B$20,2,FALSE),1) | I6: =G6*H6 | J6: Demo rate
A7: Project Controls Lead | B7: Project Management | C7: Spain | D7: EUR | E7: 95 | F7: 160 | G7: =E7*F7 | H7: =IFERROR(VLOOKUP(D7,FX_Rates!$A$5:$B$20,2,FALSE),1) | I7: =G7*H7 | J7: Demo rate
A8: Cost Estimator | B8: Project Management | C8: Remote | D8: EUR | E8: 90 | F8: 160 | G8: =E8*F8 | H8: =IFERROR(VLOOKUP(D8,FX_Rates!$A$5:$B$20,2,FALSE),1) | I8: =G8*H8 | J8: Demo rate
A9: Planner / Scheduler | B9: Project Management | C9: Remote | D9: EUR | E9: 85 | F9: 160 | G9: =E9*F9 | H9: =IFERROR(VLOOKUP(D9,FX_Rates!$A$5:$B$20,2,FALSE),1) | I9: =G9*H9 | J9: Demo rate
A10: Process Engineer | B10: Process | C10: Remote | D10: EUR | E10: 90 | F10: 160 | G10: =E10*F10 | H10: =IFERROR(VLOOKUP(D10,FX_Rates!$A$5:$B$20,2,FALSE),1) | I10: =G10*H10 | J10: Demo rate
A11: Procurement Lead | B11: Procurement | C11: Spain | D11: EUR | E11: 90 | F11: 160 | G11: =E11*F11 | H11: =IFERROR(VLOOKUP(D11,FX_Rates!$A$5:$B$20,2,FALSE),1) | I11: =G11*H11 | J11: Demo rate
A12: Construction Manager | B12: Construction | C12: Spain | D12: EUR | E12: 115 | F12: 160 | G12: =E12*F12 | H12: =IFERROR(VLOOKUP(D12,FX_Rates!$A$5:$B$20,2,FALSE),1) | I12: =G12*H12 | J12: Demo rate
A13: HSE Manager | B13: HSE | C13: Spain | D13: EUR | E13: 85 | F13: 160 | G13: =E13*F13 | H13: =IFERROR(VLOOKUP(D13,FX_Rates!$A$5:$B$20,2,FALSE),1) | I13: =G13*H13 | J13: Demo rate
A14: Commissioning Lead | B14: Commissioning | C14: Spain | D14: EUR | E14: 110 | F14: 160 | G14: =E14*F14 | H14: =IFERROR(VLOOKUP(D14,FX_Rates!$A$5:$B$20,2,FALSE),1) | I14: =G14*H14 | J14: Demo rate
A15: Document Controller | B15: Project Management | C15: Remote | D15: EUR | E15: 60 | F15: 160 | G15: =E15*F15 | H15: =IFERROR(VLOOKUP(D15,FX_Rates!$A$5:$B$20,2,FALSE),1) | I15: =G15*H15 | J15: Demo rate

Sheet Manpower_Plan
A1: Manpower Plan
A2: Dynamic 36-month FTE plan linked to Resource_Rates. Macro can regenerate months from Project_Setup.
A4: Role | B4: Discipline | C4: Monthly Rate EUR | D4: Total FTE-Months | E4: Total Cost EUR | F4: =IF(COLUMN()-5<='Project_Setup'!$B$12,DATE(YEAR('Project_Setup'!$B$10),MONTH('Project_Setup'!$B$10)+COLUMN()-6,DAY('Project_Setup'!$B$10)),"") | G4: =IF(COLUMN()-5<='Project_Setup'!$B$12,DATE(YEAR('Project_Setup'!$B$10),MONTH('Project_Setup'!$B$10)+COLUMN()-6,DAY('Project_Setup'!$B$10)),"") | H4: =IF(COLUMN()-5<='Project_Setup'!$B$12,DATE(YEAR('Project_Setup'!$B$10),MONTH('Project_Setup'!$B$10)+COLUMN()-6,DAY('Project_Setup'!$B$10)),"") | I4: =IF(COLUMN()-5<='Project_Setup'!$B$12,DATE(YEAR('Project_Setup'!$B$10),MONTH('Project_Setup'!$B$10)+COLUMN()-6,DAY('Project_Setup'!$B$10)),"") | J4: =IF(COLUMN()-5<='Project_Setup'!$B$12,DATE(YEAR('Project_Setup'!$B$10),MONTH('Project_Setup'!$B$10)+COLUMN()-6,DAY('Project_Setup'!$B$10)),"") | K4: =IF(COLUMN()-5<='Project_Setup'!$B$12,DATE(YEAR('Project_Setup'!$B$10),MONTH('Project_Setup'!$B$10)+COLUMN()-6,DAY('Project_Setup'!$B$10)),"") | L4: =IF(COLUMN()-5<='Project_Setup'!$B$12,DATE(YEAR('Project_Setup'!$B$10),MONTH('Project_Setup'!$B$10)+COLUMN()-6,DAY('Project_Setup'!$B$10)),"") | M4: =IF(COLUMN()-5<='Project_Setup'!$B$12,DATE(YEAR('Project_Setup'!$B$10),MONTH('Project_Setup'!$B$10)+COLUMN()-6,DAY('Project_Setup'!$B$10)),"") | ... BM4: =IF(COLUMN()-5<='Project_Setup'!$B$12,DATE(YEAR('Project_Setup'!$B$10),MONTH('Project_Setup'!$B$10)+COLUMN()-6,DAY('Project_Setup'!$B$10)),"")
A5: Project Manager | B5: Project Management | C5: =IFERROR(INDEX(Resource_Rates!$I$5:$I$100,MATCH(A5,Resource_Rates!$A$5:$A$100,0)),0) | D5: =SUM(F5:BM5) | E5: =C5*D5 | F5: 0.863 | G5: 0.863 | H5: 0.863 | I5: 0.863 | J5: 0.863 | K5: 0.863 | L5: 0.863 | M5: 0.863 | N5: 0.863 | O5: 0.863 | P5: 0.863 | Q5: 0.863 | R5: 0.863 | S5: 0.863 | T5: 0.863 | U5: 0.863 | V5: 0.863 | W5: 0.863 | X5: 0.863 | Y5: 0.863 | Z5: 0.863 | AA5: 0.863 | AB5: 0.863 | AC5: 0.863 | AD5: 0.863 | AE5: 0.863 | AF5: 0.863 | AG5: 0.863 | AH5: 0.863 | AI5: 0.863 | AJ5: 0.863 | AK5: 0.863 | AL5: 0.863 | AM5: 0.863 | AN5: 0.863 | AO5: 0.863
A6: Engineering Manager | B6: Project Management | C6: =IFERROR(INDEX(Resource_Rates!$I$5:$I$100,MATCH(A6,Resource_Rates!$A$5:$A$100,0)),0) | D6: =SUM(F6:BM6) | E6: =C6*D6 | F6: 0.863 | G6: 0.863 | H6: 0.863 | I6: 0.863 | J6: 0.863 | K6: 0.863 | L6: 0.863 | M6: 0.863 | N6: 0.863 | O6: 0.863 | P6: 0.863 | Q6: 0.863 | R6: 0.863 | S6: 0.863 | T6: 0.863 | U6: 0.863 | V6: 0.863 | W6: 0.863 | X6: 0.431 | Y6: 0.431 | Z6: 0.431 | AA6: 0.431 | AB6: 0.431 | AC6: 0.431 | AD6: 0.431 | AE6: 0.431 | AF6: 0.431 | AG6: 0.431 | AH6: 0.431 | AI6: 0.431 | AJ6: 0.173 | AK6: 0.173 | AL6: 0.173 | AM6: 0.173 | AN6: 0.173 | AO6: 0.173
A7: Project Controls Lead | B7: Project Management | C7: =IFERROR(INDEX(Resource_Rates!$I$5:$I$100,MATCH(A7,Resource_Rates!$A$5:$A$100,0)),0) | D7: =SUM(F7:BM7) | E7: =C7*D7 | F7: 0.863 | G7: 0.863 | H7: 0.863 | I7: 0.863 | J7: 0.863 | K7: 0.863 | L7: 0.863 | M7: 0.863 | N7: 0.863 | O7: 0.863 | P7: 0.863 | Q7: 0.863 | R7: 0.863 | S7: 0.863 | T7: 0.863 | U7: 0.863 | V7: 0.863 | W7: 0.863 | X7: 0.863 | Y7: 0.863 | Z7: 0.863 | AA7: 0.863 | AB7: 0.863 | AC7: 0.863 | AD7: 0.863 | AE7: 0.863 | AF7: 0.863 | AG7: 0.863 | AH7: 0.863 | AI7: 0.863 | AJ7: 0.863 | AK7: 0.863 | AL7: 0.863 | AM7: 0.863 | AN7: 0.863 | AO7: 0.863
A8: Cost Estimator | B8: Project Management | C8: =IFERROR(INDEX(Resource_Rates!$I$5:$I$100,MATCH(A8,Resource_Rates!$A$5:$A$100,0)),0) | D8: =SUM(F8:BM8) | E8: =C8*D8 | F8: 0.69 | G8: 0.69 | H8: 0.69 | I8: 0.69 | J8: 0.69 | K8: 0.69 | L8: 0.69 | M8: 0.69 | N8: 0.345 | O8: 0.345 | P8: 0.345 | Q8: 0.345 | R8: 0.345 | S8: 0.345 | T8: 0.345 | U8: 0.345 | V8: 0.345 | W8: 0.345 | X8: 0.173 | Y8: 0.173 | Z8: 0.173 | AA8: 0.173 | AB8: 0.173 | AC8: 0.173 | AD8: 0.173 | AE8: 0.173 | AF8: 0.173 | AG8: 0.173 | AH8: 0.173 | AI8: 0.173 | AJ8: 0.173 | AK8: 0.173 | AL8: 0.173 | AM8: 0.173 | AN8: 0.173 | AO8: 0.173
A9: Planner / Scheduler | B9: Project Management | C9: =IFERROR(INDEX(Resource_Rates!$I$5:$I$100,MATCH(A9,Resource_Rates!$A$5:$A$100,0)),0) | D9: =SUM(F9:BM9) | E9: =C9*D9 | F9: 0.431 | G9: 0.431 | H9: 0.431 | I9: 0.431 | J9: 0.431 | K9: 0.431 | L9: 0.431 | M9: 0.431 | N9: 0.431 | O9: 0.431 | P9: 0.431 | Q9: 0.431 | R9: 0.863 | S9: 0.863 | T9: 0.863 | U9: 0.863 | V9: 0.863 | W9: 0.863 | X9: 0.863 | Y9: 0.863 | Z9: 0.863 | AA9: 0.863 | AB9: 0.863 | AC9: 0.863 | AD9: 0.863 | AE9: 0.863 | AF9: 0.863 | AG9: 0.863 | AH9: 0.863 | AI9: 0.863 | AJ9: 0.69 | AK9: 0.69 | AL9: 0.69 | AM9: 0.69 | AN9: 0.69 | AO9: 0.69
A10: Process Engineer | B10: Process | C10: =IFERROR(INDEX(Resource_Rates!$I$5:$I$100,MATCH(A10,Resource_Rates!$A$5:$A$100,0)),0) | D10: =SUM(F10:BM10) | E10: =C10*D10 | F10: 2.588 | G10: 2.588 | H10: 2.588 | I10: 2.588 | J10: 2.588 | K10: 2.588 | L10: 2.588 | M10: 2.588 | N10: 2.588 | O10: 2.588 | P10: 2.588 | Q10: 2.588 | R10: 1.725 | S10: 1.725 | T10: 1.725 | U10: 1.725 | V10: 1.725 | W10: 1.725 | X10: 1.725 | Y10: 1.725 | Z10: 1.725 | AA10: 1.725 | AB10: 0.431 | AC10: 0.431 | AD10: 0.431 | AE10: 0.431 | AF10: 0.431 | AG10: 0.431 | AH10: 0.431 | AI10: 0.431 | AJ10: 0.431 | AK10: 0.431 | AL10: 0.431 | AM10: 0.431 | AN10: 0.431 | AO10: 0.431
A11: Procurement Lead | B11: Procurement | C11: =IFERROR(INDEX(Resource_Rates!$I$5:$I$100,MATCH(A11,Resource_Rates!$A$5:$A$100,0)),0) | D11: =SUM(F11:BM11) | E11: =C11*D11 | F11: 0.259 | G11: 0.259 | H11: 0.259 | I11: 0.259 | J11: 0.259 | K11: 0.259 | L11: 0.863 | M11: 0.863 | N11: 0.863 | O11: 0.863 | P11: 0.863 | Q11: 0.863 | R11: 0.863 | S11: 0.863 | T11: 0.863 | U11: 0.863 | V11: 0.863 | W11: 0.863 | X11: 0.863 | Y11: 0.863 | Z11: 0.863 | AA11: 0.863 | AB11: 0.863 | AC11: 0.863 | AD11: 0.431 | AE11: 0.431 | AF11: 0.431 | AG11: 0.431 | AH11: 0.431 | AI11: 0.431 | AJ11: 0.431 | AK11: 0.431 | AL11: 0.173 | AM11: 0.173 | AN11: 0.173 | AO11: 0.173
A12: Construction Manager | B12: Construction | C12: =IFERROR(INDEX(Resource_Rates!$I$5:$I$100,MATCH(A12,Resource_Rates!$A$5:$A$100,0)),0) | D12: =SUM(F12:BM12) | E12: =C12*D12 | F12: 0 | G12: 0 | H12: 0 | I12: 0 | J12: 0 | K12: 0 | L12: 0 | M12: 0 | N12: 0 | O12: 0 | P12: 0 | Q12: 0 | R12: 0.431 | S12: 0.431 | T12: 0.431 | U12: 0.431 | V12: 0.863 | W12: 0.863 | X12: 0.863 | Y12: 0.863 | Z12: 0.863 | AA12: 0.863 | AB12: 0.863 | AC12: 0.863 | AD12: 0.863 | AE12: 0.863 | AF12: 0.863 | AG12: 0.863 | AH12: 0.863 | AI12: 0.863 | AJ12: 0.863 | AK12: 0.863 | AL12: 0.431 | AM12: 0.431 | AN12: 0.431 | AO12: 0.431
A13: HSE Manager | B13: HSE | C13: =IFERROR(INDEX(Resource_Rates!$I$5:$I$100,MATCH(A13,Resource_Rates!$A$5:$A$100,0)),0) | D13: =SUM(F13:BM13) | E13: =C13*D13 | F13: 0 | G13: 0 | H13: 0 | I13: 0 | J13: 0 | K13: 0 | L13: 0 | M13: 0 | N13: 0 | O13: 0 | P13: 0 | Q13: 0 | R13: 0 | S13: 0 | T13: 0.604 | U13: 0.604 | V13: 0.604 | W13: 0.604 | X13: 0.863 | Y13: 0.863 | Z13: 0.863 | AA13: 0.863 | AB13: 0.863 | AC13: 0.863 | AD13: 0.863 | AE13: 0.863 | AF13: 0.863 | AG13: 0.863 | AH13: 0.863 | AI13: 0.863 | AJ13: 0.863 | AK13: 0.863 | AL13: 0.345 | AM13: 0.345 | AN13: 0.345 | AO13: 0.345
A14: Commissioning Lead | B14: Commissioning | C14: =IFERROR(INDEX(Resource_Rates!$I$5:$I$100,MATCH(A14,Resource_Rates!$A$5:$A$100,0)),0) | D14: =SUM(F14:BM14) | E14: =C14*D14 | F14: 0 | G14: 0 | H14: 0 | I14: 0 | J14: 0 | K14: 0 | L14: 0 | M14: 0 | N14: 0 | O14: 0 | P14: 0 | Q14: 0 | R14: 0 | S14: 0 | T14: 0 | U14: 0 | V14: 0 | W14: 0 | X14: 0 | Y14: 0 | Z14: 0 | AA14: 0 | AB14: 0 | AC14: 0 | AD14: 0 | AE14: 0 | AF14: 0 | AG14: 0 | AH14: 1.294 | AI14: 1.294 | AJ14: 1.294 | AK14: 1.294 | AL14: 1.294 | AM14: 1.294 | AN14: 1.294 | AO14: 1.294
A15: Document Controller | B15: Project Management | C15: =IFERROR(INDEX(Resource_Rates!$I$5:$I$100,MATCH(A15,Resource_Rates!$A$5:$A$100,0)),0) | D15: =SUM(F15:BM15) | E15: =C15*D15 | F15: 0.431 | G15: 0.431 | H15: 0.431 | I15: 0.431 | J15: 0.431 | K15: 0.431 | L15: 0.431 | M15: 0.431 | N15: 0.431 | O15: 0.431 | P15: 0.431 | Q15: 0.431 | R15: 0.431 | S15: 0.431 | T15: 0.431 | U15: 0.431 | V15: 0.431 | W15: 0.431 | X15: 0.431 | Y15: 0.431 | Z15: 0.431 | AA15: 0.431 | AB15: 0.431 | AC15: 0.431 | AD15: 0.431 | AE15: 0.431 | AF15: 0.431 | AG15: 0.431 | AH15: 0.431 | AI15: 0.431 | AJ15: 0.431 | AK15: 0.431 | AL15: 0.431 | AM15: 0.431 | AN15: 0.431 | AO15: 0.431

Sheet Indirect_Owner_Costs
A1: Indirect Owner Costs
A2: User input layer. Cost_Register must be rebuilt from these sheets via BuildCostRegister.
A4: Item ID | B4: Description | C4: Discipline | D4: WBS | E4: CBS | F4: Cost Category | G4: Cost Type | H4: Quantity | I4: Unit | J4: Unit Rate | K4: Currency | L4: FX Rate | M4: Base Cost | N4: Base Cost EUR | O4: Estimate Basis | P4: Accuracy Low % | Q4: Accuracy High % | R4: Low Cost | S4: Most Likely Cost | T4: High Cost | U4: Contingency Eligible | V4: Escalation Eligible | W4: Spend Category | X4: Phase | Y4: Start Month | Z4: End Month | AA4: Spend Curve | AB4: Notes
A5: IO-001 | B5: EPCM engineering services | C5: =IF($D5="","",IFERROR(INDEX(WBS_CBS!$E$5:$E$16,MATCH($D5,WBS_CBS!$A$5:$A$16,0)),"")) | D5: 2.0 | E5: =IF($D5="","",IFERROR(INDEX(WBS_CBS!$C$5:$C$16,MATCH($D5,WBS_CBS!$A$5:$A$16,0)),"")) | F5: =IF($D5="","",IFERROR(INDEX(WBS_CBS!$J$5:$J$16,MATCH($D5,WBS_CBS!$A$5:$A$16,0)),"")) | G5: EPCM | H5: 1 | I5: lot | J5: 2200000 | K5: EUR | L5: =IF($K5="","",IFERROR(INDEX(FX_Rates!$B$5:$B$14,MATCH($K5,FX_Rates!$A$5:$A$14,0)),"")) | M5: =IF(OR($H5="",$J5=""),"",$H5*$J5) | N5: =IF(OR($M5="",$L5=""),"",$M5*$L5) | O5: Class 3 | P5: =IF($O5="","",IFERROR(INDEX(Basis_of_Estimate!$C$5:$C$9,MATCH($O5,Basis_of_Estimate!$A$5:$A$9,0)),"")) | Q5: =IF($O5="","",IFERROR(INDEX(Basis_of_Estimate!$D$5:$D$9,MATCH($O5,Basis_of_Estimate!$A$5:$A$9,0)),"")) | R5: =IF($N5="","",$N5*(1+$P5)) | S5: =IF($N5="","",$N5) | T5: =IF($N5="","",$N5*(1+$Q5)) | U5: =IF($D5="","",IFERROR(INDEX(WBS_CBS!$M$5:$M$16,MATCH($D5,WBS_CBS!$A$5:$A$16,0)),"Yes")) | V5: =IF($D5="","",IFERROR(INDEX(WBS_CBS!$N$5:$N$16,MATCH($D5,WBS_CBS!$A$5:$A$16,0)),"Yes")) | W5: =IF($D5="","",IFERROR(INDEX(WBS_CBS!$K$5:$K$16,MATCH($D5,WBS_CBS!$A$5:$A$16,0)),"")) | X5: =IF($D5="","",IFERROR(INDEX(WBS_CBS!$F$5:$F$16,MATCH($D5,WBS_CBS!$A$5:$A$16,0)),"")) | Y5: 1 | Z5: 24 | AA5: =IF($D5="","",IFERROR(INDEX(WBS_CBS!$L$5:$L$16,MATCH($D5,WBS_CBS!$A$5:$A$16,0)),""))
A6: IO-002 | B6: Construction management and supervision | C6: =IF($D6="","",IFERROR(INDEX(WBS_CBS!$E$5:$E$16,MATCH($D6,WBS_CBS!$A$5:$A$16,0)),"")) | D6: 9.0 | E6: =IF($D6="","",IFERROR(INDEX(WBS_CBS!$C$5:$C$16,MATCH($D6,WBS_CBS!$A$5:$A$16,0)),"")) | F6: =IF($D6="","",IFERROR(INDEX(WBS_CBS!$J$5:$J$16,MATCH($D6,WBS_CBS!$A$5:$A$16,0)),"")) | G6: EPCM | H6: 1 | I6: lot | J6: 800000 | K6: EUR | L6: =IF($K6="","",IFERROR(INDEX(FX_Rates!$B$5:$B$14,MATCH($K6,FX_Rates!$A$5:$A$14,0)),"")) | M6: =IF(OR($H6="",$J6=""),"",$H6*$J6) | N6: =IF(OR($M6="",$L6=""),"",$M6*$L6) | O6: Class 3 | P6: =IF($O6="","",IFERROR(INDEX(Basis_of_Estimate!$C$5:$C$9,MATCH($O6,Basis_of_Estimate!$A$5:$A$9,0)),"")) | Q6: =IF($O6="","",IFERROR(INDEX(Basis_of_Estimate!$D$5:$D$9,MATCH($O6,Basis_of_Estimate!$A$5:$A$9,0)),"")) | R6: =IF($N6="","",$N6*(1+$P6)) | S6: =IF($N6="","",$N6) | T6: =IF($N6="","",$N6*(1+$Q6)) | U6: =IF($D6="","",IFERROR(INDEX(WBS_CBS!$M$5:$M$16,MATCH($D6,WBS_CBS!$A$5:$A$16,0)),"Yes")) | V6: =IF($D6="","",IFERROR(INDEX(WBS_CBS!$N$5:$N$16,MATCH($D6,WBS_CBS!$A$5:$A$16,0)),"Yes")) | W6: =IF($D6="","",IFERROR(INDEX(WBS_CBS!$K$5:$K$16,MATCH($D6,WBS_CBS!$A$5:$A$16,0)),"")) | X6: =IF($D6="","",IFERROR(INDEX(WBS_CBS!$F$5:$F$16,MATCH($D6,WBS_CBS!$A$5:$A$16,0)),"")) | Y6: 14 | Z6: 34 | AA6: =IF($D6="","",IFERROR(INDEX(WBS_CBS!$L$5:$L$16,MATCH($D6,WBS_CBS!$A$5:$A$16,0)),""))
A7: IO-003 | B7: Permits, studies and owner reviews | C7: =IF($D7="","",IFERROR(INDEX(WBS_CBS!$E$5:$E$16,MATCH($D7,WBS_CBS!$A$5:$A$16,0)),"")) | D7: 11.0 | E7: =IF($D7="","",IFERROR(INDEX(WBS_CBS!$C$5:$C$16,MATCH($D7,WBS_CBS!$A$5:$A$16,0)),"")) | F7: =IF($D7="","",IFERROR(INDEX(WBS_CBS!$J$5:$J$16,MATCH($D7,WBS_CBS!$A$5:$A$16,0)),"")) | G7: Owner | H7: 1 | I7: lot | J7: 600000 | K7: EUR | L7: =IF($K7="","",IFERROR(INDEX(FX_Rates!$B$5:$B$14,MATCH($K7,FX_Rates!$A$5:$A$14,0)),"")) | M7: =IF(OR($H7="",$J7=""),"",$H7*$J7) | N7: =IF(OR($M7="",$L7=""),"",$M7*$L7) | O7: Class 3 | P7: =IF($O7="","",IFERROR(INDEX(Basis_of_Estimate!$C$5:$C$9,MATCH($O7,Basis_of_Estimate!$A$5:$A$9,0)),"")) | Q7: =IF($O7="","",IFERROR(INDEX(Basis_of_Estimate!$D$5:$D$9,MATCH($O7,Basis_of_Estimate!$A$5:$A$9,0)),"")) | R7: =IF($N7="","",$N7*(1+$P7)) | S7: =IF($N7="","",$N7) | T7: =IF($N7="","",$N7*(1+$Q7)) | U7: =IF($D7="","",IFERROR(INDEX(WBS_CBS!$M$5:$M$16,MATCH($D7,WBS_CBS!$A$5:$A$16,0)),"Yes")) | V7: =IF($D7="","",IFERROR(INDEX(WBS_CBS!$N$5:$N$16,MATCH($D7,WBS_CBS!$A$5:$A$16,0)),"Yes")) | W7: =IF($D7="","",IFERROR(INDEX(WBS_CBS!$K$5:$K$16,MATCH($D7,WBS_CBS!$A$5:$A$16,0)),"")) | X7: =IF($D7="","",IFERROR(INDEX(WBS_CBS!$F$5:$F$16,MATCH($D7,WBS_CBS!$A$5:$A$16,0)),"")) | Y7: 1 | Z7: 18 | AA7: =IF($D7="","",IFERROR(INDEX(WBS_CBS!$L$5:$L$16,MATCH($D7,WBS_CBS!$A$5:$A$16,0)),""))
A8: IO-004 | B8: Freight, logistics and temporary facilities | C8: =IF($D8="","",IFERROR(INDEX(WBS_CBS!$E$5:$E$16,MATCH($D8,WBS_CBS!$A$5:$A$16,0)),"")) | D8: 3.0 | E8: =IF($D8="","",IFERROR(INDEX(WBS_CBS!$C$5:$C$16,MATCH($D8,WBS_CBS!$A$5:$A$16,0)),"")) | F8: =IF($D8="","",IFERROR(INDEX(WBS_CBS!$J$5:$J$16,MATCH($D8,WBS_CBS!$A$5:$A$16,0)),"")) | G8: Freight | H8: 1 | I8: lot | J8: 400000 | K8: EUR | L8: =IF($K8="","",IFERROR(INDEX(FX_Rates!$B$5:$B$14,MATCH($K8,FX_Rates!$A$5:$A$14,0)),"")) | M8: =IF(OR($H8="",$J8=""),"",$H8*$J8) | N8: =IF(OR($M8="",$L8=""),"",$M8*$L8) | O8: Class 3 | P8: =IF($O8="","",IFERROR(INDEX(Basis_of_Estimate!$C$5:$C$9,MATCH($O8,Basis_of_Estimate!$A$5:$A$9,0)),"")) | Q8: =IF($O8="","",IFERROR(INDEX(Basis_of_Estimate!$D$5:$D$9,MATCH($O8,Basis_of_Estimate!$A$5:$A$9,0)),"")) | R8: =IF($N8="","",$N8*(1+$P8)) | S8: =IF($N8="","",$N8) | T8: =IF($N8="","",$N8*(1+$Q8)) | U8: =IF($D8="","",IFERROR(INDEX(WBS_CBS!$M$5:$M$16,MATCH($D8,WBS_CBS!$A$5:$A$16,0)),"Yes")) | V8: =IF($D8="","",IFERROR(INDEX(WBS_CBS!$N$5:$N$16,MATCH($D8,WBS_CBS!$A$5:$A$16,0)),"Yes")) | W8: =IF($D8="","",IFERROR(INDEX(WBS_CBS!$K$5:$K$16,MATCH($D8,WBS_CBS!$A$5:$A$16,0)),"")) | X8: =IF($D8="","",IFERROR(INDEX(WBS_CBS!$F$5:$F$16,MATCH($D8,WBS_CBS!$A$5:$A$16,0)),"")) | Y8: 8 | Z8: 28 | AA8: =IF($D8="","",IFERROR(INDEX(WBS_CBS!$L$5:$L$16,MATCH($D8,WBS_CBS!$A$5:$A$16,0)),""))
C9: =IF($D9="","",IFERROR(INDEX(WBS_CBS!$E$5:$E$16,MATCH($D9,WBS_CBS!$A$5:$A$16,0)),"")) | E9: =IF($D9="","",IFERROR(INDEX(WBS_CBS!$C$5:$C$16,MATCH($D9,WBS_CBS!$A$5:$A$16,0)),"")) | F9: =IF($D9="","",IFERROR(INDEX(WBS_CBS!$J$5:$J$16,MATCH($D9,WBS_CBS!$A$5:$A$16,0)),"")) | L9: =IF($K9="","",IFERROR(INDEX(FX_Rates!$B$5:$B$14,MATCH($K9,FX_Rates!$A$5:$A$14,0)),"")) | M9: =IF(OR($H9="",$J9=""),"",$H9*$J9) | N9: =IF(OR($M9="",$L9=""),"",$M9*$L9) | P9: =IF($O9="","",IFERROR(INDEX(Basis_of_Estimate!$C$5:$C$9,MATCH($O9,Basis_of_Estimate!$A$5:$A$9,0)),"")) | Q9: =IF($O9="","",IFERROR(INDEX(Basis_of_Estimate!$D$5:$D$9,MATCH($O9,Basis_of_Estimate!$A$5:$A$9,0)),"")) | R9: =IF($N9="","",$N9*(1+$P9)) | S9: =IF($N9="","",$N9) | T9: =IF($N9="","",$N9*(1+$Q9)) | U9: =IF($D9="","",IFERROR(INDEX(WBS_CBS!$M$5:$M$16,MATCH($D9,WBS_CBS!$A$5:$A$16,0)),"Yes")) | V9: =IF($D9="","",IFERROR(INDEX(WBS_CBS!$N$5:$N$16,MATCH($D9,WBS_CBS!$A$5:$A$16,0)),"Yes")) | W9: =IF($D9="","",IFERROR(INDEX(WBS_CBS!$K$5:$K$16,MATCH($D9,WBS_CBS!$A$5:$A$16,0)),"")) | X9: =IF($D9="","",IFERROR(INDEX(WBS_CBS!$F$5:$F$16,MATCH($D9,WBS_CBS!$A$5:$A$16,0)),"")) | AA9: =IF($D9="","",IFERROR(INDEX(WBS_CBS!$L$5:$L$16,MATCH($D9,WBS_CBS!$A$5:$A$16,0)),""))
C10: =IF($D10="","",IFERROR(INDEX(WBS_CBS!$E$5:$E$16,MATCH($D10,WBS_CBS!$A$5:$A$16,0)),"")) | E10: =IF($D10="","",IFERROR(INDEX(WBS_CBS!$C$5:$C$16,MATCH($D10,WBS_CBS!$A$5:$A$16,0)),"")) | F10: =IF($D10="","",IFERROR(INDEX(WBS_CBS!$J$5:$J$16,MATCH($D10,WBS_CBS!$A$5:$A$16,0)),"")) | L10: =IF($K10="","",IFERROR(INDEX(FX_Rates!$B$5:$B$14,MATCH($K10,FX_Rates!$A$5:$A$14,0)),"")) | M10: =IF(OR($H10="",$J10=""),"",$H10*$J10) | N10: =IF(OR($M10="",$L10=""),"",$M10*$L10) | P10: =IF($O10="","",IFERROR(INDEX(Basis_of_Estimate!$C$5:$C$9,MATCH($O10,Basis_of_Estimate!$A$5:$A$9,0)),"")) | Q10: =IF($O10="","",IFERROR(INDEX(Basis_of_Estimate!$D$5:$D$9,MATCH($O10,Basis_of_Estimate!$A$5:$A$9,0)),"")) | R10: =IF($N10="","",$N10*(1+$P10)) | S10: =IF($N10="","",$N10) | T10: =IF($N10="","",$N10*(1+$Q10)) | U10: =IF($D10="","",IFERROR(INDEX(WBS_CBS!$M$5:$M$16,MATCH($D10,WBS_CBS!$A$5:$A$16,0)),"Yes")) | V10: =IF($D10="","",IFERROR(INDEX(WBS_CBS!$N$5:$N$16,MATCH($D10,WBS_CBS!$A$5:$A$16,0)),"Yes")) | W10: =IF($D10="","",IFERROR(INDEX(WBS_CBS!$K$5:$K$16,MATCH($D10,WBS_CBS!$A$5:$A$16,0)),"")) | X10: =IF($D10="","",IFERROR(INDEX(WBS_CBS!$F$5:$F$16,MATCH($D10,WBS_CBS!$A$5:$A$16,0)),"")) | AA10: =IF($D10="","",IFERROR(INDEX(WBS_CBS!$L$5:$L$16,MATCH($D10,WBS_CBS!$A$5:$A$16,0)),""))
C11: =IF($D11="","",IFERROR(INDEX(WBS_CBS!$E$5:$E$16,MATCH($D11,WBS_CBS!$A$5:$A$16,0)),"")) | E11: =IF($D11="","",IFERROR(INDEX(WBS_CBS!$C$5:$C$16,MATCH($D11,WBS_CBS!$A$5:$A$16,0)),"")) | F11: =IF($D11="","",IFERROR(INDEX(WBS_CBS!$J$5:$J$16,MATCH($D11,WBS_CBS!$A$5:$A$16,0)),"")) | L11: =IF($K11="","",IFERROR(INDEX(FX_Rates!$B$5:$B$14,MATCH($K11,FX_Rates!$A$5:$A$14,0)),"")) | M11: =IF(OR($H11="",$J11=""),"",$H11*$J11) | N11: =IF(OR($M11="",$L11=""),"",$M11*$L11) | P11: =IF($O11="","",IFERROR(INDEX(Basis_of_Estimate!$C$5:$C$9,MATCH($O11,Basis_of_Estimate!$A$5:$A$9,0)),"")) | Q11: =IF($O11="","",IFERROR(INDEX(Basis_of_Estimate!$D$5:$D$9,MATCH($O11,Basis_of_Estimate!$A$5:$A$9,0)),"")) | R11: =IF($N11="","",$N11*(1+$P11)) | S11: =IF($N11="","",$N11) | T11: =IF($N11="","",$N11*(1+$Q11)) | U11: =IF($D11="","",IFERROR(INDEX(WBS_CBS!$M$5:$M$16,MATCH($D11,WBS_CBS!$A$5:$A$16,0)),"Yes")) | V11: =IF($D11="","",IFERROR(INDEX(WBS_CBS!$N$5:$N$16,MATCH($D11,WBS_CBS!$A$5:$A$16,0)),"Yes")) | W11: =IF($D11="","",IFERROR(INDEX(WBS_CBS!$K$5:$K$16,MATCH($D11,WBS_CBS!$A$5:$A$16,0)),"")) | X11: =IF($D11="","",IFERROR(INDEX(WBS_CBS!$F$5:$F$16,MATCH($D11,WBS_CBS!$A$5:$A$16,0)),"")) | AA11: =IF($D11="","",IFERROR(INDEX(WBS_CBS!$L$5:$L$16,MATCH($D11,WBS_CBS!$A$5:$A$16,0)),""))
C12: =IF($D12="","",IFERROR(INDEX(WBS_CBS!$E$5:$E$16,MATCH($D12,WBS_CBS!$A$5:$A$16,0)),"")) | E12: =IF($D12="","",IFERROR(INDEX(WBS_CBS!$C$5:$C$16,MATCH($D12,WBS_CBS!$A$5:$A$16,0)),"")) | F12: =IF($D12="","",IFERROR(INDEX(WBS_CBS!$J$5:$J$16,MATCH($D12,WBS_CBS!$A$5:$A$16,0)),"")) | L12: =IF($K12="","",IFERROR(INDEX(FX_Rates!$B$5:$B$14,MATCH($K12,FX_Rates!$A$5:$A$14,0)),"")) | M12: =IF(OR($H12="",$J12=""),"",$H12*$J12) | N12: =IF(OR($M12="",$L12=""),"",$M12*$L12) | P12: =IF($O12="","",IFERROR(INDEX(Basis_of_Estimate!$C$5:$C$9,MATCH($O12,Basis_of_Estimate!$A$5:$A$9,0)),"")) | Q12: =IF($O12="","",IFERROR(INDEX(Basis_of_Estimate!$D$5:$D$9,MATCH($O12,Basis_of_Estimate!$A$5:$A$9,0)),"")) | R12: =IF($N12="","",$N12*(1+$P12)) | S12: =IF($N12="","",$N12) | T12: =IF($N12="","",$N12*(1+$Q12)) | U12: =IF($D12="","",IFERROR(INDEX(WBS_CBS!$M$5:$M$16,MATCH($D12,WBS_CBS!$A$5:$A$16,0)),"Yes")) | V12: =IF($D12="","",IFERROR(INDEX(WBS_CBS!$N$5:$N$16,MATCH($D12,WBS_CBS!$A$5:$A$16,0)),"Yes")) | W12: =IF($D12="","",IFERROR(INDEX(WBS_CBS!$K$5:$K$16,MATCH($D12,WBS_CBS!$A$5:$A$16,0)),"")) | X12: =IF($D12="","",IFERROR(INDEX(WBS_CBS!$F$5:$F$16,MATCH($D12,WBS_CBS!$A$5:$A$16,0)),"")) | AA12: =IF($D12="","",IFERROR(INDEX(WBS_CBS!$L$5:$L$16,MATCH($D12,WBS_CBS!$A$5:$A$16,0)),""))
C13: =IF($D13="","",IFERROR(INDEX(WBS_CBS!$E$5:$E$16,MATCH($D13,WBS_CBS!$A$5:$A$16,0)),"")) | E13: =IF($D13="","",IFERROR(INDEX(WBS_CBS!$C$5:$C$16,MATCH($D13,WBS_CBS!$A$5:$A$16,0)),"")) | F13: =IF($D13="","",IFERROR(INDEX(WBS_CBS!$J$5:$J$16,MATCH($D13,WBS_CBS!$A$5:$A$16,0)),"")) | L13: =IF($K13="","",IFERROR(INDEX(FX_Rates!$B$5:$B$14,MATCH($K13,FX_Rates!$A$5:$A$14,0)),"")) | M13: =IF(OR($H13="",$J13=""),"",$H13*$J13) | N13: =IF(OR($M13="",$L13=""),"",$M13*$L13) | P13: =IF($O13="","",IFERROR(INDEX(Basis_of_Estimate!$C$5:$C$9,MATCH($O13,Basis_of_Estimate!$A$5:$A$9,0)),"")) | Q13: =IF($O13="","",IFERROR(INDEX(Basis_of_Estimate!$D$5:$D$9,MATCH($O13,Basis_of_Estimate!$A$5:$A$9,0)),"")) | R13: =IF($N13="","",$N13*(1+$P13)) | S13: =IF($N13="","",$N13) | T13: =IF($N13="","",$N13*(1+$Q13)) | U13: =IF($D13="","",IFERROR(INDEX(WBS_CBS!$M$5:$M$16,MATCH($D13,WBS_CBS!$A$5:$A$16,0)),"Yes")) | V13: =IF($D13="","",IFERROR(INDEX(WBS_CBS!$N$5:$N$16,MATCH($D13,WBS_CBS!$A$5:$A$16,0)),"Yes")) | W13: =IF($D13="","",IFERROR(INDEX(WBS_CBS!$K$5:$K$16,MATCH($D13,WBS_CBS!$A$5:$A$16,0)),"")) | X13: =IF($D13="","",IFERROR(INDEX(WBS_CBS!$F$5:$F$16,MATCH($D13,WBS_CBS!$A$5:$A$16,0)),"")) | AA13: =IF($D13="","",IFERROR(INDEX(WBS_CBS!$L$5:$L$16,MATCH($D13,WBS_CBS!$A$5:$A$16,0)),""))
C14: =IF($D14="","",IFERROR(INDEX(WBS_CBS!$E$5:$E$16,MATCH($D14,WBS_CBS!$A$5:$A$16,0)),"")) | E14: =IF($D14="","",IFERROR(INDEX(WBS_CBS!$C$5:$C$16,MATCH($D14,WBS_CBS!$A$5:$A$16,0)),"")) | F14: =IF($D14="","",IFERROR(INDEX(WBS_CBS!$J$5:$J$16,MATCH($D14,WBS_CBS!$A$5:$A$16,0)),"")) | L14: =IF($K14="","",IFERROR(INDEX(FX_Rates!$B$5:$B$14,MATCH($K14,FX_Rates!$A$5:$A$14,0)),"")) | M14: =IF(OR($H14="",$J14=""),"",$H14*$J14) | N14: =IF(OR($M14="",$L14=""),"",$M14*$L14) | P14: =IF($O14="","",IFERROR(INDEX(Basis_of_Estimate!$C$5:$C$9,MATCH($O14,Basis_of_Estimate!$A$5:$A$9,0)),"")) | Q14: =IF($O14="","",IFERROR(INDEX(Basis_of_Estimate!$D$5:$D$9,MATCH($O14,Basis_of_Estimate!$A$5:$A$9,0)),"")) | R14: =IF($N14="","",$N14*(1+$P14)) | S14: =IF($N14="","",$N14) | T14: =IF($N14="","",$N14*(1+$Q14)) | U14: =IF($D14="","",IFERROR(INDEX(WBS_CBS!$M$5:$M$16,MATCH($D14,WBS_CBS!$A$5:$A$16,0)),"Yes")) | V14: =IF($D14="","",IFERROR(INDEX(WBS_CBS!$N$5:$N$16,MATCH($D14,WBS_CBS!$A$5:$A$16,0)),"Yes")) | W14: =IF($D14="","",IFERROR(INDEX(WBS_CBS!$K$5:$K$16,MATCH($D14,WBS_CBS!$A$5:$A$16,0)),"")) | X14: =IF($D14="","",IFERROR(INDEX(WBS_CBS!$F$5:$F$16,MATCH($D14,WBS_CBS!$A$5:$A$16,0)),"")) | AA14: =IF($D14="","",IFERROR(INDEX(WBS_CBS!$L$5:$L$16,MATCH($D14,WBS_CBS!$A$5:$A$16,0)),""))
C15: =IF($D15="","",IFERROR(INDEX(WBS_CBS!$E$5:$E$16,MATCH($D15,WBS_CBS!$A$5:$A$16,0)),"")) | E15: =IF($D15="","",IFERROR(INDEX(WBS_CBS!$C$5:$C$16,MATCH($D15,WBS_CBS!$A$5:$A$16,0)),"")) | F15: =IF($D15="","",IFERROR(INDEX(WBS_CBS!$J$5:$J$16,MATCH($D15,WBS_CBS!$A$5:$A$16,0)),"")) | L15: =IF($K15="","",IFERROR(INDEX(FX_Rates!$B$5:$B$14,MATCH($K15,FX_Rates!$A$5:$A$14,0)),"")) | M15: =IF(OR($H15="",$J15=""),"",$H15*$J15) | N15: =IF(OR($M15="",$L15=""),"",$M15*$L15) | P15: =IF($O15="","",IFERROR(INDEX(Basis_of_Estimate!$C$5:$C$9,MATCH($O15,Basis_of_Estimate!$A$5:$A$9,0)),"")) | Q15: =IF($O15="","",IFERROR(INDEX(Basis_of_Estimate!$D$5:$D$9,MATCH($O15,Basis_of_Estimate!$A$5:$A$9,0)),"")) | R15: =IF($N15="","",$N15*(1+$P15)) | S15: =IF($N15="","",$N15) | T15: =IF($N15="","",$N15*(1+$Q15)) | U15: =IF($D15="","",IFERROR(INDEX(WBS_CBS!$M$5:$M$16,MATCH($D15,WBS_CBS!$A$5:$A$16,0)),"Yes")) | V15: =IF($D15="","",IFERROR(INDEX(WBS_CBS!$N$5:$N$16,MATCH($D15,WBS_CBS!$A$5:$A$16,0)),"Yes")) | W15: =IF($D15="","",IFERROR(INDEX(WBS_CBS!$K$5:$K$16,MATCH($D15,WBS_CBS!$A$5:$A$16,0)),"")) | X15: =IF($D15="","",IFERROR(INDEX(WBS_CBS!$F$5:$F$16,MATCH($D15,WBS_CBS!$A$5:$A$16,0)),"")) | AA15: =IF($D15="","",IFERROR(INDEX(WBS_CBS!$L$5:$L$16,MATCH($D15,WBS_CBS!$A$5:$A$16,0)),""))
C16: =IF($D16="","",IFERROR(INDEX(WBS_CBS!$E$5:$E$16,MATCH($D16,WBS_CBS!$A$5:$A$16,0)),"")) | E16: =IF($D16="","",IFERROR(INDEX(WBS_CBS!$C$5:$C$16,MATCH($D16,WBS_CBS!$A$5:$A$16,0)),"")) | F16: =IF($D16="","",IFERROR(INDEX(WBS_CBS!$J$5:$J$16,MATCH($D16,WBS_CBS!$A$5:$A$16,0)),"")) | L16: =IF($K16="","",IFERROR(INDEX(FX_Rates!$B$5:$B$14,MATCH($K16,FX_Rates!$A$5:$A$14,0)),"")) | M16: =IF(OR($H16="",$J16=""),"",$H16*$J16) | N16: =IF(OR($M16="",$L16=""),"",$M16*$L16) | P16: =IF($O16="","",IFERROR(INDEX(Basis_of_Estimate!$C$5:$C$9,MATCH($O16,Basis_of_Estimate!$A$5:$A$9,0)),"")) | Q16: =IF($O16="","",IFERROR(INDEX(Basis_of_Estimate!$D$5:$D$9,MATCH($O16,Basis_of_Estimate!$A$5:$A$9,0)),"")) | R16: =IF($N16="","",$N16*(1+$P16)) | S16: =IF($N16="","",$N16) | T16: =IF($N16="","",$N16*(1+$Q16)) | U16: =IF($D16="","",IFERROR(INDEX(WBS_CBS!$M$5:$M$16,MATCH($D16,WBS_CBS!$A$5:$A$16,0)),"Yes")) | V16: =IF($D16="","",IFERROR(INDEX(WBS_CBS!$N$5:$N$16,MATCH($D16,WBS_CBS!$A$5:$A$16,0)),"Yes")) | W16: =IF($D16="","",IFERROR(INDEX(WBS_CBS!$K$5:$K$16,MATCH($D16,WBS_CBS!$A$5:$A$16,0)),"")) | X16: =IF($D16="","",IFERROR(INDEX(WBS_CBS!$F$5:$F$16,MATCH($D16,WBS_CBS!$A$5:$A$16,0)),"")) | AA16: =IF($D16="","",IFERROR(INDEX(WBS_CBS!$L$5:$L$16,MATCH($D16,WBS_CBS!$A$5:$A$16,0)),""))
C17: =IF($D17="","",IFERROR(INDEX(WBS_CBS!$E$5:$E$16,MATCH($D17,WBS_CBS!$A$5:$A$16,0)),"")) | E17: =IF($D17="","",IFERROR(INDEX(WBS_CBS!$C$5:$C$16,MATCH($D17,WBS_CBS!$A$5:$A$16,0)),"")) | F17: =IF($D17="","",IFERROR(INDEX(WBS_CBS!$J$5:$J$16,MATCH($D17,WBS_CBS!$A$5:$A$16,0)),"")) | L17: =IF($K17="","",IFERROR(INDEX(FX_Rates!$B$5:$B$14,MATCH($K17,FX_Rates!$A$5:$A$14,0)),"")) | M17: =IF(OR($H17="",$J17=""),"",$H17*$J17) | N17: =IF(OR($M17="",$L17=""),"",$M17*$L17) | P17: =IF($O17="","",IFERROR(INDEX(Basis_of_Estimate!$C$5:$C$9,MATCH($O17,Basis_of_Estimate!$A$5:$A$9,0)),"")) | Q17: =IF($O17="","",IFERROR(INDEX(Basis_of_Estimate!$D$5:$D$9,MATCH($O17,Basis_of_Estimate!$A$5:$A$9,0)),"")) | R17: =IF($N17="","",$N17*(1+$P17)) | S17: =IF($N17="","",$N17) | T17: =IF($N17="","",$N17*(1+$Q17)) | U17: =IF($D17="","",IFERROR(INDEX(WBS_CBS!$M$5:$M$16,MATCH($D17,WBS_CBS!$A$5:$A$16,0)),"Yes")) | V17: =IF($D17="","",IFERROR(INDEX(WBS_CBS!$N$5:$N$16,MATCH($D17,WBS_CBS!$A$5:$A$16,0)),"Yes")) | W17: =IF($D17="","",IFERROR(INDEX(WBS_CBS!$K$5:$K$16,MATCH($D17,WBS_CBS!$A$5:$A$16,0)),"")) | X17: =IF($D17="","",IFERROR(INDEX(WBS_CBS!$F$5:$F$16,MATCH($D17,WBS_CBS!$A$5:$A$16,0)),"")) | AA17: =IF($D17="","",IFERROR(INDEX(WBS_CBS!$L$5:$L$16,MATCH($D17,WBS_CBS!$A$5:$A$16,0)),""))
C18: =IF($D18="","",IFERROR(INDEX(WBS_CBS!$E$5:$E$16,MATCH($D18,WBS_CBS!$A$5:$A$16,0)),"")) | E18: =IF($D18="","",IFERROR(INDEX(WBS_CBS!$C$5:$C$16,MATCH($D18,WBS_CBS!$A$5:$A$16,0)),"")) | F18: =IF($D18="","",IFERROR(INDEX(WBS_CBS!$J$5:$J$16,MATCH($D18,WBS_CBS!$A$5:$A$16,0)),"")) | L18: =IF($K18="","",IFERROR(INDEX(FX_Rates!$B$5:$B$14,MATCH($K18,FX_Rates!$A$5:$A$14,0)),"")) | M18: =IF(OR($H18="",$J18=""),"",$H18*$J18) | N18: =IF(OR($M18="",$L18=""),"",$M18*$L18) | P18: =IF($O18="","",IFERROR(INDEX(Basis_of_Estimate!$C$5:$C$9,MATCH($O18,Basis_of_Estimate!$A$5:$A$9,0)),"")) | Q18: =IF($O18="","",IFERROR(INDEX(Basis_of_Estimate!$D$5:$D$9,MATCH($O18,Basis_of_Estimate!$A$5:$A$9,0)),"")) | R18: =IF($N18="","",$N18*(1+$P18)) | S18: =IF($N18="","",$N18) | T18: =IF($N18="","",$N18*(1+$Q18)) | U18: =IF($D18="","",IFERROR(INDEX(WBS_CBS!$M$5:$M$16,MATCH($D18,WBS_CBS!$A$5:$A$16,0)),"Yes")) | V18: =IF($D18="","",IFERROR(INDEX(WBS_CBS!$N$5:$N$16,MATCH($D18,WBS_CBS!$A$5:$A$16,0)),"Yes")) | W18: =IF($D18="","",IFERROR(INDEX(WBS_CBS!$K$5:$K$16,MATCH($D18,WBS_CBS!$A$5:$A$16,0)),"")) | X18: =IF($D18="","",IFERROR(INDEX(WBS_CBS!$F$5:$F$16,MATCH($D18,WBS_CBS!$A$5:$A$16,0)),"")) | AA18: =IF($D18="","",IFERROR(INDEX(WBS_CBS!$L$5:$L$16,MATCH($D18,WBS_CBS!$A$5:$A$16,0)),""))
C19: =IF($D19="","",IFERROR(INDEX(WBS_CBS!$E$5:$E$16,MATCH($D19,WBS_CBS!$A$5:$A$16,0)),"")) | E19: =IF($D19="","",IFERROR(INDEX(WBS_CBS!$C$5:$C$16,MATCH($D19,WBS_CBS!$A$5:$A$16,0)),"")) | F19: =IF($D19="","",IFERROR(INDEX(WBS_CBS!$J$5:$J$16,MATCH($D19,WBS_CBS!$A$5:$A$16,0)),"")) | L19: =IF($K19="","",IFERROR(INDEX(FX_Rates!$B$5:$B$14,MATCH($K19,FX_Rates!$A$5:$A$14,0)),"")) | M19: =IF(OR($H19="",$J19=""),"",$H19*$J19) | N19: =IF(OR($M19="",$L19=""),"",$M19*$L19) | P19: =IF($O19="","",IFERROR(INDEX(Basis_of_Estimate!$C$5:$C$9,MATCH($O19,Basis_of_Estimate!$A$5:$A$9,0)),"")) | Q19: =IF($O19="","",IFERROR(INDEX(Basis_of_Estimate!$D$5:$D$9,MATCH($O19,Basis_of_Estimate!$A$5:$A$9,0)),"")) | R19: =IF($N19="","",$N19*(1+$P19)) | S19: =IF($N19="","",$N19) | T19: =IF($N19="","",$N19*(1+$Q19)) | U19: =IF($D19="","",IFERROR(INDEX(WBS_CBS!$M$5:$M$16,MATCH($D19,WBS_CBS!$A$5:$A$16,0)),"Yes")) | V19: =IF($D19="","",IFERROR(INDEX(WBS_CBS!$N$5:$N$16,MATCH($D19,WBS_CBS!$A$5:$A$16,0)),"Yes")) | W19: =IF($D19="","",IFERROR(INDEX(WBS_CBS!$K$5:$K$16,MATCH($D19,WBS_CBS!$A$5:$A$16,0)),"")) | X19: =IF($D19="","",IFERROR(INDEX(WBS_CBS!$F$5:$F$16,MATCH($D19,WBS_CBS!$A$5:$A$16,0)),"")) | AA19: =IF($D19="","",IFERROR(INDEX(WBS_CBS!$L$5:$L$16,MATCH($D19,WBS_CBS!$A$5:$A$16,0)),""))
C20: =IF($D20="","",IFERROR(INDEX(WBS_CBS!$E$5:$E$16,MATCH($D20,WBS_CBS!$A$5:$A$16,0)),"")) | E20: =IF($D20="","",IFERROR(INDEX(WBS_CBS!$C$5:$C$16,MATCH($D20,WBS_CBS!$A$5:$A$16,0)),"")) | F20: =IF($D20="","",IFERROR(INDEX(WBS_CBS!$J$5:$J$16,MATCH($D20,WBS_CBS!$A$5:$A$16,0)),"")) | L20: =IF($K20="","",IFERROR(INDEX(FX_Rates!$B$5:$B$14,MATCH($K20,FX_Rates!$A$5:$A$14,0)),"")) | M20: =IF(OR($H20="",$J20=""),"",$H20*$J20) | N20: =IF(OR($M20="",$L20=""),"",$M20*$L20) | P20: =IF($O20="","",IFERROR(INDEX(Basis_of_Estimate!$C$5:$C$9,MATCH($O20,Basis_of_Estimate!$A$5:$A$9,0)),"")) | Q20: =IF($O20="","",IFERROR(INDEX(Basis_of_Estimate!$D$5:$D$9,MATCH($O20,Basis_of_Estimate!$A$5:$A$9,0)),"")) | R20: =IF($N20="","",$N20*(1+$P20)) | S20: =IF($N20="","",$N20) | T20: =IF($N20="","",$N20*(1+$Q20)) | U20: =IF($D20="","",IFERROR(INDEX(WBS_CBS!$M$5:$M$16,MATCH($D20,WBS_CBS!$A$5:$A$16,0)),"Yes")) | V20: =IF($D20="","",IFERROR(INDEX(WBS_CBS!$N$5:$N$16,MATCH($D20,WBS_CBS!$A$5:$A$16,0)),"Yes")) | W20: =IF($D20="","",IFERROR(INDEX(WBS_CBS!$K$5:$K$16,MATCH($D20,WBS_CBS!$A$5:$A$16,0)),"")) | X20: =IF($D20="","",IFERROR(INDEX(WBS_CBS!$F$5:$F$16,MATCH($D20,WBS_CBS!$A$5:$A$16,0)),"")) | AA20: =IF($D20="","",IFERROR(INDEX(WBS_CBS!$L$5:$L$16,MATCH($D20,WBS_CBS!$A$5:$A$16,0)),""))
... C104: =IF($D104="","",IFERROR(INDEX(WBS_CBS!$E$5:$E$16,MATCH($D104,WBS_CBS!$A$5:$A$16,0)),"")) | E104: =IF($D104="","",IFERROR(INDEX(WBS_CBS!$C$5:$C$16,MATCH($D104,WBS_CBS!$A$5:$A$16,0)),"")) | F104: =IF($D104="","",IFERROR(INDEX(WBS_CBS!$J$5:$J$16,MATCH($D104,WBS_CBS!$A$5:$A$16,0)),"")) | L104: =IF($K104="","",IFERROR(INDEX(FX_Rates!$B$5:$B$14,MATCH($K104,FX_Rates!$A$5:$A$14,0)),"")) | M104: =IF(OR($H104="",$J104=""),"",$H104*$J104) | N104: =IF(OR($M104="",$L104=""),"",$M104*$L104) | P104: =IF($O104="","",IFERROR(INDEX(Basis_of_Estimate!$C$5:$C$9,MATCH($O104,Basis_of_Estimate!$A$5:$A$9,0)),"")) | Q104: =IF($O104="","",IFERROR(INDEX(Basis_of_Estimate!$D$5:$D$9,MATCH($O104,Basis_of_Estimate!$A$5:$A$9,0)),"")) | R104: =IF($N104="","",$N104*(1+$P104)) | S104: =IF($N104="","",$N104) | T104: =IF($N104="","",$N104*(1+$Q104)) | U104: =IF($D104="","",IFERROR(INDEX(WBS_CBS!$M$5:$M$16,MATCH($D104,WBS_CBS!$A$5:$A$16,0)),"Yes")) | V104: =IF($D104="","",IFERROR(INDEX(WBS_CBS!$N$5:$N$16,MATCH($D104,WBS_CBS!$A$5:$A$16,0)),"Yes")) | W104: =IF($D104="","",IFERROR(INDEX(WBS_CBS!$K$5:$K$16,MATCH($D104,WBS_CBS!$A$5:$A$16,0)),"")) | X104: =IF($D104="","",IFERROR(INDEX(WBS_CBS!$F$5:$F$16,MATCH($D104,WBS_CBS!$A$5:$A$16,0)),"")) | AA104: =IF($D104="","",IFERROR(INDEX(WBS_CBS!$L$5:$L$16,MATCH($D104,WBS_CBS!$A$5:$A$16,0)),""))

Sheet Other_Costs
A1: Other Costs
A2: User input layer. Cost_Register must be rebuilt from these sheets via BuildCostRegister.
A4: Item ID | B4: Description | C4: Discipline | D4: WBS | E4: CBS | F4: Cost Category | G4: Cost Type | H4: Quantity | I4: Unit | J4: Unit Rate | K4: Currency | L4: FX Rate | M4: Base Cost | N4: Base Cost EUR | O4: Estimate Basis | P4: Accuracy Low % | Q4: Accuracy High % | R4: Low Cost | S4: Most Likely Cost | T4: High Cost | U4: Contingency Eligible | V4: Escalation Eligible | W4: Spend Category | X4: Phase | Y4: Start Month | Z4: End Month | AA4: Spend Curve | AB4: Notes
A5: OT-001 | B5: Capital spares initial holding | C5: =IF($D5="","",IFERROR(INDEX(WBS_CBS!$E$5:$E$16,MATCH($D5,WBS_CBS!$A$5:$A$16,0)),"")) | D5: 12.0 | E5: =IF($D5="","",IFERROR(INDEX(WBS_CBS!$C$5:$C$16,MATCH($D5,WBS_CBS!$A$5:$A$16,0)),"")) | F5: =IF($D5="","",IFERROR(INDEX(WBS_CBS!$J$5:$J$16,MATCH($D5,WBS_CBS!$A$5:$A$16,0)),"")) | G5: Spares | H5: 1 | I5: lot | J5: 400000 | K5: EUR | L5: =IF($K5="","",IFERROR(INDEX(FX_Rates!$B$5:$B$14,MATCH($K5,FX_Rates!$A$5:$A$14,0)),"")) | M5: =IF(OR($H5="",$J5=""),"",$H5*$J5) | N5: =IF(OR($M5="",$L5=""),"",$M5*$L5) | O5: Class 3 | P5: =IF($O5="","",IFERROR(INDEX(Basis_of_Estimate!$C$5:$C$9,MATCH($O5,Basis_of_Estimate!$A$5:$A$9,0)),"")) | Q5: =IF($O5="","",IFERROR(INDEX(Basis_of_Estimate!$D$5:$D$9,MATCH($O5,Basis_of_Estimate!$A$5:$A$9,0)),"")) | R5: =IF($N5="","",$N5*(1+$P5)) | S5: =IF($N5="","",$N5) | T5: =IF($N5="","",$N5*(1+$Q5)) | U5: =IF($D5="","",IFERROR(INDEX(WBS_CBS!$M$5:$M$16,MATCH($D5,WBS_CBS!$A$5:$A$16,0)),"Yes")) | V5: =IF($D5="","",IFERROR(INDEX(WBS_CBS!$N$5:$N$16,MATCH($D5,WBS_CBS!$A$5:$A$16,0)),"Yes")) | W5: =IF($D5="","",IFERROR(INDEX(WBS_CBS!$K$5:$K$16,MATCH($D5,WBS_CBS!$A$5:$A$16,0)),"")) | X5: =IF($D5="","",IFERROR(INDEX(WBS_CBS!$F$5:$F$16,MATCH($D5,WBS_CBS!$A$5:$A$16,0)),"")) | Y5: 25 | Z5: 34 | AA5: =IF($D5="","",IFERROR(INDEX(WBS_CBS!$L$5:$L$16,MATCH($D5,WBS_CBS!$A$5:$A$16,0)),""))
A6: OT-002 | B6: Training and operational readiness | C6: =IF($D6="","",IFERROR(INDEX(WBS_CBS!$E$5:$E$16,MATCH($D6,WBS_CBS!$A$5:$A$16,0)),"")) | D6: 10.0 | E6: =IF($D6="","",IFERROR(INDEX(WBS_CBS!$C$5:$C$16,MATCH($D6,WBS_CBS!$A$5:$A$16,0)),"")) | F6: =IF($D6="","",IFERROR(INDEX(WBS_CBS!$J$5:$J$16,MATCH($D6,WBS_CBS!$A$5:$A$16,0)),"")) | G6: Other | H6: 1 | I6: lot | J6: 200000 | K6: EUR | L6: =IF($K6="","",IFERROR(INDEX(FX_Rates!$B$5:$B$14,MATCH($K6,FX_Rates!$A$5:$A$14,0)),"")) | M6: =IF(OR($H6="",$J6=""),"",$H6*$J6) | N6: =IF(OR($M6="",$L6=""),"",$M6*$L6) | O6: Class 3 | P6: =IF($O6="","",IFERROR(INDEX(Basis_of_Estimate!$C$5:$C$9,MATCH($O6,Basis_of_Estimate!$A$5:$A$9,0)),"")) | Q6: =IF($O6="","",IFERROR(INDEX(Basis_of_Estimate!$D$5:$D$9,MATCH($O6,Basis_of_Estimate!$A$5:$A$9,0)),"")) | R6: =IF($N6="","",$N6*(1+$P6)) | S6: =IF($N6="","",$N6) | T6: =IF($N6="","",$N6*(1+$Q6)) | U6: =IF($D6="","",IFERROR(INDEX(WBS_CBS!$M$5:$M$16,MATCH($D6,WBS_CBS!$A$5:$A$16,0)),"Yes")) | V6: =IF($D6="","",IFERROR(INDEX(WBS_CBS!$N$5:$N$16,MATCH($D6,WBS_CBS!$A$5:$A$16,0)),"Yes")) | W6: =IF($D6="","",IFERROR(INDEX(WBS_CBS!$K$5:$K$16,MATCH($D6,WBS_CBS!$A$5:$A$16,0)),"")) | X6: =IF($D6="","",IFERROR(INDEX(WBS_CBS!$F$5:$F$16,MATCH($D6,WBS_CBS!$A$5:$A$16,0)),"")) | Y6: 28 | Z6: 36 | AA6: =IF($D6="","",IFERROR(INDEX(WBS_CBS!$L$5:$L$16,MATCH($D6,WBS_CBS!$A$5:$A$16,0)),""))
A7: OT-003 | B7: Start-up consumables and temporary support | C7: =IF($D7="","",IFERROR(INDEX(WBS_CBS!$E$5:$E$16,MATCH($D7,WBS_CBS!$A$5:$A$16,0)),"")) | D7: 10.0 | E7: =IF($D7="","",IFERROR(INDEX(WBS_CBS!$C$5:$C$16,MATCH($D7,WBS_CBS!$A$5:$A$16,0)),"")) | F7: =IF($D7="","",IFERROR(INDEX(WBS_CBS!$J$5:$J$16,MATCH($D7,WBS_CBS!$A$5:$A$16,0)),"")) | G7: Other | H7: 1 | I7: lot | J7: 400000 | K7: EUR | L7: =IF($K7="","",IFERROR(INDEX(FX_Rates!$B$5:$B$14,MATCH($K7,FX_Rates!$A$5:$A$14,0)),"")) | M7: =IF(OR($H7="",$J7=""),"",$H7*$J7) | N7: =IF(OR($M7="",$L7=""),"",$M7*$L7) | O7: Class 3 | P7: =IF($O7="","",IFERROR(INDEX(Basis_of_Estimate!$C$5:$C$9,MATCH($O7,Basis_of_Estimate!$A$5:$A$9,0)),"")) | Q7: =IF($O7="","",IFERROR(INDEX(Basis_of_Estimate!$D$5:$D$9,MATCH($O7,Basis_of_Estimate!$A$5:$A$9,0)),"")) | R7: =IF($N7="","",$N7*(1+$P7)) | S7: =IF($N7="","",$N7) | T7: =IF($N7="","",$N7*(1+$Q7)) | U7: =IF($D7="","",IFERROR(INDEX(WBS_CBS!$M$5:$M$16,MATCH($D7,WBS_CBS!$A$5:$A$16,0)),"Yes")) | V7: =IF($D7="","",IFERROR(INDEX(WBS_CBS!$N$5:$N$16,MATCH($D7,WBS_CBS!$A$5:$A$16,0)),"Yes")) | W7: =IF($D7="","",IFERROR(INDEX(WBS_CBS!$K$5:$K$16,MATCH($D7,WBS_CBS!$A$5:$A$16,0)),"")) | X7: =IF($D7="","",IFERROR(INDEX(WBS_CBS!$F$5:$F$16,MATCH($D7,WBS_CBS!$A$5:$A$16,0)),"")) | Y7: 31 | Z7: 36 | AA7: =IF($D7="","",IFERROR(INDEX(WBS_CBS!$L$5:$L$16,MATCH($D7,WBS_CBS!$A$5:$A$16,0)),""))
C8: =IF($D8="","",IFERROR(INDEX(WBS_CBS!$E$5:$E$16,MATCH($D8,WBS_CBS!$A$5:$A$16,0)),"")) | E8: =IF($D8="","",IFERROR(INDEX(WBS_CBS!$C$5:$C$16,MATCH($D8,WBS_CBS!$A$5:$A$16,0)),"")) | F8: =IF($D8="","",IFERROR(INDEX(WBS_CBS!$J$5:$J$16,MATCH($D8,WBS_CBS!$A$5:$A$16,0)),"")) | L8: =IF($K8="","",IFERROR(INDEX(FX_Rates!$B$5:$B$14,MATCH($K8,FX_Rates!$A$5:$A$14,0)),"")) | M8: =IF(OR($H8="",$J8=""),"",$H8*$J8) | N8: =IF(OR($M8="",$L8=""),"",$M8*$L8) | P8: =IF($O8="","",IFERROR(INDEX(Basis_of_Estimate!$C$5:$C$9,MATCH($O8,Basis_of_Estimate!$A$5:$A$9,0)),"")) | Q8: =IF($O8="","",IFERROR(INDEX(Basis_of_Estimate!$D$5:$D$9,MATCH($O8,Basis_of_Estimate!$A$5:$A$9,0)),"")) | R8: =IF($N8="","",$N8*(1+$P8)) | S8: =IF($N8="","",$N8) | T8: =IF($N8="","",$N8*(1+$Q8)) | U8: =IF($D8="","",IFERROR(INDEX(WBS_CBS!$M$5:$M$16,MATCH($D8,WBS_CBS!$A$5:$A$16,0)),"Yes")) | V8: =IF($D8="","",IFERROR(INDEX(WBS_CBS!$N$5:$N$16,MATCH($D8,WBS_CBS!$A$5:$A$16,0)),"Yes")) | W8: =IF($D8="","",IFERROR(INDEX(WBS_CBS!$K$5:$K$16,MATCH($D8,WBS_CBS!$A$5:$A$16,0)),"")) | X8: =IF($D8="","",IFERROR(INDEX(WBS_CBS!$F$5:$F$16,MATCH($D8,WBS_CBS!$A$5:$A$16,0)),"")) | AA8: =IF($D8="","",IFERROR(INDEX(WBS_CBS!$L$5:$L$16,MATCH($D8,WBS_CBS!$A$5:$A$16,0)),""))
C9: =IF($D9="","",IFERROR(INDEX(WBS_CBS!$E$5:$E$16,MATCH($D9,WBS_CBS!$A$5:$A$16,0)),"")) | E9: =IF($D9="","",IFERROR(INDEX(WBS_CBS!$C$5:$C$16,MATCH($D9,WBS_CBS!$A$5:$A$16,0)),"")) | F9: =IF($D9="","",IFERROR(INDEX(WBS_CBS!$J$5:$J$16,MATCH($D9,WBS_CBS!$A$5:$A$16,0)),"")) | L9: =IF($K9="","",IFERROR(INDEX(FX_Rates!$B$5:$B$14,MATCH($K9,FX_Rates!$A$5:$A$14,0)),"")) | M9: =IF(OR($H9="",$J9=""),"",$H9*$J9) | N9: =IF(OR($M9="",$L9=""),"",$M9*$L9) | P9: =IF($O9="","",IFERROR(INDEX(Basis_of_Estimate!$C$5:$C$9,MATCH($O9,Basis_of_Estimate!$A$5:$A$9,0)),"")) | Q9: =IF($O9="","",IFERROR(INDEX(Basis_of_Estimate!$D$5:$D$9,MATCH($O9,Basis_of_Estimate!$A$5:$A$9,0)),"")) | R9: =IF($N9="","",$N9*(1+$P9)) | S9: =IF($N9="","",$N9) | T9: =IF($N9="","",$N9*(1+$Q9)) | U9: =IF($D9="","",IFERROR(INDEX(WBS_CBS!$M$5:$M$16,MATCH($D9,WBS_CBS!$A$5:$A$16,0)),"Yes")) | V9: =IF($D9="","",IFERROR(INDEX(WBS_CBS!$N$5:$N$16,MATCH($D9,WBS_CBS!$A$5:$A$16,0)),"Yes")) | W9: =IF($D9="","",IFERROR(INDEX(WBS_CBS!$K$5:$K$16,MATCH($D9,WBS_CBS!$A$5:$A$16,0)),"")) | X9: =IF($D9="","",IFERROR(INDEX(WBS_CBS!$F$5:$F$16,MATCH($D9,WBS_CBS!$A$5:$A$16,0)),"")) | AA9: =IF($D9="","",IFERROR(INDEX(WBS_CBS!$L$5:$L$16,MATCH($D9,WBS_CBS!$A$5:$A$16,0)),""))
C10: =IF($D10="","",IFERROR(INDEX(WBS_CBS!$E$5:$E$16,MATCH($D10,WBS_CBS!$A$5:$A$16,0)),"")) | E10: =IF($D10="","",IFERROR(INDEX(WBS_CBS!$C$5:$C$16,MATCH($D10,WBS_CBS!$A$5:$A$16,0)),"")) | F10: =IF($D10="","",IFERROR(INDEX(WBS_CBS!$J$5:$J$16,MATCH($D10,WBS_CBS!$A$5:$A$16,0)),"")) | L10: =IF($K10="","",IFERROR(INDEX(FX_Rates!$B$5:$B$14,MATCH($K10,FX_Rates!$A$5:$A$14,0)),"")) | M10: =IF(OR($H10="",$J10=""),"",$H10*$J10) | N10: =IF(OR($M10="",$L10=""),"",$M10*$L10) | P10: =IF($O10="","",IFERROR(INDEX(Basis_of_Estimate!$C$5:$C$9,MATCH($O10,Basis_of_Estimate!$A$5:$A$9,0)),"")) | Q10: =IF($O10="","",IFERROR(INDEX(Basis_of_Estimate!$D$5:$D$9,MATCH($O10,Basis_of_Estimate!$A$5:$A$9,0)),"")) | R10: =IF($N10="","",$N10*(1+$P10)) | S10: =IF($N10="","",$N10) | T10: =IF($N10="","",$N10*(1+$Q10)) | U10: =IF($D10="","",IFERROR(INDEX(WBS_CBS!$M$5:$M$16,MATCH($D10,WBS_CBS!$A$5:$A$16,0)),"Yes")) | V10: =IF($D10="","",IFERROR(INDEX(WBS_CBS!$N$5:$N$16,MATCH($D10,WBS_CBS!$A$5:$A$16,0)),"Yes")) | W10: =IF($D10="","",IFERROR(INDEX(WBS_CBS!$K$5:$K$16,MATCH($D10,WBS_CBS!$A$5:$A$16,0)),"")) | X10: =IF($D10="","",IFERROR(INDEX(WBS_CBS!$F$5:$F$16,MATCH($D10,WBS_CBS!$A$5:$A$16,0)),"")) | AA10: =IF($D10="","",IFERROR(INDEX(WBS_CBS!$L$5:$L$16,MATCH($D10,WBS_CBS!$A$5:$A$16,0)),""))
C11: =IF($D11="","",IFERROR(INDEX(WBS_CBS!$E$5:$E$16,MATCH($D11,WBS_CBS!$A$5:$A$16,0)),"")) | E11: =IF($D11="","",IFERROR(INDEX(WBS_CBS!$C$5:$C$16,MATCH($D11,WBS_CBS!$A$5:$A$16,0)),"")) | F11: =IF($D11="","",IFERROR(INDEX(WBS_CBS!$J$5:$J$16,MATCH($D11,WBS_CBS!$A$5:$A$16,0)),"")) | L11: =IF($K11="","",IFERROR(INDEX(FX_Rates!$B$5:$B$14,MATCH($K11,FX_Rates!$A$5:$A$14,0)),"")) | M11: =IF(OR($H11="",$J11=""),"",$H11*$J11) | N11: =IF(OR($M11="",$L11=""),"",$M11*$L11) | P11: =IF($O11="","",IFERROR(INDEX(Basis_of_Estimate!$C$5:$C$9,MATCH($O11,Basis_of_Estimate!$A$5:$A$9,0)),"")) | Q11: =IF($O11="","",IFERROR(INDEX(Basis_of_Estimate!$D$5:$D$9,MATCH($O11,Basis_of_Estimate!$A$5:$A$9,0)),"")) | R11: =IF($N11="","",$N11*(1+$P11)) | S11: =IF($N11="","",$N11) | T11: =IF($N11="","",$N11*(1+$Q11)) | U11: =IF($D11="","",IFERROR(INDEX(WBS_CBS!$M$5:$M$16,MATCH($D11,WBS_CBS!$A$5:$A$16,0)),"Yes")) | V11: =IF($D11="","",IFERROR(INDEX(WBS_CBS!$N$5:$N$16,MATCH($D11,WBS_CBS!$A$5:$A$16,0)),"Yes")) | W11: =IF($D11="","",IFERROR(INDEX(WBS_CBS!$K$5:$K$16,MATCH($D11,WBS_CBS!$A$5:$A$16,0)),"")) | X11: =IF($D11="","",IFERROR(INDEX(WBS_CBS!$F$5:$F$16,MATCH($D11,WBS_CBS!$A$5:$A$16,0)),"")) | AA11: =IF($D11="","",IFERROR(INDEX(WBS_CBS!$L$5:$L$16,MATCH($D11,WBS_CBS!$A$5:$A$16,0)),""))
C12: =IF($D12="","",IFERROR(INDEX(WBS_CBS!$E$5:$E$16,MATCH($D12,WBS_CBS!$A$5:$A$16,0)),"")) | E12: =IF($D12="","",IFERROR(INDEX(WBS_CBS!$C$5:$C$16,MATCH($D12,WBS_CBS!$A$5:$A$16,0)),"")) | F12: =IF($D12="","",IFERROR(INDEX(WBS_CBS!$J$5:$J$16,MATCH($D12,WBS_CBS!$A$5:$A$16,0)),"")) | L12: =IF($K12="","",IFERROR(INDEX(FX_Rates!$B$5:$B$14,MATCH($K12,FX_Rates!$A$5:$A$14,0)),"")) | M12: =IF(OR($H12="",$J12=""),"",$H12*$J12) | N12: =IF(OR($M12="",$L12=""),"",$M12*$L12) | P12: =IF($O12="","",IFERROR(INDEX(Basis_of_Estimate!$C$5:$C$9,MATCH($O12,Basis_of_Estimate!$A$5:$A$9,0)),"")) | Q12: =IF($O12="","",IFERROR(INDEX(Basis_of_Estimate!$D$5:$D$9,MATCH($O12,Basis_of_Estimate!$A$5:$A$9,0)),"")) | R12: =IF($N12="","",$N12*(1+$P12)) | S12: =IF($N12="","",$N12) | T12: =IF($N12="","",$N12*(1+$Q12)) | U12: =IF($D12="","",IFERROR(INDEX(WBS_CBS!$M$5:$M$16,MATCH($D12,WBS_CBS!$A$5:$A$16,0)),"Yes")) | V12: =IF($D12="","",IFERROR(INDEX(WBS_CBS!$N$5:$N$16,MATCH($D12,WBS_CBS!$A$5:$A$16,0)),"Yes")) | W12: =IF($D12="","",IFERROR(INDEX(WBS_CBS!$K$5:$K$16,MATCH($D12,WBS_CBS!$A$5:$A$16,0)),"")) | X12: =IF($D12="","",IFERROR(INDEX(WBS_CBS!$F$5:$F$16,MATCH($D12,WBS_CBS!$A$5:$A$16,0)),"")) | AA12: =IF($D12="","",IFERROR(INDEX(WBS_CBS!$L$5:$L$16,MATCH($D12,WBS_CBS!$A$5:$A$16,0)),""))
C13: =IF($D13="","",IFERROR(INDEX(WBS_CBS!$E$5:$E$16,MATCH($D13,WBS_CBS!$A$5:$A$16,0)),"")) | E13: =IF($D13="","",IFERROR(INDEX(WBS_CBS!$C$5:$C$16,MATCH($D13,WBS_CBS!$A$5:$A$16,0)),"")) | F13: =IF($D13="","",IFERROR(INDEX(WBS_CBS!$J$5:$J$16,MATCH($D13,WBS_CBS!$A$5:$A$16,0)),"")) | L13: =IF($K13="","",IFERROR(INDEX(FX_Rates!$B$5:$B$14,MATCH($K13,FX_Rates!$A$5:$A$14,0)),"")) | M13: =IF(OR($H13="",$J13=""),"",$H13*$J13) | N13: =IF(OR($M13="",$L13=""),"",$M13*$L13) | P13: =IF($O13="","",IFERROR(INDEX(Basis_of_Estimate!$C$5:$C$9,MATCH($O13,Basis_of_Estimate!$A$5:$A$9,0)),"")) | Q13: =IF($O13="","",IFERROR(INDEX(Basis_of_Estimate!$D$5:$D$9,MATCH($O13,Basis_of_Estimate!$A$5:$A$9,0)),"")) | R13: =IF($N13="","",$N13*(1+$P13)) | S13: =IF($N13="","",$N13) | T13: =IF($N13="","",$N13*(1+$Q13)) | U13: =IF($D13="","",IFERROR(INDEX(WBS_CBS!$M$5:$M$16,MATCH($D13,WBS_CBS!$A$5:$A$16,0)),"Yes")) | V13: =IF($D13="","",IFERROR(INDEX(WBS_CBS!$N$5:$N$16,MATCH($D13,WBS_CBS!$A$5:$A$16,0)),"Yes")) | W13: =IF($D13="","",IFERROR(INDEX(WBS_CBS!$K$5:$K$16,MATCH($D13,WBS_CBS!$A$5:$A$16,0)),"")) | X13: =IF($D13="","",IFERROR(INDEX(WBS_CBS!$F$5:$F$16,MATCH($D13,WBS_CBS!$A$5:$A$16,0)),"")) | AA13: =IF($D13="","",IFERROR(INDEX(WBS_CBS!$L$5:$L$16,MATCH($D13,WBS_CBS!$A$5:$A$16,0)),""))
C14: =IF($D14="","",IFERROR(INDEX(WBS_CBS!$E$5:$E$16,MATCH($D14,WBS_CBS!$A$5:$A$16,0)),"")) | E14: =IF($D14="","",IFERROR(INDEX(WBS_CBS!$C$5:$C$16,MATCH($D14,WBS_CBS!$A$5:$A$16,0)),"")) | F14: =IF($D14="","",IFERROR(INDEX(WBS_CBS!$J$5:$J$16,MATCH($D14,WBS_CBS!$A$5:$A$16,0)),"")) | L14: =IF($K14="","",IFERROR(INDEX(FX_Rates!$B$5:$B$14,MATCH($K14,FX_Rates!$A$5:$A$14,0)),"")) | M14: =IF(OR($H14="",$J14=""),"",$H14*$J14) | N14: =IF(OR($M14="",$L14=""),"",$M14*$L14) | P14: =IF($O14="","",IFERROR(INDEX(Basis_of_Estimate!$C$5:$C$9,MATCH($O14,Basis_of_Estimate!$A$5:$A$9,0)),"")) | Q14: =IF($O14="","",IFERROR(INDEX(Basis_of_Estimate!$D$5:$D$9,MATCH($O14,Basis_of_Estimate!$A$5:$A$9,0)),"")) | R14: =IF($N14="","",$N14*(1+$P14)) | S14: =IF($N14="","",$N14) | T14: =IF($N14="","",$N14*(1+$Q14)) | U14: =IF($D14="","",IFERROR(INDEX(WBS_CBS!$M$5:$M$16,MATCH($D14,WBS_CBS!$A$5:$A$16,0)),"Yes")) | V14: =IF($D14="","",IFERROR(INDEX(WBS_CBS!$N$5:$N$16,MATCH($D14,WBS_CBS!$A$5:$A$16,0)),"Yes")) | W14: =IF($D14="","",IFERROR(INDEX(WBS_CBS!$K$5:$K$16,MATCH($D14,WBS_CBS!$A$5:$A$16,0)),"")) | X14: =IF($D14="","",IFERROR(INDEX(WBS_CBS!$F$5:$F$16,MATCH($D14,WBS_CBS!$A$5:$A$16,0)),"")) | AA14: =IF($D14="","",IFERROR(INDEX(WBS_CBS!$L$5:$L$16,MATCH($D14,WBS_CBS!$A$5:$A$16,0)),""))
C15: =IF($D15="","",IFERROR(INDEX(WBS_CBS!$E$5:$E$16,MATCH($D15,WBS_CBS!$A$5:$A$16,0)),"")) | E15: =IF($D15="","",IFERROR(INDEX(WBS_CBS!$C$5:$C$16,MATCH($D15,WBS_CBS!$A$5:$A$16,0)),"")) | F15: =IF($D15="","",IFERROR(INDEX(WBS_CBS!$J$5:$J$16,MATCH($D15,WBS_CBS!$A$5:$A$16,0)),"")) | L15: =IF($K15="","",IFERROR(INDEX(FX_Rates!$B$5:$B$14,MATCH($K15,FX_Rates!$A$5:$A$14,0)),"")) | M15: =IF(OR($H15="",$J15=""),"",$H15*$J15) | N15: =IF(OR($M15="",$L15=""),"",$M15*$L15) | P15: =IF($O15="","",IFERROR(INDEX(Basis_of_Estimate!$C$5:$C$9,MATCH($O15,Basis_of_Estimate!$A$5:$A$9,0)),"")) | Q15: =IF($O15="","",IFERROR(INDEX(Basis_of_Estimate!$D$5:$D$9,MATCH($O15,Basis_of_Estimate!$A$5:$A$9,0)),"")) | R15: =IF($N15="","",$N15*(1+$P15)) | S15: =IF($N15="","",$N15) | T15: =IF($N15="","",$N15*(1+$Q15)) | U15: =IF($D15="","",IFERROR(INDEX(WBS_CBS!$M$5:$M$16,MATCH($D15,WBS_CBS!$A$5:$A$16,0)),"Yes")) | V15: =IF($D15="","",IFERROR(INDEX(WBS_CBS!$N$5:$N$16,MATCH($D15,WBS_CBS!$A$5:$A$16,0)),"Yes")) | W15: =IF($D15="","",IFERROR(INDEX(WBS_CBS!$K$5:$K$16,MATCH($D15,WBS_CBS!$A$5:$A$16,0)),"")) | X15: =IF($D15="","",IFERROR(INDEX(WBS_CBS!$F$5:$F$16,MATCH($D15,WBS_CBS!$A$5:$A$16,0)),"")) | AA15: =IF($D15="","",IFERROR(INDEX(WBS_CBS!$L$5:$L$16,MATCH($D15,WBS_CBS!$A$5:$A$16,0)),""))
C16: =IF($D16="","",IFERROR(INDEX(WBS_CBS!$E$5:$E$16,MATCH($D16,WBS_CBS!$A$5:$A$16,0)),"")) | E16: =IF($D16="","",IFERROR(INDEX(WBS_CBS!$C$5:$C$16,MATCH($D16,WBS_CBS!$A$5:$A$16,0)),"")) | F16: =IF($D16="","",IFERROR(INDEX(WBS_CBS!$J$5:$J$16,MATCH($D16,WBS_CBS!$A$5:$A$16,0)),"")) | L16: =IF($K16="","",IFERROR(INDEX(FX_Rates!$B$5:$B$14,MATCH($K16,FX_Rates!$A$5:$A$14,0)),"")) | M16: =IF(OR($H16="",$J16=""),"",$H16*$J16) | N16: =IF(OR($M16="",$L16=""),"",$M16*$L16) | P16: =IF($O16="","",IFERROR(INDEX(Basis_of_Estimate!$C$5:$C$9,MATCH($O16,Basis_of_Estimate!$A$5:$A$9,0)),"")) | Q16: =IF($O16="","",IFERROR(INDEX(Basis_of_Estimate!$D$5:$D$9,MATCH($O16,Basis_of_Estimate!$A$5:$A$9,0)),"")) | R16: =IF($N16="","",$N16*(1+$P16)) | S16: =IF($N16="","",$N16) | T16: =IF($N16="","",$N16*(1+$Q16)) | U16: =IF($D16="","",IFERROR(INDEX(WBS_CBS!$M$5:$M$16,MATCH($D16,WBS_CBS!$A$5:$A$16,0)),"Yes")) | V16: =IF($D16="","",IFERROR(INDEX(WBS_CBS!$N$5:$N$16,MATCH($D16,WBS_CBS!$A$5:$A$16,0)),"Yes")) | W16: =IF($D16="","",IFERROR(INDEX(WBS_CBS!$K$5:$K$16,MATCH($D16,WBS_CBS!$A$5:$A$16,0)),"")) | X16: =IF($D16="","",IFERROR(INDEX(WBS_CBS!$F$5:$F$16,MATCH($D16,WBS_CBS!$A$5:$A$16,0)),"")) | AA16: =IF($D16="","",IFERROR(INDEX(WBS_CBS!$L$5:$L$16,MATCH($D16,WBS_CBS!$A$5:$A$16,0)),""))
C17: =IF($D17="","",IFERROR(INDEX(WBS_CBS!$E$5:$E$16,MATCH($D17,WBS_CBS!$A$5:$A$16,0)),"")) | E17: =IF($D17="","",IFERROR(INDEX(WBS_CBS!$C$5:$C$16,MATCH($D17,WBS_CBS!$A$5:$A$16,0)),"")) | F17: =IF($D17="","",IFERROR(INDEX(WBS_CBS!$J$5:$J$16,MATCH($D17,WBS_CBS!$A$5:$A$16,0)),"")) | L17: =IF($K17="","",IFERROR(INDEX(FX_Rates!$B$5:$B$14,MATCH($K17,FX_Rates!$A$5:$A$14,0)),"")) | M17: =IF(OR($H17="",$J17=""),"",$H17*$J17) | N17: =IF(OR($M17="",$L17=""),"",$M17*$L17) | P17: =IF($O17="","",IFERROR(INDEX(Basis_of_Estimate!$C$5:$C$9,MATCH($O17,Basis_of_Estimate!$A$5:$A$9,0)),"")) | Q17: =IF($O17="","",IFERROR(INDEX(Basis_of_Estimate!$D$5:$D$9,MATCH($O17,Basis_of_Estimate!$A$5:$A$9,0)),"")) | R17: =IF($N17="","",$N17*(1+$P17)) | S17: =IF($N17="","",$N17) | T17: =IF($N17="","",$N17*(1+$Q17)) | U17: =IF($D17="","",IFERROR(INDEX(WBS_CBS!$M$5:$M$16,MATCH($D17,WBS_CBS!$A$5:$A$16,0)),"Yes")) | V17: =IF($D17="","",IFERROR(INDEX(WBS_CBS!$N$5:$N$16,MATCH($D17,WBS_CBS!$A$5:$A$16,0)),"Yes")) | W17: =IF($D17="","",IFERROR(INDEX(WBS_CBS!$K$5:$K$16,MATCH($D17,WBS_CBS!$A$5:$A$16,0)),"")) | X17: =IF($D17="","",IFERROR(INDEX(WBS_CBS!$F$5:$F$16,MATCH($D17,WBS_CBS!$A$5:$A$16,0)),"")) | AA17: =IF($D17="","",IFERROR(INDEX(WBS_CBS!$L$5:$L$16,MATCH($D17,WBS_CBS!$A$5:$A$16,0)),""))
C18: =IF($D18="","",IFERROR(INDEX(WBS_CBS!$E$5:$E$16,MATCH($D18,WBS_CBS!$A$5:$A$16,0)),"")) | E18: =IF($D18="","",IFERROR(INDEX(WBS_CBS!$C$5:$C$16,MATCH($D18,WBS_CBS!$A$5:$A$16,0)),"")) | F18: =IF($D18="","",IFERROR(INDEX(WBS_CBS!$J$5:$J$16,MATCH($D18,WBS_CBS!$A$5:$A$16,0)),"")) | L18: =IF($K18="","",IFERROR(INDEX(FX_Rates!$B$5:$B$14,MATCH($K18,FX_Rates!$A$5:$A$14,0)),"")) | M18: =IF(OR($H18="",$J18=""),"",$H18*$J18) | N18: =IF(OR($M18="",$L18=""),"",$M18*$L18) | P18: =IF($O18="","",IFERROR(INDEX(Basis_of_Estimate!$C$5:$C$9,MATCH($O18,Basis_of_Estimate!$A$5:$A$9,0)),"")) | Q18: =IF($O18="","",IFERROR(INDEX(Basis_of_Estimate!$D$5:$D$9,MATCH($O18,Basis_of_Estimate!$A$5:$A$9,0)),"")) | R18: =IF($N18="","",$N18*(1+$P18)) | S18: =IF($N18="","",$N18) | T18: =IF($N18="","",$N18*(1+$Q18)) | U18: =IF($D18="","",IFERROR(INDEX(WBS_CBS!$M$5:$M$16,MATCH($D18,WBS_CBS!$A$5:$A$16,0)),"Yes")) | V18: =IF($D18="","",IFERROR(INDEX(WBS_CBS!$N$5:$N$16,MATCH($D18,WBS_CBS!$A$5:$A$16,0)),"Yes")) | W18: =IF($D18="","",IFERROR(INDEX(WBS_CBS!$K$5:$K$16,MATCH($D18,WBS_CBS!$A$5:$A$16,0)),"")) | X18: =IF($D18="","",IFERROR(INDEX(WBS_CBS!$F$5:$F$16,MATCH($D18,WBS_CBS!$A$5:$A$16,0)),"")) | AA18: =IF($D18="","",IFERROR(INDEX(WBS_CBS!$L$5:$L$16,MATCH($D18,WBS_CBS!$A$5:$A$16,0)),""))
C19: =IF($D19="","",IFERROR(INDEX(WBS_CBS!$E$5:$E$16,MATCH($D19,WBS_CBS!$A$5:$A$16,0)),"")) | E19: =IF($D19="","",IFERROR(INDEX(WBS_CBS!$C$5:$C$16,MATCH($D19,WBS_CBS!$A$5:$A$16,0)),"")) | F19: =IF($D19="","",IFERROR(INDEX(WBS_CBS!$J$5:$J$16,MATCH($D19,WBS_CBS!$A$5:$A$16,0)),"")) | L19: =IF($K19="","",IFERROR(INDEX(FX_Rates!$B$5:$B$14,MATCH($K19,FX_Rates!$A$5:$A$14,0)),"")) | M19: =IF(OR($H19="",$J19=""),"",$H19*$J19) | N19: =IF(OR($M19="",$L19=""),"",$M19*$L19) | P19: =IF($O19="","",IFERROR(INDEX(Basis_of_Estimate!$C$5:$C$9,MATCH($O19,Basis_of_Estimate!$A$5:$A$9,0)),"")) | Q19: =IF($O19="","",IFERROR(INDEX(Basis_of_Estimate!$D$5:$D$9,MATCH($O19,Basis_of_Estimate!$A$5:$A$9,0)),"")) | R19: =IF($N19="","",$N19*(1+$P19)) | S19: =IF($N19="","",$N19) | T19: =IF($N19="","",$N19*(1+$Q19)) | U19: =IF($D19="","",IFERROR(INDEX(WBS_CBS!$M$5:$M$16,MATCH($D19,WBS_CBS!$A$5:$A$16,0)),"Yes")) | V19: =IF($D19="","",IFERROR(INDEX(WBS_CBS!$N$5:$N$16,MATCH($D19,WBS_CBS!$A$5:$A$16,0)),"Yes")) | W19: =IF($D19="","",IFERROR(INDEX(WBS_CBS!$K$5:$K$16,MATCH($D19,WBS_CBS!$A$5:$A$16,0)),"")) | X19: =IF($D19="","",IFERROR(INDEX(WBS_CBS!$F$5:$F$16,MATCH($D19,WBS_CBS!$A$5:$A$16,0)),"")) | AA19: =IF($D19="","",IFERROR(INDEX(WBS_CBS!$L$5:$L$16,MATCH($D19,WBS_CBS!$A$5:$A$16,0)),""))
... C104: =IF($D104="","",IFERROR(INDEX(WBS_CBS!$E$5:$E$16,MATCH($D104,WBS_CBS!$A$5:$A$16,0)),"")) | E104: =IF($D104="","",IFERROR(INDEX(WBS_CBS!$C$5:$C$16,MATCH($D104,WBS_CBS!$A$5:$A$16,0)),"")) | F104: =IF($D104="","",IFERROR(INDEX(WBS_CBS!$J$5:$J$16,MATCH($D104,WBS_CBS!$A$5:$A$16,0)),"")) | L104: =IF($K104="","",IFERROR(INDEX(FX_Rates!$B$5:$B$14,MATCH($K104,FX_Rates!$A$5:$A$14,0)),"")) | M104: =IF(OR($H104="",$J104=""),"",$H104*$J104) | N104: =IF(OR($M104="",$L104=""),"",$M104*$L104) | P104: =IF($O104="","",IFERROR(INDEX(Basis_of_Estimate!$C$5:$C$9,MATCH($O104,Basis_of_Estimate!$A$5:$A$9,0)),"")) | Q104: =IF($O104="","",IFERROR(INDEX(Basis_of_Estimate!$D$5:$D$9,MATCH($O104,Basis_of_Estimate!$A$5:$A$9,0)),"")) | R104: =IF($N104="","",$N104*(1+$P104)) | S104: =IF($N104="","",$N104) | T104: =IF($N104="","",$N104*(1+$Q104)) | U104: =IF($D104="","",IFERROR(INDEX(WBS_CBS!$M$5:$M$16,MATCH($D104,WBS_CBS!$A$5:$A$16,0)),"Yes")) | V104: =IF($D104="","",IFERROR(INDEX(WBS_CBS!$N$5:$N$16,MATCH($D104,WBS_CBS!$A$5:$A$16,0)),"Yes")) | W104: =IF($D104="","",IFERROR(INDEX(WBS_CBS!$K$5:$K$16,MATCH($D104,WBS_CBS!$A$5:$A$16,0)),"")) | X104: =IF($D104="","",IFERROR(INDEX(WBS_CBS!$F$5:$F$16,MATCH($D104,WBS_CBS!$A$5:$A$16,0)),"")) | AA104: =IF($D104="","",IFERROR(INDEX(WBS_CBS!$L$5:$L$16,MATCH($D104,WBS_CBS!$A$5:$A$16,0)),""))

Sheet Cost_Register
A1: Cost Register
A2: Normalized single source of truth. Populated by BuildCostRegister; demo rows pre-loaded.
A4: Source Sheet | B4: Source Row | C4: Item ID | D4: Description | E4: Discipline | F4: WBS | G4: CBS | H4: Cost Category | I4: Cost Type | J4: Quantity | K4: Unit | L4: Unit Rate | M4: Currency | N4: FX Rate | O4: Base Cost | P4: Base Cost EUR | Q4: Estimate Basis | R4: Accuracy Low % | S4: Accuracy High % | T4: Low Cost | U4: Most Likely Cost | V4: High Cost | W4: Contingency Eligible | X4: Escalation Eligible | Y4: Spend Category | Z4: Phase | AA4: Start Month | AB4: End Month | AC4: Spend Curve | AD4: Notes
A5: Equipment_Estimate | B5: 2 | C5: EQ-001 | D5: Process mixer package | E5: Mechanical | F5: 4.0 | G5: EQP | H5: Direct Cost | I5: Equipment | J5: 1 | K5: lot | L5: 2800000 | M5: EUR | N5: 1 | O5: 2800000 | P5: 2800000 | Q5: Class 3 | R5: -0.2 | S5: 0.3 | T5: 2240000 | U5: 2800000 | V5: 3640000 | W5: Yes | X5: Yes | Y5: Procurement | Z5: Procurement | AA5: 8 | AB5: 18 | AC5: Back Loaded
A6: Equipment_Estimate | B6: 3 | C6: EQ-002 | D6: Process vessels and tanks | E6: Mechanical | F6: 4.0 | G6: EQP | H6: Direct Cost | I6: Equipment | J6: 1 | K6: lot | L6: 3200000 | M6: EUR | N6: 1 | O6: 3200000 | P6: 3200000 | Q6: Class 3 | R6: -0.2 | S6: 0.3 | T6: 2560000 | U6: 3200000 | V6: 4160000 | W6: Yes | X6: Yes | Y6: Procurement | Z6: Procurement | AA6: 6 | AB6: 18 | AC6: Linear
A7: Equipment_Estimate | B7: 4 | C7: EQ-003 | D7: Pumping and transfer skids | E7: Mechanical | F7: 4.0 | G7: EQP | H7: Direct Cost | I7: Equipment | J7: 1 | K7: lot | L7: 2000000 | M7: EUR | N7: 1 | O7: 2000000 | P7: 2000000 | Q7: Class 3 | R7: -0.2 | S7: 0.3 | T7: 1600000 | U7: 2000000 | V7: 2600000 | W7: Yes | X7: Yes | Y7: Procurement | Z7: Procurement | AA7: 10 | AB7: 20 | AC7: Back Loaded
A8: Equipment_Estimate | B8: 5 | C8: EQ-004 | D8: Heat exchangers and utility skids | E8: Mechanical | F8: 4.0 | G8: EQP | H8: Direct Cost | I8: Equipment | J8: 1 | K8: lot | L8: 2400000 | M8: EUR | N8: 1 | O8: 2400000 | P8: 2400000 | Q8: Class 3 | R8: -0.2 | S8: 0.3 | T8: 1920000 | U8: 2400000 | V8: 3120000 | W8: Yes | X8: Yes | Y8: Procurement | Z8: Procurement | AA8: 9 | AB8: 21 | AC8: Back Loaded
A9: Equipment_Estimate | B9: 6 | C9: EQ-005 | D9: Equipment installation auxiliaries | E9: Mechanical | F9: 4.0 | G9: EQP | H9: Direct Cost | I9: Equipment | J9: 1 | K9: lot | L9: 1600000 | M9: EUR | N9: 1 | O9: 1600000 | P9: 1600000 | Q9: Class 3 | R9: -0.2 | S9: 0.3 | T9: 1280000 | U9: 1600000 | V9: 2080000 | W9: Yes | X9: Yes | Y9: Construction | Z9: Construction | AA9: 14 | AB9: 27 | AC9: Bell Curve
A10: Electrical_Estimate | B10: 2 | C10: EL-001 | D10: MV/LV substation package | E10: Electrical | F10: 7.0 | G10: ELE | H10: Direct Cost | I10: Equipment | J10: 1 | K10: lot | L10: 1400000 | M10: EUR | N10: 1 | O10: 1400000 | P10: 1400000 | Q10: Class 3 | R10: -0.2 | S10: 0.3 | T10: 1120000 | U10: 1400000 | V10: 1820000 | W10: Yes | X10: Yes | Y10: Procurement | Z10: Procurement | AA10: 8 | AB10: 18 | AC10: Back Loaded
A11: Electrical_Estimate | B11: 3 | C11: EL-002 | D11: MCC and distribution boards | E11: Electrical | F11: 7.0 | G11: ELE | H11: Direct Cost | I11: Equipment | J11: 1 | K11: lot | L11: 1200000 | M11: EUR | N11: 1 | O11: 1200000 | P11: 1200000 | Q11: Class 3 | R11: -0.2 | S11: 0.3 | T11: 960000 | U11: 1200000 | V11: 1560000 | W11: Yes | X11: Yes | Y11: Procurement | Z11: Procurement | AA11: 9 | AB11: 20 | AC11: Back Loaded
A12: Electrical_Estimate | B12: 4 | C12: EL-003 | D12: Cable trays, cabling and termination | E12: Electrical | F12: 7.0 | G12: ELE | H12: Direct Cost | I12: Bulk Material | J12: 1 | K12: lot | L12: 1600000 | M12: EUR | N12: 1 | O12: 1600000 | P12: 1600000 | Q12: Class 3 | R12: -0.2 | S12: 0.3 | T12: 1280000 | U12: 1600000 | V12: 2080000 | W12: Yes | X12: Yes | Y12: Construction | Z12: Construction | AA12: 15 | AB12: 30 | AC12: Linear
A13: Electrical_Estimate | B13: 5 | C13: EL-004 | D13: Lighting, earthing and small power | E13: Electrical | F13: 7.0 | G13: ELE | H13: Direct Cost | I13: Construction | J13: 1 | K13: lot | L13: 800000 | M13: EUR | N13: 1 | O13: 800000 | P13: 800000 | Q13: Class 3 | R13: -0.2 | S13: 0.3 | T13: 640000 | U13: 800000 | V13: 1040000 | W13: Yes | X13: Yes | Y13: Construction | Z13: Construction | AA13: 18 | AB13: 31 | AC13: Linear
A14: Instrumentation_Automation | B14: 2 | C14: IA-001 | D14: PLC/DCS hardware and software | E14: Automation | F14: 8.0 | G14: I&A | H14: Direct Cost | I14: Equipment | J14: 1 | K14: lot | L14: 1200000 | M14: EUR | N14: 1 | O14: 1200000 | P14: 1200000 | Q14: Class 3 | R14: -0.2 | S14: 0.3 | T14: 960000 | U14: 1200000 | V14: 1560000 | W14: Yes | X14: Yes | Y14: Procurement | Z14: Procurement | AA14: 8 | AB14: 22 | AC14: Back Loaded
A15: Instrumentation_Automation | B15: 3 | C15: IA-002 | D15: Field instrumentation and valves | E15: Instrumentation | F15: 8.0 | G15: I&A | H15: Direct Cost | I15: Equipment | J15: 1 | K15: lot | L15: 1000000 | M15: EUR | N15: 1 | O15: 1000000 | P15: 1000000 | Q15: Class 3 | R15: -0.2 | S15: 0.3 | T15: 800000 | U15: 1000000 | V15: 1300000 | W15: Yes | X15: Yes | Y15: Procurement | Z15: Procurement | AA15: 10 | AB15: 25 | AC15: Linear
A16: Instrumentation_Automation | B16: 4 | C16: IA-003 | D16: Automation engineering and commissioning | E16: Automation | F16: 8.0 | G16: I&A | H16: Direct Cost | I16: Engineering | J16: 1 | K16: lot | L16: 800000 | M16: EUR | N16: 1 | O16: 800000 | P16: 800000 | Q16: Class 3 | R16: -0.2 | S16: 0.3 | T16: 640000 | U16: 800000 | V16: 1040000 | W16: Yes | X16: Yes | Y16: Engineering | Z16: Engineering | AA16: 4 | AB16: 35 | AC16: Bell Curve
... A30: Other_Costs | B30: 4 | C30: OT-003 | D30: Start-up consumables and temporary support | E30: Owner | F30: 10.0 | G30: COM | H30: Other Cost | I30: Other | J30: 1 | K30: lot | L30: 400000 | M30: EUR | N30: 1 | O30: 400000 | P30: 400000 | Q30: Class 3 | R30: -0.2 | S30: 0.3 | T30: 320000 | U30: 400000 | V30: 520000 | W30: Yes | X30: Yes | Y30: Commissioning | Z30: Commissioning | AA30: 31 | AB30: 36 | AC30: Back Loaded
A31: Manpower_Plan | B31: 2 | C31: MP-001 | D31: Project Manager | E31: Project Management | F31: 1.0 | G31: ENG | H31: Manpower Cost | I31: Labour | J31: 1 | K31: lot | L31: 645962.73 | M31: EUR | N31: 1 | O31: 645962.73 | P31: 645962.73 | Q31: Class 3 | R31: -0.2 | S31: 0.3 | T31: 516770.19 | U31: 645962.73 | V31: 839751.55 | W31: Yes | X31: Yes | Y31: Engineering | Z31: Engineering | AA31: 1 | AB31: 36 | AC31: Bell Curve | AD31: Generated from Resource_Rates and Manpower_Plan profile. FTE scaled to fit 40M demo.
A32: Manpower_Plan | B32: 3 | C32: MP-002 | D32: Engineering Manager | E32: Project Management | F32: 1.0 | G32: ENG | H32: Manpower Cost | I32: Labour | J32: 1 | K32: lot | L32: 417391.3 | M32: EUR | N32: 1 | O32: 417391.3 | P32: 417391.3 | Q32: Class 3 | R32: -0.2 | S32: 0.3 | T32: 333913.04 | U32: 417391.3 | V32: 542608.7 | W32: Yes | X32: Yes | Y32: Engineering | Z32: Engineering | AA32: 1 | AB32: 36 | AC32: Bell Curve | AD32: Generated from Resource_Rates and Manpower_Plan profile. FTE scaled to fit 40M demo.
A33: Manpower_Plan | B33: 4 | C33: MP-003 | D33: Project Controls Lead | E33: Project Management | F33: 2.0 | G33: ENG | H33: Manpower Cost | I33: Labour | J33: 1 | K33: lot | L33: 472049.69 | M33: EUR | N33: 1 | O33: 472049.69 | P33: 472049.69 | Q33: Class 3 | R33: -0.2 | S33: 0.3 | T33: 377639.75 | U33: 472049.69 | V33: 613664.6 | W33: Yes | X33: Yes | Y33: Engineering | Z33: Engineering | AA33: 1 | AB33: 36 | AC33: Bell Curve | AD33: Generated from Resource_Rates and Manpower_Plan profile. FTE scaled to fit 40M demo.
A34: Manpower_Plan | B34: 5 | C34: MP-004 | D34: Cost Estimator | E34: Project Management | F34: 2.0 | G34: ENG | H34: Manpower Cost | I34: Labour | J34: 1 | K34: lot | L34: 173913.04 | M34: EUR | N34: 1 | O34: 173913.04 | P34: 173913.04 | Q34: Class 3 | R34: -0.2 | S34: 0.3 | T34: 139130.43 | U34: 173913.04 | V34: 226086.96 | W34: Yes | X34: Yes | Y34: Engineering | Z34: Engineering | AA34: 1 | AB34: 36 | AC34: Bell Curve | AD34: Generated from Resource_Rates and Manpower_Plan profile. FTE scaled to fit 40M demo.
A35: Manpower_Plan | B35: 6 | C35: MP-005 | D35: Planner / Scheduler | E35: Project Management | F35: 2.0 | G35: ENG | H35: Manpower Cost | I35: Labour | J35: 1 | K35: lot | L35: 337888.2 | M35: EUR | N35: 1 | O35: 337888.2 | P35: 337888.2 | Q35: Class 3 | R35: -0.2 | S35: 0.3 | T35: 270310.56 | U35: 337888.2 | V35: 439254.66 | W35: Yes | X35: Yes | Y35: Engineering | Z35: Engineering | AA35: 1 | AB35: 36 | AC35: Bell Curve | AD35: Generated from Resource_Rates and Manpower_Plan profile. FTE scaled to fit 40M demo.
A36: Manpower_Plan | B36: 7 | C36: MP-006 | D36: Process Engineer | E36: Process | F36: 2.0 | G36: ENG | H36: Manpower Cost | I36: Labour | J36: 1 | K36: lot | L36: 782608.7 | M36: EUR | N36: 1 | O36: 782608.7 | P36: 782608.7 | Q36: Class 3 | R36: -0.2 | S36: 0.3 | T36: 626086.96 | U36: 782608.7 | V36: 1017391.3 | W36: Yes | X36: Yes | Y36: Engineering | Z36: Engineering | AA36: 1 | AB36: 36 | AC36: Bell Curve | AD36: Generated from Resource_Rates and Manpower_Plan profile. FTE scaled to fit 40M demo.
A37: Manpower_Plan | B37: 8 | C37: MP-007 | D37: Procurement Lead | E37: Procurement | F37: 2.0 | G37: ENG | H37: Manpower Cost | I37: Labour | J37: 1 | K37: lot | L37: 305590.06 | M37: EUR | N37: 1 | O37: 305590.06 | P37: 305590.06 | Q37: Class 3 | R37: -0.2 | S37: 0.3 | T37: 244472.05 | U37: 305590.06 | V37: 397267.08 | W37: Yes | X37: Yes | Y37: Engineering | Z37: Engineering | AA37: 1 | AB37: 36 | AC37: Bell Curve | AD37: Generated from Resource_Rates and Manpower_Plan profile. FTE scaled to fit 40M demo.
A38: Manpower_Plan | B38: 9 | C38: MP-008 | D38: Construction Manager | E38: Construction | F38: 9.0 | G38: CON | H38: Manpower Cost | I38: Labour | J38: 1 | K38: lot | L38: 317460.32 | M38: EUR | N38: 1 | O38: 317460.32 | P38: 317460.32 | Q38: Class 3 | R38: -0.2 | S38: 0.3 | T38: 253968.25 | U38: 317460.32 | V38: 412698.41 | W38: Yes | X38: Yes | Y38: Construction | Z38: Construction | AA38: 1 | AB38: 36 | AC38: Bell Curve | AD38: Generated from Resource_Rates and Manpower_Plan profile. FTE scaled to fit 40M demo.
A39: Manpower_Plan | B39: 10 | C39: MP-009 | D39: HSE Manager | E39: HSE | F39: 9.0 | G39: CON | H39: Manpower Cost | I39: Labour | J39: 1 | K39: lot | L39: 215873.02 | M39: EUR | N39: 1 | O39: 215873.02 | P39: 215873.02 | Q39: Class 3 | R39: -0.2 | S39: 0.3 | T39: 172698.41 | U39: 215873.02 | V39: 280634.92 | W39: Yes | X39: Yes | Y39: Construction | Z39: Construction | AA39: 1 | AB39: 36 | AC39: Bell Curve | AD39: Generated from Resource_Rates and Manpower_Plan profile. FTE scaled to fit 40M demo.
A40: Manpower_Plan | B40: 11 | C40: MP-010 | D40: Commissioning Lead | E40: Commissioning | F40: 10.0 | G40: COM | H40: Manpower Cost | I40: Labour | J40: 1 | K40: lot | L40: 182194.62 | M40: EUR | N40: 1 | O40: 182194.62 | P40: 182194.62 | Q40: Class 3 | R40: -0.2 | S40: 0.3 | T40: 145755.69 | U40: 182194.62 | V40: 236853 | W40: Yes | X40: Yes | Y40: Commissioning | Z40: Commissioning | AA40: 1 | AB40: 36 | AC40: Bell Curve | AD40: Generated from Resource_Rates and Manpower_Plan profile. FTE scaled to fit 40M demo.
A41: Manpower_Plan | B41: 12 | C41: MP-011 | D41: Document Controller | E41: Project Management | F41: 2.0 | G41: ENG | H41: Manpower Cost | I41: Labour | J41: 1 | K41: lot | L41: 149068.32 | M41: EUR | N41: 1 | O41: 149068.32 | P41: 149068.32 | Q41: Class 3 | R41: -0.2 | S41: 0.3 | T41: 119254.66 | U41: 149068.32 | V41: 193788.82 | W41: Yes | X41: Yes | Y41: Engineering | Z41: Engineering | AA41: 1 | AB41: 36 | AC41: Bell Curve | AD41: Generated from Resource_Rates and Manpower_Plan profile. FTE scaled to fit 40M demo.

Sheet Estimate_BuildUp
A1: Estimate BuildUp
A2: Aggregations by category, discipline, WBS, phase and eligibility. Reconciles to Cost_Register.
A4: Breakdown Type | B4: Breakdown | C4: Base Cost EUR | D4: Low Cost EUR | E4: Most Likely EUR | F4: High Cost EUR | G4: % of Base | H4: Notes
A5: Cost Category | B5: Direct Cost | C5: =IF($A5="Cost Category",SUMIFS(Cost_Register!$P:$P,Cost_Register!$H:$H,$B5),IF($A5="Discipline",SUMIFS(Cost_Register!$P:$P,Cost_Register!$E:$E,$B5),IF($A5="WBS",SUMIFS(Cost_Register!$P:$P,Cost_Register!$F:$F,$B5),IF($A5="Phase",SUMIFS(Cost_Register!$P:$P,Cost_Register!$Z:$Z,$B5),IF($A5="Contingency Eligible",SUMIFS(Cost_Register!$P:$P,Cost_Register!$W:$W,$B5),IF($A5="Escalation Eligible",SUMIFS(Cost_Register!$P:$P,Cost_Register!$X:$X,$B5),0)))))) | D5: =IF($A5="Cost Category",SUMIFS(Cost_Register!$T:$T,Cost_Register!$H:$H,$B5),IF($A5="Discipline",SUMIFS(Cost_Register!$T:$T,Cost_Register!$E:$E,$B5),IF($A5="WBS",SUMIFS(Cost_Register!$T:$T,Cost_Register!$F:$F,$B5),IF($A5="Phase",SUMIFS(Cost_Register!$T:$T,Cost_Register!$Z:$Z,$B5),IF($A5="Contingency Eligible",SUMIFS(Cost_Register!$T:$T,Cost_Register!$W:$W,$B5),IF($A5="Escalation Eligible",SUMIFS(Cost_Register!$T:$T,Cost_Register!$X:$X,$B5),0)))))) | E5: =IF($A5="Cost Category",SUMIFS(Cost_Register!$U:$U,Cost_Register!$H:$H,$B5),IF($A5="Discipline",SUMIFS(Cost_Register!$U:$U,Cost_Register!$E:$E,$B5),IF($A5="WBS",SUMIFS(Cost_Register!$U:$U,Cost_Register!$F:$F,$B5),IF($A5="Phase",SUMIFS(Cost_Register!$U:$U,Cost_Register!$Z:$Z,$B5),IF($A5="Contingency Eligible",SUMIFS(Cost_Register!$U:$U,Cost_Register!$W:$W,$B5),IF($A5="Escalation Eligible",SUMIFS(Cost_Register!$U:$U,Cost_Register!$X:$X,$B5),0)))))) | F5: =IF($A5="Cost Category",SUMIFS(Cost_Register!$V:$V,Cost_Register!$H:$H,$B5),IF($A5="Discipline",SUMIFS(Cost_Register!$V:$V,Cost_Register!$E:$E,$B5),IF($A5="WBS",SUMIFS(Cost_Register!$V:$V,Cost_Register!$F:$F,$B5),IF($A5="Phase",SUMIFS(Cost_Register!$V:$V,Cost_Register!$Z:$Z,$B5),IF($A5="Contingency Eligible",SUMIFS(Cost_Register!$V:$V,Cost_Register!$W:$W,$B5),IF($A5="Escalation Eligible",SUMIFS(Cost_Register!$V:$V,Cost_Register!$X:$X,$B5),0)))))) | G5: =IFERROR(C5/SUM(Cost_Register!$P:$P),0) | H5: Formula-driven aggregation
